Workbook

Sheet Summary
A1: Teman Journey - 2027 plan (v16): EAP as the channel, BI kept as a premium client, new school channel
A2: Goal for 2027: a business that is profitable on its own and pays both founders. Investors come later, after scale. All money in Rp million.
A3: Active scenario: | B3: =CHOOSE(Inputs!$C$6,"1. Base plan","2. No new B2B deal Jan-Jun 2027","3. BI cuts volume","4. Worst case (2 + 3)") -> 1. Base plan
A4: Active price plan: | B4: =CHOOSE(Inputs!$C$85,"1. Current prices","2. New rate card") -> 2. New rate card
A5: Question | B5: Answer | C5: Unit | D5: What it means
A6: A. Is 2027 profitable?
A7: Revenue FY 2027 | B7: =PnL!$D$12 -> 2432.5546 | C7: Rp m | D7: Total sales booked in 2027.
A8: Gross profit FY 2027 | B8: =PnL!$D$23 -> 1451.7137 | C8: Rp m | D8: Revenue minus delivery cost.
A9: Total fixed cost FY 2027 | B9: =PnL!$D$31 -> 882.92578 | C9: Rp m | D9: Base + founders + sales + delivery steps.
A10: of which founder salaries | B10: =PnL!$D$28 -> 270 | C10: Rp m | D10: Both founders, from the start month in Inputs.
A11: Net profit FY 2027 | B11: =PnL!$D$35 -> 556.6252 | C11: Rp m | D11: After founder salaries and tax.
A12: Net margin FY 2027 | B12: =PnL!$D$36 -> 0.22882331 | C12: % | D12: Net profit / revenue.
A13: Meets your target margin? | B13: =IF(PnL!$D$36>=Inputs!$C$82,"Yes","No") -> Yes | D13: Target is set in Inputs.
A14: Break-even: BI work needed per month (in KPW-event equivalents) | B14: =IF(Unit_Economics!$G$5<=0,0,(PnL!$D$31/12-(PnL!$D$23-PnL!$D$6-PnL!$D$7+PnL!$D$15+PnL!$D$16)/12)/Unit_Economics!$G$5) -> 0.46329694 | C14: events | D14: With banks, EAP and B2C at plan, this many KPW-size BI events a month (or the same profit from Flagships) covers all 2027 fixed costs.
A15: B. Is cash safe? (Pillar 3)
A16: Lowest month-end cash (Oct 26 - Dec 27) | B16: =MIN(CashFlow!$E$21:$S$21) -> 69.760296 | C16: Rp m | D16: Must stay above zero.
A17: Month of lowest cash | B17: =INDEX(Volume!$E$4:$S$4,MATCH(MIN(CashFlow!$E$21:$S$21),CashFlow!$E$21:$S$21,0)) -> Feb-27 | D17: Where the squeeze is.
A18: Months below the cash floor | B18: =COUNTIF(CashFlow!$E$25:$S$25,0) -> 5 | C18: months | D18: Floor = 1 month fixed cost + delivery cost.
A19: Cash at end of 2027 | B19: =CashFlow!$D$21 -> 541.81498 | C19: Rp m
A20: Peak money owed by clients | B20: =CashFlow!$D$26 -> 237.69875 | C20: Rp m | D20: Cash tied up in unpaid invoices.
A21: Runway at end of Dec 2026 if B2B stops | B21: =CashFlow!$G$21/(Capacity_OPEX!$H$32-((PnL!$D$10+PnL!$D$11-PnL!$D$19-PnL!$D$20)/12)) -> 3.3346773 | C21: months | D21: Months you survive on B2C alone with 2027 cost base.
A22: C. Can we deliver it? (Pillar 2)
A23: Peak facilitators needed in one month | B23: =Capacity_OPEX!$D$8 -> 9 | C23: people | D23: Compare with your plan of 11.
A24: Facilitators to certify by end 2027 | B24: =Capacity_OPEX!$D$9-Inputs!$C$35 -> 7 | C24: people
A25: Month the Project Manager is hired | B25: =IFERROR(INDEX(Volume!$E$4:$S$4,MATCH(1,Capacity_OPEX!$E$15:$S$15,0)),"Not needed") -> Dec-27 | D25: Triggered by the 3-month average of B2B events.
A26: D. What will investors ask? (risk)
A27: BI share of 2027 revenue | B27: =PnL!$D$41 -> 0.55690549 | C27: % | D27: Concentration risk. Lower is safer.
A28: B2B share of 2027 revenue | B28: =IF(PnL!$D$12=0,0,PnL!$D$42/PnL!$D$12) -> 0.93451881 | C28: %
A29: Q4 share of 2027 revenue | B29: =IF(PnL!$D$12=0,0,SUM(PnL!Q12:S12)/PnL!$D$12) -> 0.42631613 | C29: % | D29: Seasonality risk.
A30: Cost to win one new B2B client (CAC) | B30: =Unit_Economics!$B$13 -> 6 | C30: Rp m | D30: Sales spend / new clients.
A31: Memo: Coreitera revenue from TJ in 2027 | B31: =PnL!$D$43 -> 89.25 | C31: Rp m | D31: The 'tech' revenue line for the investor story.
A32: Memo: Theta revenue from TJ in 2027 | B32: =PnL!$D$44 -> 44.772326 | C32: Rp m
A34: Scenario comparison (v16 values; refresh with analysis/lo_runner.py, then rebuild)
A35: Measure | B35: v15 plan (check) | C35: v16 plan | D35: v16 recommended (new prices + cash guard) | E35: v16 conservative | F35: v16 aggressive
A36: Revenue FY 2027 | B36: 2039.9735 | C36: 2432.5546 | D36: 2451.4196 | E36: 1738.751 | F36: 3300.0779
A37: Net profit FY 2027 | B37: 532.20857 | C37: 556.6252 | D37: 612.39587 | E37: 235.93773 | F37: 982.83707
A38: Net margin FY 2027 | B38: 0.26088994 | C38: 0.22882331 | D38: 0.24981275 | E38: 0.1356938 | F38: 0.29782239
A39: Lowest month-end cash (Oct 26 - Dec 27) | B39: 82.489448 | C39: 69.760296 | D39: 106.75957 | E39: 55.370504 | F39: 69.209735
A40: Month of lowest cash | B40: Feb-27 | C40: Feb-27 | D40: Jan-27 | E40: Apr-27 | F40: Feb-27
A41: Months below the cash floor | B41: 1 | C41: 5 | D41: 1 | E41: 7 | F41: 5
A42: Cash at end of 2027 | B42: 523.85587 | C42: 541.81498 | D42: 598.2655 | E42: 290.33012 | F42: 907.04916
A44: E. Where the money comes from (v16 targets, Segments sheet)
A45: EAP channel share of 2027 revenue | B45: =Segments!D14 -> 0.23547694 | C45: % | D45: Primary target.
A46: BI BAU share of 2027 revenue | B46: =Segments!D15 -> 0.44883885 | C46: % | D46: Kept at today's volume.
A47: LPS / OJK share | B47: =Segments!D16 -> 0.0537768 | C47: % | D47: Secondary.
A48: Banks share | B48: =Segments!D17 -> 0.15395338 | C48: % | D48: Tertiary.
A49: Schools share | B49: =Segments!D18 -> 0.059197028 | C49: % | D49: New.
A50: B2C direct share | B50: =Segments!D19 -> 0.048757002 | C50: % | D50: Instagram, referral, events.
A51: All money from BI (incl. KPw packages) | B51: =Segments!D21 -> 0.55690549 | C51: % | D51: Concentration: lower is safer.

Sheet Outlook
A1: Outlook: sales, costs and cash each month (Rp million)
A2: Read the bars against the line: when the grey cost bar is taller than the blue sales bar, cash goes down. Cash is paid later than sales, because clients pay 0 to 60 days after the event.
A4: Month | B4: =Volume!E4 -> Oct-26 | C4: =Volume!F4 -> Nov-26 | D4: =Volume!G4 -> Dec-26 | E4: =Volume!H4 -> Jan-27 | F4: =Volume!I4 -> Feb-27 | G4: =Volume!J4 -> Mar-27 | H4: =Volume!K4 -> Apr-27 | I4: =Volume!L4 -> May-27 | ... P4: =Volume!S4 -> Dec-27
A5: Sales (revenue) | B5: =PnL!E12 -> 20.428617 | C5: =PnL!F12 -> 22.032105 | D5: =PnL!G12 -> 22.096289 | E5: =PnL!H12 -> 22.808889 | F5: =PnL!I12 -> 71.830236 | G5: =PnL!J12 -> 175.59012 | H5: =PnL!K12 -> 110.16744 | I5: =PnL!L12 -> 199.75153 | ... P5: =PnL!S12 -> 303.27404
A6: Delivery cost | B6: =PnL!E21 -> 8.6621793 | C6: =PnL!F21 -> 10.498458 | D6: =PnL!G21 -> 10.465034 | E6: =PnL!H21 -> 10.98213 | F6: =PnL!I21 -> 38.071621 | G6: =PnL!J21 -> 61.577273 | H6: =PnL!K21 -> 45.592659 | I6: =PnL!L21 -> 74.210092 | ... P6: =PnL!S21 -> 121.59837
A7: Fixed cost | B7: =PnL!E31 -> 31.685442 | C7: =PnL!F31 -> 32.474586 | D7: =PnL!G31 -> 32.476361 | E7: =PnL!H31 -> 42.882367 | F7: =PnL!I31 -> 42.785582 | G7: =PnL!J31 -> 62.411306 | H7: =PnL!K31 -> 58.300834 | I7: =PnL!L31 -> 67.360432 | ... P7: =PnL!S31 -> 97.312888
A8: Tax | B8: =PnL!E34 -> 0.10214308 | C8: =PnL!F34 -> 0.11016052 | D8: =PnL!G34 -> 0.11048145 | E8: =PnL!H34 -> 0.11404445 | F8: =PnL!I34 -> 0.35915118 | G8: =PnL!J34 -> 0.87795062 | H8: =PnL!K34 -> 0.55083722 | I8: =PnL!L34 -> 0.99875767 | ... P8: =PnL!S34 -> 1.5163702
A9: Total cost | B9: =B6+B7+B8 -> 40.449765 | C9: =C6+C7+C8 -> 43.083205 | D9: =D6+D7+D8 -> 43.051876 | E9: =E6+E7+E8 -> 53.978541 | F9: =F6+F7+F8 -> 81.216355 | G9: =G6+G7+G8 -> 124.86653 | H9: =H6+H7+H8 -> 104.44433 | I9: =I6+I7+I8 -> 142.56928 | ... P9: =P6+P7+P8 -> 220.42763
A10: Net profit | B10: =PnL!E35 -> -20.021148 | C10: =PnL!F35 -> -21.0511 | D10: =PnL!G35 -> -20.955587 | E10: =PnL!H35 -> -31.169652 | F10: =PnL!I35 -> -9.3861181 | G10: =PnL!J35 -> 50.723595 | H10: =PnL!K35 -> 5.7231127 | I10: =PnL!L35 -> 57.182253 | ... P10: =PnL!S35 -> 82.846414
A11: Cash in | B11: =CashFlow!E11 -> 5.428617 | C11: =CashFlow!F11 -> 24.567855 | D11: =CashFlow!G11 -> 17.024789 | E11: =CashFlow!H11 -> 25.344639 | F11: =CashFlow!I11 -> 48.814986 | G11: =CashFlow!J11 -> 136.45637 | H11: =CashFlow!K11 -> 104.51644 | I11: =CashFlow!L11 -> 189.40053 | ... P11: =CashFlow!S11 -> 376.67404
A12: Cash out | B12: =CashFlow!E17 -> 40.347622 | C12: =CashFlow!F17 -> 43.075188 | D12: =CashFlow!G17 -> 43.051556 | E12: =CashFlow!H17 -> 53.974978 | F12: =CashFlow!I17 -> 80.971248 | G12: =CashFlow!J17 -> 124.34773 | H12: =CashFlow!K17 -> 104.77144 | I12: =CashFlow!L17 -> 142.12136 | ... P12: =CashFlow!S17 -> 221.05085
A13: Cash at end of month | B13: =CashFlow!E21 -> 175.081 | C13: =CashFlow!F21 -> 156.57366 | D13: =CashFlow!G21 -> 130.5469 | E13: =CashFlow!H21 -> 101.91656 | F13: =CashFlow!I21 -> 69.760296 | G13: =CashFlow!J21 -> 81.868941 | H13: =CashFlow!K21 -> 81.61394 | I13: =CashFlow!L21 -> 128.89311 | ... P13: =CashFlow!S21 -> 541.81498
A14: Cash floor (1 month of costs) | B14: =CashFlow!E24 -> 40.347622 | C14: =CashFlow!F24 -> 42.973045 | D14: =CashFlow!G24 -> 42.941395 | E14: =CashFlow!H24 -> 53.864497 | F14: =CashFlow!I24 -> 80.857203 | G14: =CashFlow!J24 -> 123.98858 | H14: =CashFlow!K24 -> 103.89349 | I14: =CashFlow!L24 -> 141.57052 | ... P14: =CashFlow!S24 -> 218.91126
A15: Above the floor? (1 = yes) | B15: =CashFlow!E25 -> 1 | C15: =CashFlow!F25 -> 1 | D15: =CashFlow!G25 -> 1 | E15: =CashFlow!H25 -> 1 | F15: =CashFlow!I25 -> 0 | G15: =CashFlow!J25 -> 0 | H15: =CashFlow!K25 -> 0 | I15: =CashFlow!L25 -> 0 | ... P15: =CashFlow!S25 -> 1

Sheet Roadmap
A1: Roadmap: when we must start selling and preparing, worked backward from each start date
A2: Rule: start from the date the work begins and go back through three clocks: sales (lead to signed), delivery (people ready) and cash (work done to cash in). Regulators and banks also need us inside their budget, which they plan in the second half of the year before.
A4: Today (blue: change it when you review) | C4: 46300
A6: A. Lead times by client type, in days (Estimate until we log 3 real deals of each type in section E)
A7: Client type | B7: Contract and paperwork (legal, vendor registration, work order) | C7: Pitch, scoping, proposal | D7: Finding qualified leads
A8: Private company | B8: 14 | C8: 45 | D8: 30
A9: Regulator (BI, OJK, LPS) | B9: 42 | C9: 75 | D9: 30
A10: State-owned bank | B10: 42 | C10: 75 | D10: 30
A11: B2C public | B11: 0 | C11: 30 | D11: 30
A13: B. Sales clock: the latest date to start each deal
A14: Milestone | B14: Client type | C14: New client? (1 = yes) | D14: Work starts | E14: Client budget window closes | F14: Sign by | G14: Start pitching | H14: Start finding leads | I14: Latest start | J14: Owner | K14: Status today
A15: BI 2027: Flagship and regional programs (first in March) | B15: Regulator (BI, OJK, LPS) | C15: 0 | D15: 46447 | E15: 46387 | F15: =D15-VLOOKUP(B15,$A$8:$D$11,2,0) -> 46405 | G15: =F15-VLOOKUP(B15,$A$8:$D$11,3,0) -> 46330 | H15: =G15-C15*VLOOKUP(B15,$A$8:$D$11,4,0) -> 46330 | I15: =IF(E15="",H15,MIN(H15,E15-VLOOKUP(B15,$A$8:$D$11,3,0))) -> 46312 | J15: Kia | K15: =IF(G15<$C$4,"Late",IF(I15<$C$4,"At risk",IF(I15-$C$4<=31,"Start now","On track"))) -> Start now
A16: BI 2027: regional events Jul-Sep (moved from the Q4 peak) | B16: Regulator (BI, OJK, LPS) | C16: 0 | D16: 46569 | E16: 46387 | F16: =D16-VLOOKUP(B16,$A$8:$D$11,2,0) -> 46527 | G16: =F16-VLOOKUP(B16,$A$8:$D$11,3,0) -> 46452 | H16: =G16-C16*VLOOKUP(B16,$A$8:$D$11,4,0) -> 46452 | I16: =IF(E16="",H16,MIN(H16,E16-VLOOKUP(B16,$A$8:$D$11,3,0))) -> 46312 | J16: Kia | K16: =IF(G16<$C$4,"Late",IF(I16<$C$4,"At risk",IF(I16-$C$4<=31,"Start now","On track"))) -> Start now
A17: BI 2027: regional peak Oct-Dec | B17: Regulator (BI, OJK, LPS) | C17: 0 | D17: 46661 | E17: 46387 | F17: =D17-VLOOKUP(B17,$A$8:$D$11,2,0) -> 46619 | G17: =F17-VLOOKUP(B17,$A$8:$D$11,3,0) -> 46544 | H17: =G17-C17*VLOOKUP(B17,$A$8:$D$11,4,0) -> 46544 | I17: =IF(E17="",H17,MIN(H17,E17-VLOOKUP(B17,$A$8:$D$11,3,0))) -> 46312 | J17: Kia | K17: =IF(G17<$C$4,"Late",IF(I17<$C$4,"At risk",IF(I17-$C$4<=31,"Start now","On track"))) -> Start now
A18: EAP contract 2: the warm lead (chase now) | B18: Private company | C18: 0 | D18: 46419 | F18: =D18-VLOOKUP(B18,$A$8:$D$11,2,0) -> 46405 | G18: =F18-VLOOKUP(B18,$A$8:$D$11,3,0) -> 46360 | H18: =G18-C18*VLOOKUP(B18,$A$8:$D$11,4,0) -> 46360 | I18: =IF(E18="",H18,MIN(H18,E18-VLOOKUP(B18,$A$8:$D$11,3,0))) -> 46360 | J18: Galih | K18: =IF(G18<$C$4,"Late",IF(I18<$C$4,"At risk",IF(I18-$C$4<=31,"Start now","On track"))) -> On track
A19: EAP contract 2 if the client is a bank | B19: State-owned bank | C19: 1 | D19: 46419 | E19: 46387 | F19: =D19-VLOOKUP(B19,$A$8:$D$11,2,0) -> 46377 | G19: =F19-VLOOKUP(B19,$A$8:$D$11,3,0) -> 46302 | H19: =G19-C19*VLOOKUP(B19,$A$8:$D$11,4,0) -> 46272 | I19: =IF(E19="",H19,MIN(H19,E19-VLOOKUP(B19,$A$8:$D$11,3,0))) -> 46272 | J19: Galih | K19: =IF(G19<$C$4,"Late",IF(I19<$C$4,"At risk",IF(I19-$C$4<=31,"Start now","On track"))) -> At risk
A20: EAP contract 3 with a bank | B20: State-owned bank | C20: 1 | D20: 46569 | E20: 46387 | F20: =D20-VLOOKUP(B20,$A$8:$D$11,2,0) -> 46527 | G20: =F20-VLOOKUP(B20,$A$8:$D$11,3,0) -> 46452 | H20: =G20-C20*VLOOKUP(B20,$A$8:$D$11,4,0) -> 46422 | I20: =IF(E20="",H20,MIN(H20,E20-VLOOKUP(B20,$A$8:$D$11,3,0))) -> 46312 | J20: Kia | K20: =IF(G20<$C$4,"Late",IF(I20<$C$4,"At risk",IF(I20-$C$4<=31,"Start now","On track"))) -> Start now
A21: Bank agreement: training days | B21: State-owned bank | C21: 1 | D21: 46661 | E21: 46387 | F21: =D21-VLOOKUP(B21,$A$8:$D$11,2,0) -> 46619 | G21: =F21-VLOOKUP(B21,$A$8:$D$11,3,0) -> 46544 | H21: =G21-C21*VLOOKUP(B21,$A$8:$D$11,4,0) -> 46514 | I21: =IF(E21="",H21,MIN(H21,E21-VLOOKUP(B21,$A$8:$D$11,3,0))) -> 46312 | J21: Kia, then BD co-founder | K21: =IF(G21<$C$4,"Late",IF(I21<$C$4,"At risk",IF(I21-$C$4<=31,"Start now","On track"))) -> Start now
A22: B2C events (Instagram campaign, then tickets) | B22: B2C public | C22: 1 | D22: 46661 | F22: =D22-VLOOKUP(B22,$A$8:$D$11,2,0) -> 46661 | G22: =F22-VLOOKUP(B22,$A$8:$D$11,3,0) -> 46631 | H22: =G22-C22*VLOOKUP(B22,$A$8:$D$11,4,0) -> 46601 | I22: =IF(E22="",H22,MIN(H22,E22-VLOOKUP(B22,$A$8:$D$11,3,0))) -> 46601 | J22: Galih (lead marketing) | K22: =IF(G22<$C$4,"Late",IF(I22<$C$4,"At risk",IF(I22-$C$4<=31,"Start now","On track"))) -> On track
A23: OJK and LPS programs for 2028 | B23: Regulator (BI, OJK, LPS) | C23: 1 | D23: 46813 | E23: 46660 | F23: =D23-VLOOKUP(B23,$A$8:$D$11,2,0) -> 46771 | G23: =F23-VLOOKUP(B23,$A$8:$D$11,3,0) -> 46696 | H23: =G23-C23*VLOOKUP(B23,$A$8:$D$11,4,0) -> 46666 | I23: =IF(E23="",H23,MIN(H23,E23-VLOOKUP(B23,$A$8:$D$11,3,0))) -> 46585 | J23: Kia, then BD co-founder | K23: =IF(G23<$C$4,"Late",IF(I23<$C$4,"At risk",IF(I23-$C$4<=31,"Start now","On track"))) -> On track
A24: BI 2028 programs | B24: Regulator (BI, OJK, LPS) | C24: 0 | D24: 46813 | E24: 46752 | F24: =D24-VLOOKUP(B24,$A$8:$D$11,2,0) -> 46771 | G24: =F24-VLOOKUP(B24,$A$8:$D$11,3,0) -> 46696 | H24: =G24-C24*VLOOKUP(B24,$A$8:$D$11,4,0) -> 46696 | I24: =IF(E24="",H24,MIN(H24,E24-VLOOKUP(B24,$A$8:$D$11,3,0))) -> 46677 | J24: Kia | K24: =IF(G24<$C$4,"Late",IF(I24<$C$4,"At risk",IF(I24-$C$4<=31,"Start now","On track"))) -> On track
A25: Latest start = the earlier of: start finding leads, or the budget window close minus the pitch time.
A27: C. Delivery clock: people ready before the work
A28: Item | B28: Why | D28: Needed by | E28: Lead time (months) | I28: Latest start | J28: Owner | K28: Status today
A29: 3 certified trainers | B29: First programs in March need 3 trainers | D29: 46447 | E29: 3 | I29: =EDATE(D29,-E29) -> 46357 | J29: Galih | K29: =IF(I29<$C$4,"Late",IF(I29-$C$4<=31,"Start now","On track")) -> On track
A30: Part-time psychologist pool for EAP 2 | B30: EAP 2 starts in February | D30: 46419 | E30: 1 | I30: =EDATE(D30,-E30) -> 46388 | J30: Galih | K30: =IF(I30<$C$4,"Late",IF(I30-$C$4<=31,"Start now","On track")) -> On track
A31: Second paid part-time psychologist | B31: B2C evenings and EAP days from January | D31: 46388 | E31: 2 | I31: =EDATE(D31,-E31) -> 46327 | J31: Galih | K31: =IF(I31<$C$4,"Late",IF(I31-$C$4<=31,"Start now","On track")) -> Start now
A32: Standby project manager (paid per project) | B32: From July, more than 2 projects in a month | D32: 46569 | E32: 2 | I32: =EDATE(D32,-E32) -> 46508 | J32: Kia | K32: =IF(I32<$C$4,"Late",IF(I32-$C$4<=31,"Start now","On track")) -> On track
A33: Sales co-founder | B33: Joins in July; searching takes longer than a normal hire | D33: 46569 | E33: 6 | I33: =EDATE(D33,-E33) -> 46388 | J33: Kia and Galih | K33: =IF(I33<$C$4,"Late",IF(I33-$C$4<=31,"Start now","On track")) -> On track
A34: 8 certified trainers | B34: Busiest months: Oct to Dec 2027 | D34: 46661 | E34: 3 | I34: =EDATE(D34,-E34) -> 46569 | J34: Galih | K34: =IF(I34<$C$4,"Late",IF(I34-$C$4<=31,"Start now","On track")) -> On track
A35: Lead Partnership (non-psychologist) | B35: Manages EAP clients from October; brings clients | D35: 46661 | E35: 3 | I35: =EDATE(D35,-E35) -> 46569 | J35: Kia | K35: =IF(I35<$C$4,"Late",IF(I35-$C$4<=31,"Start now","On track")) -> On track
A36: Intern for invoices | B36: Invoices grow to about 11 a month in Q4 | D36: 46631 | E36: 1 | I36: =EDATE(D36,-E36) -> 46600 | J36: Galih | K36: =IF(I36<$C$4,"Late",IF(I36-$C$4<=31,"Start now","On track")) -> On track
A38: D. Cash clock: work done, cash not yet in
A39: Lowest cash in the plan (Rp m) | D39: =MIN(Outlook!B13:P13) -> 69.760296
A40: Month of the lowest cash | D40: =INDEX(Outlook!B4:P4,MATCH(MIN(Outlook!B13:P13),Outlook!B13:P13,0)) -> Feb-27
A41: Months below the safety floor | D41: =COUNTIF(Outlook!B15:P15,0) -> 5
A42: Down payment on Flagship programs (Inputs) | D42: =Inputs!$C$117 -> 0
A43: Costs leave in the event month; BI central pays 60/30/10% over 60 days, regional offices per payday, banks 20/50/30%, EAP the next month. Fix a gap before signing: a down payment, staged invoices, or a later start.
A45: E. Sales speed log: fill in after every won or lost deal, then replace the estimates in section A
A46: Client | B46: Client type | C46: First contact | D46: Proposal sent | E46: Signed | F46: Work started | G46: Cash in | H46: Days to sign | I46: Days to cash | J46: Won or lost | K46: Note
H47: =IF(OR(C47="",E47=""),"",E47-C47) | I47: =IF(OR(F47="",G47=""),"",G47-F47)
H48: =IF(OR(C48="",E48=""),"",E48-C48) | I48: =IF(OR(F48="",G48=""),"",G48-F48)
H49: =IF(OR(C49="",E49=""),"",E49-C49) | I49: =IF(OR(F49="",G49=""),"",G49-F49)
H50: =IF(OR(C50="",E50=""),"",E50-C50) | I50: =IF(OR(F50="",G50=""),"",G50-F50)
H51: =IF(OR(C51="",E51=""),"",E51-C51) | I51: =IF(OR(F51="",G51=""),"",G51-F51)
H52: =IF(OR(C52="",E52=""),"",E52-C52) | I52: =IF(OR(F52="",G52=""),"",G52-F52)
H53: =IF(OR(C53="",E53=""),"",E53-C53) | I53: =IF(OR(F53="",G53=""),"",G53-F53)
H54: =IF(OR(C54="",E54=""),"",E54-C54) | I54: =IF(OR(F54="",G54=""),"",G54-F54)

Sheet Segments
A1: Targets by priority: where 2027 revenue comes from (Rp million)
A2: Priority (founders, 16 Oct 2026): 1. EAP as the channel to counseling and training. BI stays at today's volume as a premium client (BAU). 2. LPS and OJK. 3. Banks (private banks last). New: schools. Rows add up to PnL row 12.
A4: Line | B4: Unit | C4: Q4 2026 | D4: FY 2027 | E4: =Volume!E4 -> Oct-26 | F4: =Volume!F4 -> Nov-26 | G4: =Volume!G4 -> Dec-26 | H4: =Volume!H4 -> Jan-27 | I4: =Volume!I4 -> Feb-27 | J4: =Volume!J4 -> Mar-27 | K4: =Volume!K4 -> Apr-27 | L4: =Volume!L4 -> May-27 | ... S4: =Volume!S4 -> Dec-27
A5: 1. EAP channel (primary): KPw packages, new EAP contracts, their trainings, channel counseling | B5: Rp m | C5: =SUM(E5:G5) -> 11.37245 | D5: =SUM(H5:S5) -> 572.8105 | E5: =PnL!E47+PnL!E48+IF(Volume!E26=0,0,PnL!E9*(Volume!E35+Volume!E18*(1-Inputs!$C$152*Inputs!$C$131))/Volume!E26)+Volume!E49*Inputs!$C$14 -> 0 | F5: =PnL!F47+PnL!F48+IF(Volume!F26=0,0,PnL!F9*(Volume!F35+Volume!F18*(1-Inputs!$C$152*Inputs!$C$131))/Volume!F26)+Volume!F49*Inputs!$C$14 -> 5.686225 | G5: =PnL!G47+PnL!G48+IF(Volume!G26=0,0,PnL!G9*(Volume!G35+Volume!G18*(1-Inputs!$C$152*Inputs!$C$131))/Volume!G26)+Volume!G49*Inputs!$C$14 -> 5.686225 | H5: =PnL!H47+PnL!H48+IF(Volume!H26=0,0,PnL!H9*(Volume!H35+Volume!H18*(1-Inputs!$C$152*Inputs!$C$131))/Volume!H26)+Volume!H49*Inputs!$C$14 -> 5.686225 | I5: =PnL!I47+PnL!I48+IF(Volume!I26=0,0,PnL!I9*(Volume!I35+Volume!I18*(1-Inputs!$C$152*Inputs!$C$131))/Volume!I26)+Volume!I49*Inputs!$C$14 -> 26.399666 | J5: =PnL!J47+PnL!J48+IF(Volume!J26=0,0,PnL!J9*(Volume!J35+Volume!J18*(1-Inputs!$C$152*Inputs!$C$131))/Volume!J26)+Volume!J49*Inputs!$C$14 -> 29.626991 | K5: =PnL!K47+PnL!K48+IF(Volume!K26=0,0,PnL!K9*(Volume!K35+Volume!K18*(1-Inputs!$C$152*Inputs!$C$131))/Volume!K26)+Volume!K49*Inputs!$C$14 -> 35.313215 | L5: =PnL!L47+PnL!L48+IF(Volume!L26=0,0,PnL!L9*(Volume!L35+Volume!L18*(1-Inputs!$C$152*Inputs!$C$131))/Volume!L26)+Volume!L49*Inputs!$C$14 -> 49.563215 | ... S5: =PnL!S47+PnL!S48+IF(Volume!S26=0,0,PnL!S9*(Volume!S35+Volume!S18*(1-Inputs!$C$152*Inputs!$C$131))/Volume!S26)+Volume!S49*Inputs!$C$14 -> 63.947297
A6: BI BAU premium: Flagship, BI regional ToT, existing EAP (kept at today's volume) | B6: Rp m | C6: =SUM(E6:G6) -> 45 | D6: =SUM(H6:S6) -> 1091.825 | E6: =PnL!E6+PnL!E7*Inputs!$C$83+IF(Volume!E26=0,0,PnL!E9*Volume!E18*Inputs!$C$152*Inputs!$C$131/Volume!E26) -> 15 | F6: =PnL!F6+PnL!F7*Inputs!$C$83+IF(Volume!F26=0,0,PnL!F9*Volume!F18*Inputs!$C$152*Inputs!$C$131/Volume!F26) -> 15 | G6: =PnL!G6+PnL!G7*Inputs!$C$83+IF(Volume!G26=0,0,PnL!G9*Volume!G18*Inputs!$C$152*Inputs!$C$131/Volume!G26) -> 15 | H6: =PnL!H6+PnL!H7*Inputs!$C$83+IF(Volume!H26=0,0,PnL!H9*Volume!H18*Inputs!$C$152*Inputs!$C$131/Volume!H26) -> 15 | I6: =PnL!I6+PnL!I7*Inputs!$C$83+IF(Volume!I26=0,0,PnL!I9*Volume!I18*Inputs!$C$152*Inputs!$C$131/Volume!I26) -> 15 | J6: =PnL!J6+PnL!J7*Inputs!$C$83+IF(Volume!J26=0,0,PnL!J9*Volume!J18*Inputs!$C$152*Inputs!$C$131/Volume!J26) -> 139.225 | K6: =PnL!K6+PnL!K7*Inputs!$C$83+IF(Volume!K26=0,0,PnL!K9*Volume!K18*Inputs!$C$152*Inputs!$C$131/Volume!K26) -> 15 | L6: =PnL!L6+PnL!L7*Inputs!$C$83+IF(Volume!L26=0,0,PnL!L9*Volume!L18*Inputs!$C$152*Inputs!$C$131/Volume!L26) -> 139.225 | ... S6: =PnL!S6+PnL!S7*Inputs!$C$83+IF(Volume!S26=0,0,PnL!S9*Volume!S18*Inputs!$C$152*Inputs!$C$131/Volume!S26) -> 136.125
A7: 2. LPS / OJK (secondary) | B7: Rp m | C7: =SUM(E7:G7) -> 0 | D7: =SUM(H7:S7) -> 130.815 | E7: =PnL!E7*(1-Inputs!$C$83)+PnL!E49 -> 0 | F7: =PnL!F7*(1-Inputs!$C$83)+PnL!F49 -> 0 | G7: =PnL!G7*(1-Inputs!$C$83)+PnL!G49 -> 0 | H7: =PnL!H7*(1-Inputs!$C$83)+PnL!H49 -> 0 | I7: =PnL!I7*(1-Inputs!$C$83)+PnL!I49 -> 0 | J7: =PnL!J7*(1-Inputs!$C$83)+PnL!J49 -> 4.275 | K7: =PnL!K7*(1-Inputs!$C$83)+PnL!K49 -> 0 | L7: =PnL!L7*(1-Inputs!$C$83)+PnL!L49 -> 4.275 | ... S7: =PnL!S7*(1-Inputs!$C$83)+PnL!S49 -> 31.065
A8: 3. Banks: state and private (tertiary) | B8: Rp m | C8: =SUM(E8:G8) -> 0 | D8: =SUM(H8:S8) -> 374.5 | E8: =PnL!E8 -> 0 | F8: =PnL!F8 -> 0 | G8: =PnL!G8 -> 0 | H8: =PnL!H8 -> 0 | I8: =PnL!I8 -> 0 | J8: =PnL!J8 -> 0 | K8: =PnL!K8 -> 53.5 | L8: =PnL!L8 -> 0 | ... S8: =PnL!S8 -> 53.5
A9: New: schools | B9: Rp m | C9: =SUM(E9:G9) -> 0 | D9: =SUM(H9:S9) -> 144 | E9: =PnL!E50 -> 0 | F9: =PnL!F50 -> 0 | G9: =PnL!G50 -> 0 | H9: =PnL!H50 -> 0 | I9: =PnL!I50 -> 24 | J9: =PnL!J50 -> 0 | K9: =PnL!K50 -> 0 | L9: =PnL!L50 -> 0 | ... S9: =PnL!S50 -> 0
A10: B2C direct: Instagram, referral, vouchers, public events | B10: Rp m | C10: =SUM(E10:G10) -> 8.184561 | D10: =SUM(H10:S10) -> 118.60407 | E10: =PnL!E10+PnL!E11-Volume!E49*Inputs!$C$14 -> 5.428617 | F10: =PnL!F10+PnL!F11-Volume!F49*Inputs!$C$14 -> 1.3458798 | G10: =PnL!G10+PnL!G11-Volume!G49*Inputs!$C$14 -> 1.4100642 | H10: =PnL!H10+PnL!H11-Volume!H49*Inputs!$C$14 -> 2.1226645 | I10: =PnL!I10+PnL!I11-Volume!I49*Inputs!$C$14 -> 6.430571 | J10: =PnL!J10+PnL!J11-Volume!J49*Inputs!$C$14 -> 2.4631339 | K10: =PnL!K10+PnL!K11-Volume!K49*Inputs!$C$14 -> 6.3542276 | L10: =PnL!L10+PnL!L11-Volume!L49*Inputs!$C$14 -> 6.6883184 | ... S10: =PnL!S10+PnL!S11-Volume!S49*Inputs!$C$14 -> 18.636748
A11: Total | B11: Rp m | C11: =SUM(E11:G11) -> 64.557011 | D11: =SUM(H11:S11) -> 2432.5546 | E11: =SUM(E5:E10) -> 20.428617 | F11: =SUM(F5:F10) -> 22.032105 | G11: =SUM(G5:G10) -> 22.096289 | H11: =SUM(H5:H10) -> 22.808889 | I11: =SUM(I5:I10) -> 71.830236 | J11: =SUM(J5:J10) -> 175.59012 | K11: =SUM(K5:K10) -> 110.16744 | L11: =SUM(L5:L10) -> 199.75153 | ... S11: =SUM(S5:S10) -> 303.27404
A12: Check: difference to PnL total revenue (must be 0) | B12: Rp m | C12: =SUM(E12:G12) -> 0 | D12: =SUM(H12:S12) -> 0 | E12: =ROUND(E11-PnL!E12,6) -> 0 | F12: =ROUND(F11-PnL!F12,6) -> 0 | G12: =ROUND(G11-PnL!G12,6) -> 0 | H12: =ROUND(H11-PnL!H12,6) -> 0 | I12: =ROUND(I11-PnL!I12,6) -> 0 | J12: =ROUND(J11-PnL!J12,6) -> 0 | K12: =ROUND(K11-PnL!K12,6) -> 0 | L12: =ROUND(L11-PnL!L12,6) -> 0 | ... S12: =ROUND(S11-PnL!S12,6) -> 0
A13: Mix
A14: Share: EAP channel | B14: % | C14: =IF(C11=0,0,C5/C11) -> 0.17616135 | D14: =IF(D11=0,0,D5/D11) -> 0.23547694 | E14: =IF(E11=0,0,E5/E11) -> 0 | F14: =IF(F11=0,0,F5/F11) -> 0.25808814 | G14: =IF(G11=0,0,G5/G11) -> 0.25733846 | H14: =IF(H11=0,0,H5/H11) -> 0.24929863 | I14: =IF(I11=0,0,I5/I11) -> 0.36752859 | J14: =IF(J11=0,0,J5/J11) -> 0.16872811 | ... S14: =IF(S11=0,0,S5/S11) -> 0.21085648
A15: Share: BI BAU | B15: % | C15: =IF(C11=0,0,C6/C11) -> 0.6970583 | D15: =IF(D11=0,0,D6/D11) -> 0.44883885 | E15: =IF(E11=0,0,E6/E11) -> 0.7342641 | F15: =IF(F11=0,0,F6/F11) -> 0.68082465 | G15: =IF(G11=0,0,G6/G11) -> 0.67884702 | H15: =IF(H11=0,0,H6/H11) -> 0.65763833 | I15: =IF(I11=0,0,I6/I11) -> 0.20882571 | J15: =IF(J11=0,0,J6/J11) -> 0.79289767 | ... S15: =IF(S11=0,0,S6/S11) -> 0.44885147
A16: Share: LPS / OJK | B16: % | C16: =IF(C11=0,0,C7/C11) -> 0 | D16: =IF(D11=0,0,D7/D11) -> 0.0537768 | E16: =IF(E11=0,0,E7/E11) -> 0 | F16: =IF(F11=0,0,F7/F11) -> 0 | G16: =IF(G11=0,0,G7/G11) -> 0 | H16: =IF(H11=0,0,H7/H11) -> 0 | I16: =IF(I11=0,0,I7/I11) -> 0 | J16: =IF(J11=0,0,J7/J11) -> 0.024346472 | ... S16: =IF(S11=0,0,S7/S11) -> 0.10243211
A17: Share: banks | B17: % | C17: =IF(C11=0,0,C8/C11) -> 0 | D17: =IF(D11=0,0,D8/D11) -> 0.15395338 | E17: =IF(E11=0,0,E8/E11) -> 0 | F17: =IF(F11=0,0,F8/F11) -> 0 | G17: =IF(G11=0,0,G8/G11) -> 0 | H17: =IF(H11=0,0,H8/H11) -> 0 | I17: =IF(I11=0,0,I8/I11) -> 0 | J17: =IF(J11=0,0,J8/J11) -> 0 | ... S17: =IF(S11=0,0,S8/S11) -> 0.17640811
A18: Share: schools | B18: % | C18: =IF(C11=0,0,C9/C11) -> 0 | D18: =IF(D11=0,0,D9/D11) -> 0.059197028 | E18: =IF(E11=0,0,E9/E11) -> 0 | F18: =IF(F11=0,0,F9/F11) -> 0 | G18: =IF(G11=0,0,G9/G11) -> 0 | H18: =IF(H11=0,0,H9/H11) -> 0 | I18: =IF(I11=0,0,I9/I11) -> 0.33412113 | J18: =IF(J11=0,0,J9/J11) -> 0 | ... S18: =IF(S11=0,0,S9/S11) -> 0
A19: Share: B2C direct | B19: % | C19: =IF(C11=0,0,C10/C11) -> 0.12678036 | D19: =IF(D11=0,0,D10/D11) -> 0.048757002 | E19: =IF(E11=0,0,E10/E11) -> 0.2657359 | F19: =IF(F11=0,0,F10/F11) -> 0.061087209 | G19: =IF(G11=0,0,G10/G11) -> 0.063814525 | H19: =IF(H11=0,0,H10/H11) -> 0.093063034 | I19: =IF(I11=0,0,I10/I11) -> 0.089524569 | J19: =IF(J11=0,0,J10/J11) -> 0.014027747 | ... S19: =IF(S11=0,0,S10/S11) -> 0.06145184
A20: All money from BI (BI BAU + KPw packages + their trainings): concentration risk | B20: Rp m | C20: =SUM(E20:G20) -> 55.143 | D20: =SUM(H20:S20) -> 1354.703 | E20: =PnL!E40 -> 15 | F20: =PnL!F40 -> 20.0715 | G20: =PnL!G40 -> 20.0715 | H20: =PnL!H40 -> 20.0715 | I20: =PnL!I40 -> 22.9695 | J20: =PnL!J40 -> 152.266 | K20: =PnL!K40 -> 33.1125 | L20: =PnL!L40 -> 164.4625 | ... S20: =PnL!S40 -> 167.1585
A21: Share of revenue from BI | B21: % | C21: =IF(C11=0,0,C20/C11) -> 0.85417523 | D21: =IF(D11=0,0,D20/D11) -> 0.55690549 | E21: =IF(E11=0,0,E20/E11) -> 0.7342641 | F21: =IF(F11=0,0,F20/F11) -> 0.91101146 | G21: =IF(G11=0,0,G20/G11) -> 0.90836519 | H21: =IF(H11=0,0,H20/H11) -> 0.87998585 | I21: =IF(I11=0,0,I20/I11) -> 0.31977481 | J21: =IF(J11=0,0,J20/J11) -> 0.86716722 | ... S21: =IF(S11=0,0,S20/S11) -> 0.55117971
A23: 2027 targets: the numbers to track every month
A24: Priority | B24: Target for 2027 | C24: Unit | D24: Plan (FY 2027) | E24: Owner
A25: 1. EAP channel | B25: New BI KPw packages signed | C25: packages | D25: =Volume!D39 -> 10 | E25: Kia
A26: 1. EAP channel | B26: Commit-2 second terms + renewals | C26: packages | D26: =Volume!D40+Volume!D41 -> 4.64 | E26: Kia
A27: 1. EAP channel | B27: Enterprise EAP contracts running in Dec 2027 (incl. existing) | C27: contracts | D27: =Volume!S26 -> 3 | E27: Galih
A28: 1. EAP channel | B28: Trainings sold to EAP clients | C28: events | D28: =Volume!D44+Volume!D45 -> 2.25 | E28: Kia
A29: 1. EAP channel | B29: Paid counseling sessions through channels | C29: sessions | D29: =Volume!D49 -> 66.18 | E29: Galih
A30: BI BAU | B30: Flagship + BI regional ToT (same as v15) | C30: events | D30: =Volume!D23+Volume!D24*Inputs!$C$83 -> 19.45 | E30: Kia
A31: 2. LPS / OJK | B31: LPS / OJK programs (incl. non-BI regional ToT) | C31: events | D31: =Volume!D46+Volume!D24*(1-Inputs!$C$83) -> 4.59 | E31: Kia, then BD co-founder
A32: 3. Banks | B32: Bank training days and events | C32: events | D32: =Volume!D25 -> 7 | E32: Kia, then BD co-founder
A33: New: schools | B33: Schools tested / students | C33: schools | D33: =Volume!D47 -> 6 | E33: Galih's wife (schools lead)
A34: New: schools | B34: Students tested | C34: students | D34: =Volume!D48 -> 480 | E34: Galih's wife (schools lead)
A35: B2C direct | B35: Paid B2C sessions (all sources) | C35: sessions | D35: =B2C!D26 -> 232.15351 | E35: Galih (lead marketing)
A36: Result | B36: BI share of revenue (all BI money) | C36: % | D36: =D21 -> 0.55690549 | E36: Kia
A37: Result | B37: Net margin FY 2027 | C37: % | D37: =PnL!D36 -> 0.22882331 | E37: Both founders

Sheet B2C
A1: B2C funnel: Instagram followers to paid counseling sessions, and B2C vs B2B revenue (Rp million)
A2: Growth is set per quarter (blue). Followers on 5 Oct 2026: @temanjourney_id. Today about 2 paid sessions a month, so the booking rate starts at about 0.6 new paying clients a month per 1,000 followers. Feeds Volume row 28.
A4: Quarterly inputs (blue = change freely)
C5: Q4 2026 | D5: Q1 2027 | E5: Q2 2027 | F5: Q3 2027 | G5: Q4 2027
A6: Follower growth in the quarter | C6: 0.15 | D6: 0.25 | E6: 0.28 | F6: 0.28 | G6: 0.24
A7: Booking rate: new paying clients a month per 1,000 followers | C7: 0.58 | D7: 0.7 | E7: 0.85 | F7: 1 | G7: 1
A8: Sessions per client | C8: 1 | D8: 1.1 | E8: 1.25 | F8: 1.4 | G8: 1.4
A9: Referral share of new clients (target 20% by Q4 2027) | C9: 0 | D9: 0.05 | E9: 0.1 | F9: 0.15 | G9: 0.2
A10: Instagram followers on 5 Oct 2026 | C10: 3439
A11: Theta voucher sessions a month per EAP contract | C11: 2
A12: Theta vouchers start | C12: Apr-27
A13: Sessions one paid part-time psychologist covers a month (3 shifts a week x 3) | C13: 36
A14: Paid part-time psychologists from Jan-27 | C14: 2
A15: Pool capacity: 20 part-timers x 8 hours a month | C15: 160
A16: Full-time psychologist pay, if hired (gross) | C16: 9
A17: Referral reward per referred client (Rp100k credit to each side) | C17: 0.2 | E17: Base Instagram ads already in the software budget (Rp m a month) | K17: 1
A18: Line | B18: Unit | C18: Q4 2026 | D18: FY 2027 | E18: =Volume!E4 -> Oct-26 | F18: =Volume!F4 -> Nov-26 | G18: =Volume!G4 -> Dec-26 | H18: =Volume!H4 -> Jan-27 | I18: =Volume!I4 -> Feb-27 | J18: =Volume!J4 -> Mar-27 | K18: =Volume!K4 -> Apr-27 | L18: =Volume!L4 -> May-27 | ... S18: =Volume!S4 -> Dec-27
A19: Quarter (1 = Q4 2026 ... 5 = Q4 2027) | B19: # | E19: =INT((Volume!E6-1)/3)+1 -> 1 | F19: =INT((Volume!F6-1)/3)+1 -> 1 | G19: =INT((Volume!G6-1)/3)+1 -> 1 | H19: =INT((Volume!H6-1)/3)+1 -> 2 | I19: =INT((Volume!I6-1)/3)+1 -> 2 | J19: =INT((Volume!J6-1)/3)+1 -> 2 | K19: =INT((Volume!K6-1)/3)+1 -> 3 | L19: =INT((Volume!L6-1)/3)+1 -> 3 | ... S19: =INT((Volume!S6-1)/3)+1 -> 5
A20: Instagram followers (end of month) | B20: people | C20: =MAX(E20:G20) -> 3954.85 | D20: =MAX(H20:S20) -> 10043.421 | E20: =$C$10*(1+INDEX($C$6:$G$6,E19))^(1/3) -> 3603.0044 | F20: =E20*(1+INDEX($C$6:$G$6,F19))^(1/3) -> 3774.83 | G20: =F20*(1+INDEX($C$6:$G$6,G19))^(1/3) -> 3954.85 | H20: =G20*(1+INDEX($C$6:$G$6,H19))^(1/3) -> 4260.233 | I20: =H20*(1+INDEX($C$6:$G$6,I19))^(1/3) -> 4589.1969 | J20: =I20*(1+INDEX($C$6:$G$6,J19))^(1/3) -> 4943.5625 | K20: =J20*(1+INDEX($C$6:$G$6,K19))^(1/3) -> 5367.5573 | L20: =K20*(1+INDEX($C$6:$G$6,L19))^(1/3) -> 5827.9168 | M20: =L20*(1+INDEX($C$6:$G$6,M19))^(1/3) -> 6327.76 | ... S20: =R20*(1+INDEX($C$6:$G$6,S19))^(1/3) -> 10043.421
A21: Booking rate | B21: per 1,000 | C21: =MAX(E21:G21) -> 0.58 | D21: =MAX(H21:S21) -> 1 | E21: =INDEX($C$7:$G$7,E19) -> 0.58 | F21: =INDEX($C$7:$G$7,F19) -> 0.58 | G21: =INDEX($C$7:$G$7,G19) -> 0.58 | H21: =INDEX($C$7:$G$7,H19) -> 0.7 | I21: =INDEX($C$7:$G$7,I19) -> 0.7 | J21: =INDEX($C$7:$G$7,J19) -> 0.7 | K21: =INDEX($C$7:$G$7,K19) -> 0.85 | L21: =INDEX($C$7:$G$7,L19) -> 0.85 | ... S21: =INDEX($C$7:$G$7,S19) -> 1
A22: Sessions per client | B22: x | C22: =MAX(E22:G22) -> 1 | D22: =MAX(H22:S22) -> 1.4 | E22: =INDEX($C$8:$G$8,E19) -> 1 | F22: =INDEX($C$8:$G$8,F19) -> 1 | G22: =INDEX($C$8:$G$8,G19) -> 1 | H22: =INDEX($C$8:$G$8,H19) -> 1.1 | I22: =INDEX($C$8:$G$8,I19) -> 1.1 | J22: =INDEX($C$8:$G$8,J19) -> 1.1 | K22: =INDEX($C$8:$G$8,K19) -> 1.25 | L22: =INDEX($C$8:$G$8,L19) -> 1.25 | ... S22: =INDEX($C$8:$G$8,S19) -> 1.4
A23: New paying clients from Instagram | B23: clients | C23: =SUM(E23:G23) -> 6.572957 | D23: =SUM(H23:S23) -> 75.073114 | E23: =E20/1000*E21 -> 2.0897425 | F23: =F20/1000*F21 -> 2.1894014 | G23: =G20/1000*G21 -> 2.293813 | H23: =H20/1000*H21 -> 2.9821631 | I23: =I20/1000*I21 -> 3.2124378 | J23: =J20/1000*J21 -> 3.4604937 | K23: =K20/1000*K21 -> 4.5624237 | L23: =L20/1000*L21 -> 4.9537293 | ... S23: =S20/1000*S21 -> 10.043421
A24: Sessions from Instagram | B24: sessions | C24: =SUM(E24:G24) -> 6.572957 | D24: =SUM(H24:S24) -> 99.971619 | E24: =E23*E22 -> 2.0897425 | F24: =F23*F22 -> 2.1894014 | G24: =G23*G22 -> 2.293813 | H24: =H23*H22 -> 3.2803794 | I24: =I23*I22 -> 3.5336816 | J24: =J23*J22 -> 3.8065431 | K24: =K23*K22 -> 5.7030296 | L24: =L23*L22 -> 6.1921616 | ... S24: =S23*S22 -> 14.060789
A25: Sessions from Theta vouchers (EAP staff) | B25: sessions | C25: =SUM(E25:G25) -> 0 | D25: =SUM(H25:S25) -> 48 | E25: =IF(Volume!E6>=IFERROR(MATCH($C$12,Volume!$E$4:$S$4,0),99),$C$11*Volume!E26,0) -> 0 | F25: =IF(Volume!F6>=IFERROR(MATCH($C$12,Volume!$E$4:$S$4,0),99),$C$11*Volume!F26,0) -> 0 | G25: =IF(Volume!G6>=IFERROR(MATCH($C$12,Volume!$E$4:$S$4,0),99),$C$11*Volume!G26,0) -> 0 | H25: =IF(Volume!H6>=IFERROR(MATCH($C$12,Volume!$E$4:$S$4,0),99),$C$11*Volume!H26,0) -> 0 | I25: =IF(Volume!I6>=IFERROR(MATCH($C$12,Volume!$E$4:$S$4,0),99),$C$11*Volume!I26,0) -> 0 | J25: =IF(Volume!J6>=IFERROR(MATCH($C$12,Volume!$E$4:$S$4,0),99),$C$11*Volume!J26,0) -> 0 | K25: =IF(Volume!K6>=IFERROR(MATCH($C$12,Volume!$E$4:$S$4,0),99),$C$11*Volume!K26,0) -> 4 | L25: =IF(Volume!L6>=IFERROR(MATCH($C$12,Volume!$E$4:$S$4,0),99),$C$11*Volume!L26,0) -> 4 | ... S25: =IF(Volume!S6>=IFERROR(MATCH($C$12,Volume!$E$4:$S$4,0),99),$C$11*Volume!S26,0) -> 6
A26: Paid B2C counseling sessions (Instagram + vouchers + referral + channels) | B26: sessions | C26: =SUM(E26:G26) -> 8.572957 | D26: =SUM(H26:S26) -> 232.15351 | E26: =E24+E25+E52+Volume!E49 -> 2.0897425 | F26: =F24+F25+F52+Volume!F49 -> 3.1894014 | G26: =G24+G25+G52+Volume!G49 -> 3.293813 | H26: =H24+H25+H52+Volume!H49 -> 4.453031 | I26: =I24+I25+I52+Volume!I49 -> 9.2996649 | J26: =J24+J25+J52+Volume!J49 -> 6.5868875 | K26: =K24+K25+K52+Volume!K49 -> 13.9167 | L26: =L24+L25+L52+Volume!L49 -> 14.46018 | ... S26: =S24+S25+S52+Volume!S49 -> 28.315986
A27: Revenue
A28: Counseling revenue | B28: Rp m | C28: =SUM(E28:G28) -> 5.270011 | D28: =SUM(H28:S28) -> 142.71057 | E28: =PnL!E11 -> 1.284617 | F28: =PnL!F11 -> 1.9606048 | G28: =PnL!G11 -> 2.0247892 | H28: =PnL!H11 -> 2.7373895 | I28: =PnL!I11 -> 5.7167365 | J28: =PnL!J11 -> 4.0491244 | K28: =PnL!K11 -> 8.5549431 | L28: =PnL!L11 -> 8.8890339 | ... S28: =PnL!S11 -> 17.406545
A29: Public events | B29: events | C29: =SUM(E29:G29) -> 1 | D29: =SUM(H29:S29) -> 4 | E29: =Volume!E27 -> 1 | F29: =Volume!F27 -> 0 | G29: =Volume!G27 -> 0 | H29: =Volume!H27 -> 0 | I29: =Volume!I27 -> 1 | J29: =Volume!J27 -> 0 | K29: =Volume!K27 -> 0 | L29: =Volume!L27 -> 0 | ... S29: =Volume!S27 -> 1
A30: Public event revenue | B30: Rp m | C30: =SUM(E30:G30) -> 4.144 | D30: =SUM(H30:S30) -> 16.576 | E30: =PnL!E10 -> 4.144 | F30: =PnL!F10 -> 0 | G30: =PnL!G10 -> 0 | H30: =PnL!H10 -> 0 | I30: =PnL!I10 -> 4.144 | J30: =PnL!J10 -> 0 | K30: =PnL!K10 -> 0 | L30: =PnL!L10 -> 0 | ... S30: =PnL!S10 -> 4.144
A31: B2C revenue | B31: Rp m | C31: =SUM(E31:G31) -> 9.414011 | D31: =SUM(H31:S31) -> 159.28657 | E31: =E28+E30 -> 5.428617 | F31: =F28+F30 -> 1.9606048 | G31: =G28+G30 -> 2.0247892 | H31: =H28+H30 -> 2.7373895 | I31: =I28+I30 -> 9.8607365 | J31: =J28+J30 -> 4.0491244 | K31: =K28+K30 -> 8.5549431 | L31: =L28+L30 -> 8.8890339 | ... S31: =S28+S30 -> 21.550545
A32: B2B revenue (regulators, banks, EAP) | B32: Rp m | C32: =SUM(E32:G32) -> 55.143 | D32: =SUM(H32:S32) -> 2273.268 | E32: =PnL!E12-E31 -> 15 | F32: =PnL!F12-F31 -> 20.0715 | G32: =PnL!G12-G31 -> 20.0715 | H32: =PnL!H12-H31 -> 20.0715 | I32: =PnL!I12-I31 -> 61.9695 | J32: =PnL!J12-J31 -> 171.541 | K32: =PnL!K12-K31 -> 101.6125 | L32: =PnL!L12-L31 -> 190.8625 | ... S32: =PnL!S12-S31 -> 281.7235
A33: B2C share of all revenue | B33: % | C33: =IF(SUM(PnL!E12:G12)=0,0,C31/SUM(PnL!E12:G12)) -> 0.14582477 | D33: =IF(SUM(PnL!H12:S12)=0,0,D31/SUM(PnL!H12:S12)) -> 0.06548119 | E33: =IF(PnL!E12=0,0,E31/PnL!E12) -> 0.2657359 | F33: =IF(PnL!F12=0,0,F31/PnL!F12) -> 0.088988538 | G33: =IF(PnL!G12=0,0,G31/PnL!G12) -> 0.091634807 | H33: =IF(PnL!H12=0,0,H31/PnL!H12) -> 0.12001415 | I33: =IF(PnL!I12=0,0,I31/PnL!I12) -> 0.13727835 | J33: =IF(PnL!J12=0,0,J31/PnL!J12) -> 0.023060092 | K33: =IF(PnL!K12=0,0,K31/PnL!K12) -> 0.077654004 | L33: =IF(PnL!L12=0,0,L31/PnL!L12) -> 0.044500454 | ... S33: =IF(PnL!S12=0,0,S31/PnL!S12) -> 0.071059641
A34: Can B2C pay for our psychologists?
A35: B2C gross profit (after psychologist session fees and event costs) | B35: Rp m | C35: =SUM(E35:G35) -> 2.8598399 | D35: =SUM(H35:S35) -> 44.80898 | E35: =PnL!E10+PnL!E11-PnL!E19-PnL!E20 -> 1.7664377 | F35: =PnL!F10+PnL!F11-PnL!F19-PnL!F20 -> 0.53789654 | G35: =PnL!G10+PnL!G11-PnL!G19-PnL!G20 -> 0.55550568 | H35: =PnL!H10+PnL!H11-PnL!H19-PnL!H20 -> 0.75100924 | I35: =PnL!I10+PnL!I11-PnL!I19-PnL!I20 -> 2.9824001 | J35: =PnL!J10+PnL!J11-PnL!J19-PnL!J20 -> 1.1108868 | K35: =PnL!K10+PnL!K11-PnL!K19-PnL!K20 -> 2.3470688 | L35: =PnL!L10+PnL!L11-PnL!L19-PnL!L20 -> 2.4387274 | ... S35: =PnL!S10+PnL!S11-PnL!S19-PnL!S20 -> 6.1895265
A36: Paid psychologists' pay incl. BPJS and THR | B36: Rp m | C36: =SUM(E36:G36) -> 6.9 | D36: =SUM(H36:S36) -> 65.136 | E36: =Pay_Plan!E9*(1+Inputs!$C$106*Pay_Plan!E14) -> 2.3 | F36: =Pay_Plan!F9*(1+Inputs!$C$106*Pay_Plan!F14) -> 2.3 | G36: =Pay_Plan!G9*(1+Inputs!$C$106*Pay_Plan!G14) -> 2.3 | H36: =Pay_Plan!H9*(1+Inputs!$C$106*Pay_Plan!H14) -> 5.428 | I36: =Pay_Plan!I9*(1+Inputs!$C$106*Pay_Plan!I14) -> 5.428 | J36: =Pay_Plan!J9*(1+Inputs!$C$106*Pay_Plan!J14) -> 5.428 | K36: =Pay_Plan!K9*(1+Inputs!$C$106*Pay_Plan!K14) -> 5.428 | L36: =Pay_Plan!L9*(1+Inputs!$C$106*Pay_Plan!L14) -> 5.428 | ... S36: =Pay_Plan!S9*(1+Inputs!$C$106*Pay_Plan!S14) -> 5.428
A37: Extra Instagram ads | B37: Rp m | C37: =SUM(E37:G37) -> 0 | D37: =SUM(H37:S37) -> 42 | E37: =Pay_Plan!E12 -> 0 | F37: =Pay_Plan!F12 -> 0 | G37: =Pay_Plan!G12 -> 0 | H37: =Pay_Plan!H12 -> 3.5 | I37: =Pay_Plan!I12 -> 3.5 | J37: =Pay_Plan!J12 -> 3.5 | K37: =Pay_Plan!K12 -> 3.5 | L37: =Pay_Plan!L12 -> 3.5 | ... S37: =Pay_Plan!S12 -> 3.5
A38: Psychologists' pay covered by B2C gross profit | B38: x | C38: =IF(C36=0,0,C35/C36) -> 0.41446955 | D38: =IF(D36=0,0,D35/D36) -> 0.68792957 | E38: =IF(E36=0,0,E35/E36) -> 0.76801639 | F38: =IF(F36=0,0,F35/F36) -> 0.23386806 | G38: =IF(G36=0,0,G35/G36) -> 0.24152421 | H38: =IF(H36=0,0,H35/H36) -> 0.13835837 | I38: =IF(I36=0,0,I35/I36) -> 0.54944733 | J38: =IF(J36=0,0,J35/J36) -> 0.20465859 | ... S38: =IF(S36=0,0,S35/S36) -> 1.140296
A39: B2C profit after psychologists, ads and referral rewards | B39: Rp m | C39: =SUM(E39:G39) -> -4.0401601 | D39: =SUM(H39:S39) -> -64.955961 | E39: =E35-E36-E37-E53 -> -0.53356231 | F39: =F35-F36-F37-F53 -> -1.7621035 | G39: =G35-G36-G37-G53 -> -1.7444943 | H39: =H35-H36-H37-H53 -> -8.208382 | I39: =I35-I36-I37-I53 -> -5.979415 | J39: =J35-J36-J37-J53 -> -7.8535394 | K39: =K35-K36-K37-K53 -> -6.6823184 | L39: =L35-L36-L37-L53 -> -6.5993555 | ... S39: =S35-S36-S37-S53 -> -3.2406446
A40: Capacity (COO)
A41: COO: sessions to deliver (B2C + EAP + BI KPw packages) | B41: sessions | C41: =SUM(E41:G41) -> 56.272957 | D41: =SUM(H41:S41) -> 895.44651 | E41: =E26+Volume!E26*Inputs!$C$68+Volume!E43 -> 12.089743 | F41: =F26+Volume!F26*Inputs!$C$68+Volume!F43 -> 22.039401 | G41: =G26+Volume!G26*Inputs!$C$68+Volume!G43 -> 22.143813 | H41: =H26+Volume!H26*Inputs!$C$68+Volume!H43 -> 23.303031 | I41: =I26+Volume!I26*Inputs!$C$68+Volume!I43 -> 43.282665 | J41: =J26+Volume!J26*Inputs!$C$68+Volume!J43 -> 49.419888 | K41: =K26+Volume!K26*Inputs!$C$68+Volume!K43 -> 65.5997 | L41: =L26+Volume!L26*Inputs!$C$68+Volume!L43 -> 66.14318 | ... S41: =S26+Volume!S26*Inputs!$C$68+Volume!S43 -> 100.26499
A42: Paid part-time capacity | B42: sessions | C42: =SUM(E42:G42) -> 108 | D42: =SUM(H42:S42) -> 864 | E42: =IF(Volume!E6>=4,$C$14,1)*$C$13 -> 36 | F42: =IF(Volume!F6>=4,$C$14,1)*$C$13 -> 36 | G42: =IF(Volume!G6>=4,$C$14,1)*$C$13 -> 36 | H42: =IF(Volume!H6>=4,$C$14,1)*$C$13 -> 72 | I42: =IF(Volume!I6>=4,$C$14,1)*$C$13 -> 72 | J42: =IF(Volume!J6>=4,$C$14,1)*$C$13 -> 72 | K42: =IF(Volume!K6>=4,$C$14,1)*$C$13 -> 72 | L42: =IF(Volume!L6>=4,$C$14,1)*$C$13 -> 72 | ... S42: =IF(Volume!S6>=4,$C$14,1)*$C$13 -> 72
A43: Load on paid part-timers | B43: % | E43: =E41/E42 -> 0.33582618 | F43: =F41/F42 -> 0.6122056 | G43: =G41/G42 -> 0.61510592 | H43: =H41/H42 -> 0.32365321 | I43: =I41/I42 -> 0.60114812 | J43: =J41/J42 -> 0.68638733 | K43: =K41/K42 -> 0.91110694 | L43: =L41/L42 -> 0.91865527 | ... S43: =S41/S42 -> 1.3925693
A44: Sessions for the pool of 20 | B44: sessions | C44: =SUM(E44:G44) -> 0 | D44: =SUM(H44:S44) -> 153.10178 | E44: =MAX(0,E41-E42) -> 0 | F44: =MAX(0,F41-F42) -> 0 | G44: =MAX(0,G41-G42) -> 0 | H44: =MAX(0,H41-H42) -> 0 | I44: =MAX(0,I41-I42) -> 0 | J44: =MAX(0,J41-J42) -> 0 | K44: =MAX(0,K41-K42) -> 0 | L44: =MAX(0,L41-L42) -> 0 | ... S44: =MAX(0,S41-S42) -> 28.264986
A45: When can we afford a full-time psychologist?
A46: Full-time test: counseling profit, 3-month average | B46: Rp m | E46: =AVERAGE(E26)*Inputs!$C$14*(1-Inputs!$C$21) -> 0.35243769 | F46: =AVERAGE(F26,E26)*Inputs!$C$14*(1-Inputs!$C$21) -> 0.44516711 | G46: =AVERAGE(G26,F26,E26)*Inputs!$C$14*(1-Inputs!$C$21) -> 0.48194664 | H46: =AVERAGE(H26,G26,F26)*Inputs!$C$14*(1-Inputs!$C$21) -> 0.61480382 | I46: =AVERAGE(I26,H26,G26)*Inputs!$C$14*(1-Inputs!$C$21) -> 0.95830501 | J46: =AVERAGE(J26,I26,H26)*Inputs!$C$14*(1-Inputs!$C$21) -> 1.1434321 | K46: =AVERAGE(K26,J26,I26)*Inputs!$C$14*(1-Inputs!$C$21) -> 1.6754519 | L46: =AVERAGE(L26,K26,J26)*Inputs!$C$14*(1-Inputs!$C$21) -> 1.965561 | M46: =AVERAGE(M26,L26,K26)*Inputs!$C$14*(1-Inputs!$C$21) -> 2.4177366 | N46: =AVERAGE(N26,M26,L26)*Inputs!$C$14*(1-Inputs!$C$21) -> 3.0439597 | ... S46: =AVERAGE(S26,R26,Q26)*Inputs!$C$14*(1-Inputs!$C$21) -> 5.0721121
A47: Pay of the PIC part-timer + one full-timer, incl. BPJS and THR | B47: Rp m | E47: =(2.3+$C$16)*(1+Inputs!$C$106) -> 13.334 | F47: =(2.3+$C$16)*(1+Inputs!$C$106) -> 13.334 | G47: =(2.3+$C$16)*(1+Inputs!$C$106) -> 13.334 | H47: =(2.3+$C$16)*(1+Inputs!$C$106) -> 13.334 | I47: =(2.3+$C$16)*(1+Inputs!$C$106) -> 13.334 | J47: =(2.3+$C$16)*(1+Inputs!$C$106) -> 13.334 | K47: =(2.3+$C$16)*(1+Inputs!$C$106) -> 13.334 | L47: =(2.3+$C$16)*(1+Inputs!$C$106) -> 13.334 | ... S47: =(2.3+$C$16)*(1+Inputs!$C$106) -> 13.334
A48: Full-time psychologist affordable? (1 = yes) | B48: flag | C48: =MAX(E48:G48) -> 0 | D48: =MAX(H48:S48) -> 0 | E48: =IF(E46>=E47,1,0) -> 0 | F48: =IF(F46>=F47,1,0) -> 0 | G48: =IF(G46>=G47,1,0) -> 0 | H48: =IF(H46>=H47,1,0) -> 0 | I48: =IF(I46>=I47,1,0) -> 0 | J48: =IF(J46>=J47,1,0) -> 0 | K48: =IF(K46>=K47,1,0) -> 0 | L48: =IF(L46>=L47,1,0) -> 0 | ... S48: =IF(S46>=S47,1,0) -> 0
A50: Referral (track the source of every booking)
A51: New clients from referral | B51: clients | C51: =SUM(E51:G51) -> 0 | D51: =SUM(H51:S51) -> 13.144707 | E51: =E23*INDEX($C$9:$G$9,E19)/(1-INDEX($C$9:$G$9,E19)) -> 0 | F51: =F23*INDEX($C$9:$G$9,F19)/(1-INDEX($C$9:$G$9,F19)) -> 0 | G51: =G23*INDEX($C$9:$G$9,G19)/(1-INDEX($C$9:$G$9,G19)) -> 0 | H51: =H23*INDEX($C$9:$G$9,H19)/(1-INDEX($C$9:$G$9,H19)) -> 0.15695595 | I51: =I23*INDEX($C$9:$G$9,I19)/(1-INDEX($C$9:$G$9,I19)) -> 0.16907568 | J51: =J23*INDEX($C$9:$G$9,J19)/(1-INDEX($C$9:$G$9,J19)) -> 0.18213125 | K51: =K23*INDEX($C$9:$G$9,K19)/(1-INDEX($C$9:$G$9,K19)) -> 0.50693596 | L51: =L23*INDEX($C$9:$G$9,L19)/(1-INDEX($C$9:$G$9,L19)) -> 0.55041436 | ... S51: =S23*INDEX($C$9:$G$9,S19)/(1-INDEX($C$9:$G$9,S19)) -> 2.5108552
A52: Sessions from referral | B52: sessions | C52: =SUM(E52:G52) -> 0 | D52: =SUM(H52:S52) -> 18.001895 | E52: =E51*E22 -> 0 | F52: =F51*F22 -> 0 | G52: =G51*G22 -> 0 | H52: =H51*H22 -> 0.17265155 | I52: =I51*I22 -> 0.18598324 | J52: =J51*J22 -> 0.20034437 | K52: =K51*K22 -> 0.63366995 | L52: =L51*L22 -> 0.68801795 | ... S52: =S51*S22 -> 3.5151972
A53: Referral rewards (cost) | B53: Rp m | C53: =SUM(E53:G53) -> 0 | D53: =SUM(H53:S53) -> 2.6289414 | E53: =E51*$C$17 -> 0 | F53: =F51*$C$17 -> 0 | G53: =G51*$C$17 -> 0 | H53: =H51*$C$17 -> 0.031391191 | I53: =I51*$C$17 -> 0.033815135 | J53: =J51*$C$17 -> 0.03642625 | K53: =K51*$C$17 -> 0.10138719 | L53: =L51*$C$17 -> 0.11008287 | ... S53: =S51*$C$17 -> 0.50217103
A54: Referral share of new clients | B54: % | E54: =IF(E23+E51=0,0,E51/(E23+E51)) -> 0 | F54: =IF(F23+F51=0,0,F51/(F23+F51)) -> 0 | G54: =IF(G23+G51=0,0,G51/(G23+G51)) -> 0 | H54: =IF(H23+H51=0,0,H51/(H23+H51)) -> 0.05 | I54: =IF(I23+I51=0,0,I51/(I23+I51)) -> 0.05 | J54: =IF(J23+J51=0,0,J51/(J23+J51)) -> 0.05 | K54: =IF(K23+K51=0,0,K51/(K23+K51)) -> 0.1 | L54: =IF(L23+L51=0,0,L51/(L23+L51)) -> 0.1 | ... S54: =IF(S23+S51=0,0,S51/(S23+S51)) -> 0.2
A55: Unit economics per client
A56: Profit per client (LTV) = price x (1 - psychologist fee) x sessions per client | B56: Rp m | E56: =Inputs!$C$14*(1-Inputs!$C$21)*E22 -> 0.16865125 | F56: =Inputs!$C$14*(1-Inputs!$C$21)*F22 -> 0.16865125 | G56: =Inputs!$C$14*(1-Inputs!$C$21)*G22 -> 0.16865125 | H56: =Inputs!$C$14*(1-Inputs!$C$21)*H22 -> 0.18551638 | I56: =Inputs!$C$14*(1-Inputs!$C$21)*I22 -> 0.18551638 | J56: =Inputs!$C$14*(1-Inputs!$C$21)*J22 -> 0.18551638 | K56: =Inputs!$C$14*(1-Inputs!$C$21)*K22 -> 0.21081406 | L56: =Inputs!$C$14*(1-Inputs!$C$21)*L22 -> 0.21081406 | ... S56: =Inputs!$C$14*(1-Inputs!$C$21)*S22 -> 0.23611175
A57: Cost to win a client through Instagram (all ads / Instagram clients) | B57: Rp m | E57: =IF(E23=0,0,($K$17+Pay_Plan!E12)/E23) -> 0.47852785 | F57: =IF(F23=0,0,($K$17+Pay_Plan!F12)/F23) -> 0.45674584 | G57: =IF(G23=0,0,($K$17+Pay_Plan!G12)/G23) -> 0.43595533 | H57: =IF(H23=0,0,($K$17+Pay_Plan!H12)/H23) -> 1.5089718 | I57: =IF(I23=0,0,($K$17+Pay_Plan!I12)/I23) -> 1.4008053 | J57: =IF(J23=0,0,($K$17+Pay_Plan!J12)/J23) -> 1.3003925 | K57: =IF(K23=0,0,($K$17+Pay_Plan!K12)/K23) -> 0.98631787 | L57: =IF(L23=0,0,($K$17+Pay_Plan!L12)/L23) -> 0.90840653 | ... S57: =IF(S23=0,0,($K$17+Pay_Plan!S12)/S23) -> 0.44805452
A58: LTV / CAC, Instagram | B58: x | E58: =IF(E57=0,0,E56/E57) -> 0.35243769 | F58: =IF(F57=0,0,F56/F57) -> 0.36924529 | G58: =IF(G57=0,0,G56/G57) -> 0.38685443 | H58: =IF(H57=0,0,H56/H57) -> 0.12294224 | I58: =IF(I57=0,0,I56/I57) -> 0.13243552 | J58: =IF(J57=0,0,J56/J57) -> 0.14266183 | K58: =IF(K57=0,0,K56/K57) -> 0.21373846 | L58: =IF(L57=0,0,L56/L57) -> 0.23207018 | ... S58: =IF(S57=0,0,S56/S57) -> 0.52697103
A59: LTV / CAC, referral | B59: x | E59: =E56/$C$17 -> 0.84325625 | F59: =F56/$C$17 -> 0.84325625 | G59: =G56/$C$17 -> 0.84325625 | H59: =H56/$C$17 -> 0.92758188 | I59: =I56/$C$17 -> 0.92758188 | J59: =J56/$C$17 -> 0.92758188 | K59: =K56/$C$17 -> 1.0540703 | L59: =L56/$C$17 -> 1.0540703 | ... S59: =S56/$C$17 -> 1.1805588

Sheet B2C_Pricing
A1: B2C prices: psychologist tiers and profit share (latest price list, 13 Oct 2026)
A2: Source: B2C Pricing/TJ_Pricing_Tier_Psikolog_Profit_Sharing.xlsx (Pricing_Counseling, Inputs). Blue = copy of that file; change both together. Rp million per session. Feeds Inputs b2c_p_new and b2c_f_new.
A4: Tier (psychologist experience) | B4: Online 60 min price | C4: Offline 60 min price | D4: Share to psychologist | E4: Share of sessions (mix) | F4: Fee online | G4: Fee offline | H4: TJ margin online | I4: TJ margin offline
A5: Tier 1 (0-2 years) | B5: 0.5 | C5: 0.58 | D5: 0.6 | E5: 0.3 | F5: =B5*D5 -> 0.3 | G5: =C5*D5 -> 0.348 | H5: =B5-F5 -> 0.2 | I5: =C5-G5 -> 0.232
A6: Tier 2 (2-5 years) | B6: 0.5 | C6: 0.58 | D6: 0.65 | E6: 0.35 | F6: =B6*D6 -> 0.325 | G6: =C6*D6 -> 0.377 | H6: =B6-F6 -> 0.175 | I6: =C6-G6 -> 0.203
A7: Tier 3 (5-10 years) | B7: 0.725 | C7: 0.8 | D7: 0.65 | E7: 0.25 | F7: =B7*D7 -> 0.47125 | G7: =C7*D7 -> 0.52 | H7: =B7-F7 -> 0.25375 | I7: =C7-G7 -> 0.28
A8: Tier 4 (over 10 years) | B8: 0.85 | C8: 0.925 | D8: 0.7 | E8: 0.1 | F8: =B8*D8 -> 0.595 | G8: =C8*D8 -> 0.6475 | H8: =B8-F8 -> 0.255 | I8: =C8-G8 -> 0.2775
A9: Check: mix adds to 100% | E9: =IF(ABS(SUM(E5:E8)-1)<0.0001,"OK","CHECK") -> OK
A11: Share of sessions online (rest offline) | B11: 0.7 | C11: Estimate: fill from real bookings
A12: Platform and payment cost per session (paid by TJ) | B12: 0.05 | C12: Estimate: pricing file default (Rp50k)
A13: 4-session package discount | B13: 0.1 | C13: Known: ACC sheet, ~10%
A14: Share of clients on the 4-session package | B14: =Inputs!$C$136 -> 0 | C14: Inputs b2c_pack (0 = price list as is)
A15: Blended result (feeds the model)
A16: Average list price per session | B16: =SUMPRODUCT(E5:E8,B5:B8)*B11+SUMPRODUCT(E5:E8,C5:C8)*(1-B11) -> 0.614725
A17: Average psychologist fee per session | B17: =SUMPRODUCT(E5:E8,F5:F8)*B11+SUMPRODUCT(E5:E8,G5:G8)*(1-B11) -> 0.39607375
A18: Average price actually paid (after package discount) | B18: =B16*(1-B14*B13) -> 0.614725
A19: Psychologist fee on the price paid (profit share is on the price paid) | B19: =B17*(1-B14*B13) -> 0.39607375
A20: TJ margin per session after platform cost | B20: =B18-B19-B12 -> 0.16865125
A21: Cost share used by the model: (fee + platform) / price | B21: =(B19+B12)/B18 -> 0.72564765
A22: v15 for comparison: price, and TJ margin per session | B22: =Inputs!$C$134 -> 1
A23: v15 TJ margin per session (Rp1m x 60%) | B23: =Inputs!$C$134*(1-Inputs!$C$135) -> 0.6
A24: New margin vs v15 margin | B24: =B20/B23-1 -> -0.71891458
A26: Reference: assessments (one price for all assessors, 50:50 share after the test-tool cost)
A27: Tes Minat Bakat (interest and aptitude) | B27: 1.625 | C27: 14+
A28: Tes IQ | B28: 0.725 | C28: child to adult
A29: Tes Profiling | B29: 1.225 | C29: 6-13
A30: MHCU (adult mental health check) | B30: 0.375 | C30: adult
A32: Read: the latest price list earns about Rp170k per session after the psychologist and platform, against Rp600k in v15. Counseling alone cannot pay for Instagram ads (see B2C rows 56-59); it pays when clients come through EAP, schools and referral.

Sheet Channels
A1: Channels (v16): EAP packages for BI regional offices, and schools
A2: Package prices and costs: SPKnProposalAnalysis/BI Sibolga/Internal_-_BI_Sibolga_Costing_format_TJ_v4.xlsx (costs with every session paid at the Rp350k honor; before the 2% PPh 23 withholding). Rp million.
A4: BI KPw package (3 months) | B4: Price | C4: Cost (all sessions paid) | D4: Counseling sessions | E4: Mix (blue) | F4: Margin | G4: Price / cost | H4: Price for a 30% margin | I4: Gap to that price
A5: Sapa (intro: 15 sessions) | B5: 7.5 | C5: 5.925 | D5: 15 | E5: 0.25 | F5: =1-C5/B5 -> 0.21 | G5: =B5/C5 -> 1.2658228 | H5: =C5/(1-0.3) -> 8.4642857 | I5: =MAX(0,H5-B5) -> 0.96428571
A6: Tumbuh (24 sessions + MHCU + report) | B6: 14 | C6: 10.7 | D6: 24 | E6: 0.35 | F6: =1-C6/B6 -> 0.23571429 | G6: =B6/C6 -> 1.3084112 | H6: =C6/(1-0.3) -> 15.285714 | I6: =MAX(0,H6-B6) -> 1.2857143
A7: Seperjalanan (36 sessions + 2 MHCU + webinar + 2 penyuluhan) | B7: 23 | C7: 16.64 | D7: 36 | E7: 0.25 | F7: =1-C7/B7 -> 0.27652174 | G7: =B7/C7 -> 1.3822115 | H7: =C7/(1-0.3) -> 23.771429 | I7: =MAX(0,H7-B7) -> 0.77142857
A8: Berbagi (Seperjalanan, webinar free) | B8: 20 | C8: 18.74 | D8: 36 | E8: 0.05 | F8: =1-C8/B8 -> 0.063 | G8: =B8/C8 -> 1.0672359 | H8: =C8/(1-0.3) -> 26.771429 | I8: =MAX(0,H8-B8) -> 6.7714286
A9: Penyuluhan (Seperjalanan, no webinar) | B9: 20 | C9: 16.64 | D9: 36 | E9: 0.1 | F9: =1-C9/B9 -> 0.168 | G9: =B9/C9 -> 1.2019231 | H9: =C9/(1-0.3) -> 23.771429 | I9: =MAX(0,H9-B9) -> 3.7714286
A10: Average package (mix-weighted) | B10: =SUMPRODUCT($E$5:$E$9,B5:B9) -> 15.525 | C10: =SUMPRODUCT($E$5:$E$9,C5:C9) -> 11.98725 | D10: =SUMPRODUCT($E$5:$E$9,D5:D9) -> 26.55 | E10: =SUM(E5:E9) -> 1 | F10: =1-C10/B10 -> 0.2278744 | G10: =B10/C10 -> 1.2951261
A11: Read: with every session paid at Rp350k the packages earn 7-27%, far below the 3x rule for training. They make money only when the paid part-timers deliver the sessions inside their fixed pay. Next offices: price Tumbuh and Seperjalanan at or above column H, and keep Sapa as the small intro.
A13: Monthly plan (blue = change freely)
A14: Line | B14: Unit | C14: Q4 2026 | D14: FY 2027 | E14: =Volume!E4 -> Oct-26 | F14: =Volume!F4 -> Nov-26 | G14: =Volume!G4 -> Dec-26 | H14: =Volume!H4 -> Jan-27 | I14: =Volume!I4 -> Feb-27 | J14: =Volume!J4 -> Mar-27 | K14: =Volume!K4 -> Apr-27 | L14: =Volume!L4 -> May-27 | ... S14: =Volume!S4 -> Dec-27
A15: New BI KPw packages signed (new offices; Nov-26 = Sibolga) | B15: packages | C15: =SUM(E15:G15) -> 1 | D15: =SUM(H15:S15) -> 10 | E15: 0 | F15: 1 | G15: 0 | H15: 0 | I15: 1 | J15: 1 | K15: 1 | L15: 1 | M15: 0 | N15: 1 | O15: 1 | P15: 1 | Q15: 2 | R15: 1 | S15: 0
A16: Schools tested (group interest and aptitude test; Feb pilot, Jul grade 10, Aug-Nov grade 12) | B16: schools | C16: =SUM(E16:G16) -> 0 | D16: =SUM(H16:S16) -> 6 | E16: 0 | F16: 0 | G16: 0 | H16: 0 | I16: 1 | J16: 0 | K16: 0 | L16: 0 | M16: 0 | N16: 1 | O16: 1 | P16: 1 | Q16: 1 | R16: 1 | S16: 0
A18: Why these dates: BI KPw offices spend their own yearly budget, most of it in the second half; schools test grade 10 before the major choice (Jun-Jul) and grade 12 before college applications (Aug-Nov).

Sheet Inputs
A1: Inputs and assumptions (all money in Rp million)
A2: Blue numbers are inputs you can change. Status: Known = you told us or it is in your v10 file; Your plan = your own budget; Estimate = industry estimate used until you give the real number (yellow-shaded, listed in the To_Fill sheet).
A4: Key | B4: Item | C4: Value | D4: Unit | E4: Status | F4: Source / logic
A5: 0. Scenario selector
A6: scen | B6: Active scenario (1-4) | C6: 1 | D6: number | E6: Known | F6: 1 = Base plan (v10 volumes). 2 = No new B2B event closes Jan-Jun 2027. 3 = BI cuts its volume by the % below. 4 = Both 2 and 3 (worst case).
A7: bi_cut | B7: BI volume cut used in scenarios 3 and 4 | C7: 0.3 | D7: % | E7: Known | F7: Stress test size. Change freely.
A8: 1. Prices (per event, or per month for EAP)
A9: p_flag | B9: Flagship regulator ToT (CBP Rupiah) | C9: 85 | D9: Rp m / event | E9: Known | F9: Your v10 file.
A10: p_kpw | B10: Regulator regional ToT (BI KPW and LPS) | C10: 20 | D10: Rp m / event | E10: Known | F10: Your v10 file.
A11: p_kcp | B11: Bank branch event (KCP) | C11: 35 | D11: Rp m / event | E11: Known | F11: Your v10 file.
A12: p_eap | B12: Bank EAP subscription | C12: 15 | D12: Rp m / month | E12: Known | F12: Your v10 file.
A13: p_b2ce | B13: B2C mass event | C13: =IF(Inputs!$C$131=1,Inputs!$C$137,Inputs!$C$139) -> 4.144 | D13: Rp m / event | E13: Known | F13: v16: Lyfe at 30s format (Inputs section 14). v15: your v10 file.
A14: p_b2cc | B14: B2C counseling client | C14: =IF(Inputs!$C$131=1,Inputs!$C$132,Inputs!$C$134) -> 0.614725 | D14: Rp m / client | E14: Known | F14: v16: latest price list (B2C_Pricing sheet). v15: Rp1,000,000 per session.
A15: 2. Delivery cost (cost of goods sold)
A16: c_flag | B16: Flagship delivery cost | C16: 25 | D16: Rp m / event | E16: Known | F16: Your v10 file: travel, hotel, materials, premium facilitator fees.
A17: c_kpw | B17: KPW / LPS delivery cost | C17: 8 | D17: Rp m / event | E17: Known | F17: Your v10 file. Covers about 2 handler fees only, so travel is assumed paid by the client (see below).
A18: c_kcp | B18: Bank KCP event delivery cost | C18: 12 | D18: Rp m / event | E18: Known | F18: Your v10 file.
A19: c_eap | B19: EAP delivery cost | C19: 5 | D19: Rp m / month | E19: Known | F19: Your v10 file: on-call tele-counseling retainer.
A20: c_b2ce | B20: B2C event delivery cost | C20: =IF(Inputs!$C$131=1,Inputs!$C$138,Inputs!$C$140) -> 2.73 | D20: Rp m / event | E20: Known | F20: v16: Lyfe RAB at 16 people. v15: venue, ads, materials, fees.
A21: c_b2cc | B21: B2C counseling cost (psychologist fee) | C21: =IF(Inputs!$C$131=1,Inputs!$C$133,Inputs!$C$135) -> 0.72564765 | D21: % of price | E21: Known | F21: v16: psychologist share by tier + platform cost (B2C_Pricing). v15: Rp400k of Rp1m.
A22: travel_client | B22: Client pays travel for regional events? (1 = yes, 0 = no) | C22: 1 | D22: switch | E22: Estimate | F22: The Rp 8m KPW cost only covers 2 handler fees, so we assume BI pays travel.
A23: travel_pp | B23: Travel cost per handler per regional trip | C23: 3.5 | D23: Rp m / person | E23: Estimate | F23: Industry estimate: return flight ~Rp 2m + 2 hotel nights ~Rp 1m + per diem ~Rp 0.5m.
A24: regional_share | B24: Share of KPW / LPS events outside Jakarta | C24: 0.8 | D24: % | E24: Estimate | F24: Estimate: most KPW offices are outside Jakarta.
A25: 3. Delivery staffing (from your v10 file)
A26: h_flag | B26: Handlers per Flagship event | C26: 4 | D26: people | E26: Known | F26: 1 PM, 1 Lead Psychologist, 2 Facilitators.
A27: h_kpw | B27: Handlers per KPW / LPS event | C27: 2 | D27: people | E27: Known | F27: 1 Lead, 1 Facilitator.
A28: h_kcp | B28: Handlers per KCP event | C28: 2 | D28: people | E28: Known | F28: 1 Lead, 1 Facilitator.
A29: h_b2ce | B29: Handlers per B2C event | C29: 2 | D29: people | E29: Known | F29: 1 Lead, 1 Facilitator / Assistant.
A30: d_flag | B30: Days per Flagship event | C30: 3 | D30: days | E30: Estimate | F30: You said 2-3 day program; we use 3.
A31: d_kpw | B31: Days per KPW / LPS event | C31: 1 | D31: days | E31: Estimate | F31: Estimate.
A32: d_kcp | B32: Days per KCP event | C32: 1 | D32: days | E32: Estimate | F32: Estimate.
A33: d_b2ce | B33: Days per B2C event | C33: 1 | D33: days | E33: Estimate | F33: Estimate (weekend event).
A34: fac_cap | B34: Max events per facilitator per month | C34: 2 | D34: events | E34: Known | F34: Your v10 quality rule.
A35: fac_now | B35: Certified facilitators today | C35: 2 | D35: people | E35: Known | F35: You told us: 2 active core facilitators.
A36: fac_plan | B36: Your plan: facilitators certified by Nov 2026 | C36: 11 | D36: people | E36: Known | F36: Your earlier plan.
A37: cert_cost | B37: Cost to certify one new facilitator | C37: 2.5 | D37: Rp m / person | E37: Estimate | F37: Industry estimate: 2-day internal ToT, materials, observed practice event.
A38: 4. Fixed cost: base (your 2027 'bensin' budget, monthly)
A39: o_lead_mkt | B39: Lead Marketing | C39: 2.5 | D39: Rp m / month | E39: Known | F39: Your 2027 budget.
A40: o_socmed | B40: Social Media Specialist | C40: 1.5 | D40: Rp m / month | E40: Known | F40: Your 2027 budget.
A41: o_intern_mkt | B41: Marketing intern | C41: 1 | D41: Rp m / month | E41: Known | F41: Your 2027 budget.
A42: o_pic | B42: PIC Psychologist | C42: 2.3 | D42: Rp m / month | E42: Known | F42: Your 2027 budget.
A43: o_admin | B43: Admin | C43: 3 | D43: Rp m / month | E43: Known | F43: You raised it from Rp 1.8m to Rp 3m (Oct 2026).
A44: o_intern_ops | B44: Operations intern | C44: 1 | D44: Rp m / month | E44: Known | F44: Your 2027 budget.
A45: o_saas | B45: Software and IG ads (Workspace, Canva, Claude, CapCut, IG ads, Zoom) | C45: 2.0799167 | D45: Rp m / month | E45: Known | F45: Your 2027 budget: Rp 24.959m per year / 12.
A46: o_office | B46: Office (rent 5.0 + electricity 0.5 + meals 0.3) | C46: 5.8 | D46: Rp m / month | E46: Known | F46: Your 2027 budget: Rp 69.6m per year / 12.
A47: o_acct | B47: Accountant / tax consultant | C47: 1.5 | D47: Rp m / month | E47: Estimate | F47: Industry estimate for a small PT in Jakarta. Not in your list; set to 0 if you do it yourself.
A48: 5. Fixed cost: steps (only switched on when triggered)
A49: f_sal1 | B49: Founder salary: co-founder | C49: 15 | D49: Rp m / month | E49: Known | F49: You set this (Oct 2026).
A50: f_sal2 | B50: Founder salary: Galih | C50: 10 | D50: Rp m / month | E50: Known | F50: You set this (Oct 2026).
A51: f_start | B51: Founder salaries start month | C51: Jan-27 | D51: month | E51: Your plan - confirm | F51: Your 2027 goal. Must match a month label exactly (e.g. Jan-27).
A52: am_on | B52: Hire a B2B Account Manager? (1 = yes) | C52: 0 | D52: switch | E52: Known | F52: You decided: founders handle accounts for now. Set 1 to test hiring one later.
A53: am_cost | B53: Account Manager salary | C53: 7 | D53: Rp m / month | E53: Known | F53: Your Rp 35m plan.
A54: am_start | B54: B2B sales push start month (and AM start, if hired) | C54: Jan-27 | D54: month | E54: Estimate | F54: Founders start selling to LPS, OJK and banks. Must match a month label.
A55: sales_travel | B55: Sales travel and meetings (from sales start month) | C55: 2 | D55: Rp m / month | E55: Estimate | F55: Industry estimate: 2 regional or bank HQ trips a month + meeting costs.
A56: pm_cost | B56: Project Manager salary | C56: 5 | D56: Rp m / month | E56: Known | F56: Your Rp 35m plan.
A57: pm_thr | B57: PM trigger: average B2B events per month (last 3 months) at or above | C57: 4 | D57: events | E57: Estimate | F57: Step rule: when the 3-month average reaches this, hire the PM next month. Once hired, the PM stays.
A58: adm2_thr | B58: Second admin trigger: invoices per month above | C58: 12 | D58: invoices | E58: Estimate | F58: Step rule: invoicing on time protects the KPW payday cutoff.
A59: corp_inv | B59: Invoices per month from small corporate clients | C59: 1.33 | D59: invoices | E59: Estimate | F59: You have about 4 small clients, mostly quarterly: 4 / 3 per month.
A60: 6. Coreitera and Theta (charges between your own companies)
A61: core_in_cogs | B61: Coreitera fee already inside the delivery costs above? (1 = yes) | C61: 1 | D61: switch | E61: Estimate | F61: Assumed yes. If 0, the fee is added on top of event cost.
A62: core_fee | B62: Coreitera fee per assessment | C62: 0.075 | D62: Rp m / participant | E62: Estimate | F62: Industry estimate for online B2B psychometric assessment in Indonesia: Rp 50k-150k. We use Rp 75k.
A63: pax_flag | B63: Participants per Flagship event | C63: 40 | D63: people | E63: Estimate | F63: Estimate.
A64: pax_kpw | B64: Participants per KPW / LPS event | C64: 30 | D64: people | E64: Estimate | F64: Estimate.
A65: pax_kcp | B65: Participants per KCP event | C65: 40 | D65: people | E65: Estimate | F65: Estimate.
A66: pax_b2ce | B66: Participants per B2C event | C66: 50 | D66: people | E66: Estimate | F66: Estimate.
A67: theta_fee | B67: Theta fee per counseling allocation | C67: 0.05 | D67: Rp m / session | E67: Estimate | F67: Industry estimate for a platform fee per session. Shown as a memo only.
A68: eap_sessions | B68: Counseling sessions per EAP contract per month | C68: 10 | D68: sessions | E68: Estimate | F68: Estimate.
A69: 7. Customer acquisition (B2B)
A70: new_logos | B70: New B2B clients won in 2027 (LPS, OJK, banks) | C70: 4 | D70: clients | E70: Estimate | F70: Your strategy: LPS and OJK, then banks such as BRI and Mandiri. Estimate: 2 regulators + 2 banks.
A71: 8. Cash timing
A72: cash0 | B72: Cash in bank at 1 Oct 2026 | C72: 210 | D72: Rp m | E72: Known | F72: You told us. Assumed free cash: no unpaid bills and no money owed to you.
A73: flag_s0 | B73: BI central (Flagship): paid same month | C73: 0.6 | D73: % | E73: Estimate | F73: You said most clients pay the same month, never later than 60 days.
A74: flag_s30 | B74: BI central (Flagship): paid after ~30 days | C74: 0.3 | D74: % | E74: Estimate | F74: As above.
A75: flag_s60 | B75: BI central (Flagship): paid after ~60 days | C75: 0.1 | D75: % | E75: Estimate | F75: As above.
A76: kpw_cut | B76: KPW / LPS: share of invoices sent before the payday cutoff | C76: 0.8 | D76: % | E76: Estimate | F76: Known rule: BI pays on the 1st; invoice before cutoff = paid that cycle, after = next month. Share is an estimate.
A77: bank_s0 | B77: Banks (KCP events): paid same month | C77: 0.2 | D77: % | E77: Estimate | F77: No bank client yet, so we assume slower than BI.
A78: bank_s30 | B78: Banks (KCP events): paid after ~30 days | C78: 0.5 | D78: % | E78: Estimate | F78: As above.
A79: bank_s60 | B79: Banks (KCP events): paid after ~60 days | C79: 0.3 | D79: % | E79: Estimate | F79: As above.
A80: tax_rate | B80: Income tax on revenue (final tax, PP 55/2022) | C80: 0.005 | D80: % of revenue | E80: Estimate | F80: Assumes the 0.5% small-business final tax and that prices exclude VAT. Paid the next month.
A81: 9. Targets and concentration
A82: target_margin | B82: Target net profit margin for 2027 | C82: 0.15 | D82: % | E82: Estimate | F82: Your goal is to 'look profitable'. 15% used until you set a number.
A83: bi_share_kpw | B83: Share of 'KPW and LPS' events that are BI (rest is LPS / OJK) | C83: 0.85 | D83: % | E83: Estimate | F83: BI is 70% of revenue today; LPS / OJK are new in 2027.
A84: 10. Rate card - elite boutique pricing (used when price plan = 2)
A85: plan | B85: Active price plan (1 = current prices, 2 = new rate card) | C85: 2 | D85: number | E85: Known | F85: Switch to compare old and new prices.
A86: np_start | B86: New prices start month | C86: Jan-27 | D86: month | E86: Your plan - confirm | F86: Q4 2026 work is already agreed at old prices. Must match a month label.
A87: np_flag | B87: New price: Flagship regulator ToT (3 days, training part) | C87: 94 | D87: Rp m / program | E87: Your plan - confirm | F87: About 2x the SBM fee budget for 3 days (~Rp50m); regulators assumed to allow a bit more than SBM.
A88: np_kpw | B88: New price: KPW / LPS regional ToT (1 day, training part) | C88: 24 | D88: Rp m / event | E88: Your plan - confirm | F88: Brings KPW to your 3x rule. About 1.9x the SBM fee budget for 1 day (~Rp12.6m).
A89: np_bumn | B89: New price: state-owned bank, per group per day | C89: 45 | D89: Rp m / day | E89: Your plan - confirm | F89: About half of what big trainers charge banks (2-3x your old rate). Tender pressure keeps it below private banks.
A90: np_priv | B90: New price: private big bank, per group per day | C90: 55 | D90: Rp m / day | E90: Your plan - confirm | F90: About 60% of the big-trainer rate: elite boutique = clearly cheaper than big firms, never the cheapest.
A91: priv_share | B91: Share of 2027 bank events with private banks | C91: 0.25 | D91: % | E91: Estimate | F91: Your plan starts with state banks; 1 in 4 bank events assumed private.
A92: assess_price | B92: Assessment and impact report, price per participant | C92: 0.15 | D92: Rp m / person | E92: Your plan - confirm | F92: Sold as its own line (BI confirmed this is allowed). Pre- and post-assessment by Coreitera + impact report.
A93: as_flag | B93: Sell assessment with Flagship? (1 = yes) | C93: 1 | D93: switch | E93: Known | F93: BI accepts it as a separate line.
A94: as_kpw | B94: Sell assessment with KPW / LPS? (1 = yes) | C94: 1 | D94: switch | E94: Known | F94: BI accepts it as a separate line.
A95: as_kcp | B95: Sell assessment with bank events? (1 = yes) | C95: 1 | D95: switch | E95: Your plan - confirm | F95: Banks have not been asked yet.
A96: bt_mult | B96: Big trainers charge banks this multiple of your old bank rate | C96: 2.5 | D96: x | E96: Known | F96: You said 2-3x; midpoint used.
A97: elite_up | B97: Elite package uplift over Signature package | C97: 0.3 | D97: % | E97: Estimate | F97: Elite adds a cascade licence and 3 months of trainer follow-up.
A98: vol_keep | B98: B2B volume kept after the price change | C98: 1 | D98: % | E98: Estimate | F98: 100% = no client lost. Lower it to test the risk; see the volume-loss table on Rate_Card.
A100: 11. Timing - when new sales really start (v15)
A101: pipe_on | B101: Pipeline-first timing? (1 = no new sales before the month below) | C101: 1 | D101: switch | E101: Your plan - confirm | F101: Oct 2026 to Feb 2027 is used to pitch and sign. Existing EAP and counseling clients continue.
A102: sales_from | B102: First month new events are delivered | C102: Mar-27 | D102: month | E102: Your plan - confirm | F102: Must match a month label (e.g. Mar-27). Earlier months get no new B2B events.
...

Sheet Pay_Plan
A1: Pay plan: gross pay a month for every role (Rp million). Blue cells are your decisions; change them freely.
A2: Decided 5 Oct 2026: BPJS + THR from Jan-27; social media up in steps; admin to the minimum wage from Jul-27; lead marketing capped at Rp4m in 2027 (KPI: 10k IG followers) with Rp3.5m of her budget moved to ads; admin paid per client (Rp1.8m base + Rp17k a client + Rp620k bonus); pay rises for admin, social media and lead marketing unlock when sales targets are met (rows 27-30), not by date; psychologist stays part-time (no full-time hire for now); a non-psychologist Lead Partnership from Oct-27; IG ads today Rp1m (software budget) + Rp3.5m moved from lead marketing; founders: only one is paid today (Rp10m); Rp25m from Mar-27 keeps room for the second founder, whose start is still to decide.
A4: Line | B4: Unit | C4: Q4 2026 | D4: FY 2027 | E4: =Volume!E4 -> Oct-26 | F4: =Volume!F4 -> Nov-26 | G4: =Volume!G4 -> Dec-26 | H4: =Volume!H4 -> Jan-27 | I4: =Volume!I4 -> Feb-27 | J4: =Volume!J4 -> Mar-27 | K4: =Volume!K4 -> Apr-27 | L4: =Volume!L4 -> May-27 | ... S4: =Volume!S4 -> Dec-27
A5: Gross pay a month (blue = your input)
A6: Admin (formula: base + fee per client + weekly bonus; minimum wage once step 2 is unlocked) | B6: Rp m | C6: =SUM(E6:G6) -> 7.5966403 | D6: =SUM(H6:S6) -> 56.421724 | E6: =IF(E30>=2,MAX(Inputs!$C$122,Inputs!$C$118+Inputs!$C$119*(Volume!E28+Volume!E26*Inputs!$C$68+Volume!E43)+IF((Volume!E28+Volume!E26*Inputs!$C$68+Volume!E43)>=Inputs!$C$121,Inputs!$C$120,0)),Inputs!$C$118+Inputs!$C$119*(Volume!E28+Volume!E26*Inputs!$C$68+Volume!E43)+IF((Volume!E28+Volume!E26*Inputs!$C$68+Volume!E43)>=Inputs!$C$121,Inputs!$C$120,0)) -> 2.0055256 | F6: =IF(F30>=2,MAX(Inputs!$C$122,Inputs!$C$118+Inputs!$C$119*(Volume!F28+Volume!F26*Inputs!$C$68+Volume!F43)+IF((Volume!F28+Volume!F26*Inputs!$C$68+Volume!F43)>=Inputs!$C$121,Inputs!$C$120,0)),Inputs!$C$118+Inputs!$C$119*(Volume!F28+Volume!F26*Inputs!$C$68+Volume!F43)+IF((Volume!F28+Volume!F26*Inputs!$C$68+Volume!F43)>=Inputs!$C$121,Inputs!$C$120,0)) -> 2.7946698 | G6: =IF(G30>=2,MAX(Inputs!$C$122,Inputs!$C$118+Inputs!$C$119*(Volume!G28+Volume!G26*Inputs!$C$68+Volume!G43)+IF((Volume!G28+Volume!G26*Inputs!$C$68+Volume!G43)>=Inputs!$C$121,Inputs!$C$120,0)),Inputs!$C$118+Inputs!$C$119*(Volume!G28+Volume!G26*Inputs!$C$68+Volume!G43)+IF((Volume!G28+Volume!G26*Inputs!$C$68+Volume!G43)>=Inputs!$C$121,Inputs!$C$120,0)) -> 2.7964448 | H6: =IF(H30>=2,MAX(Inputs!$C$122,Inputs!$C$118+Inputs!$C$119*(Volume!H28+Volume!H26*Inputs!$C$68+Volume!H43)+IF((Volume!H28+Volume!H26*Inputs!$C$68+Volume!H43)>=Inputs!$C$121,Inputs!$C$120,0)),Inputs!$C$118+Inputs!$C$119*(Volume!H28+Volume!H26*Inputs!$C$68+Volume!H43)+IF((Volume!H28+Volume!H26*Inputs!$C$68+Volume!H43)>=Inputs!$C$121,Inputs!$C$120,0)) -> 2.8161515 | I6: =IF(I30>=2,MAX(Inputs!$C$122,Inputs!$C$118+Inputs!$C$119*(Volume!I28+Volume!I26*Inputs!$C$68+Volume!I43)+IF((Volume!I28+Volume!I26*Inputs!$C$68+Volume!I43)>=Inputs!$C$121,Inputs!$C$120,0)),Inputs!$C$118+Inputs!$C$119*(Volume!I28+Volume!I26*Inputs!$C$68+Volume!I43)+IF((Volume!I28+Volume!I26*Inputs!$C$68+Volume!I43)>=Inputs!$C$121,Inputs!$C$120,0)) -> 3.1558053 | J6: =IF(J30>=2,MAX(Inputs!$C$122,Inputs!$C$118+Inputs!$C$119*(Volume!J28+Volume!J26*Inputs!$C$68+Volume!J43)+IF((Volume!J28+Volume!J26*Inputs!$C$68+Volume!J43)>=Inputs!$C$121,Inputs!$C$120,0)),Inputs!$C$118+Inputs!$C$119*(Volume!J28+Volume!J26*Inputs!$C$68+Volume!J43)+IF((Volume!J28+Volume!J26*Inputs!$C$68+Volume!J43)>=Inputs!$C$121,Inputs!$C$120,0)) -> 3.2601381 | K6: =IF(K30>=2,MAX(Inputs!$C$122,Inputs!$C$118+Inputs!$C$119*(Volume!K28+Volume!K26*Inputs!$C$68+Volume!K43)+IF((Volume!K28+Volume!K26*Inputs!$C$68+Volume!K43)>=Inputs!$C$121,Inputs!$C$120,0)),Inputs!$C$118+Inputs!$C$119*(Volume!K28+Volume!K26*Inputs!$C$68+Volume!K43)+IF((Volume!K28+Volume!K26*Inputs!$C$68+Volume!K43)>=Inputs!$C$121,Inputs!$C$120,0)) -> 3.5351949 | L6: =IF(L30>=2,MAX(Inputs!$C$122,Inputs!$C$118+Inputs!$C$119*(Volume!L28+Volume!L26*Inputs!$C$68+Volume!L43)+IF((Volume!L28+Volume!L26*Inputs!$C$68+Volume!L43)>=Inputs!$C$121,Inputs!$C$120,0)),Inputs!$C$118+Inputs!$C$119*(Volume!L28+Volume!L26*Inputs!$C$68+Volume!L43)+IF((Volume!L28+Volume!L26*Inputs!$C$68+Volume!L43)>=Inputs!$C$121,Inputs!$C$120,0)) -> 3.5444341 | ... S6: =IF(S30>=2,MAX(Inputs!$C$122,Inputs!$C$118+Inputs!$C$119*(Volume!S28+Volume!S26*Inputs!$C$68+Volume!S43)+IF((Volume!S28+Volume!S26*Inputs!$C$68+Volume!S43)>=Inputs!$C$121,Inputs!$C$120,0)),Inputs!$C$118+Inputs!$C$119*(Volume!S28+Volume!S26*Inputs!$C$68+Volume!S43)+IF((Volume!S28+Volume!S26*Inputs!$C$68+Volume!S43)>=Inputs!$C$121,Inputs!$C$120,0)) -> 5.73
A7: Social media specialist (formula: 1.5, then 3.0 / 4.5 / minimum wage at pay steps 1 / 2 / 3) | B7: Rp m | C7: =SUM(E7:G7) -> 4.5 | D7: =SUM(H7:S7) -> 44.19 | E7: =CHOOSE(E30+1,1.5,3,4.5,Inputs!$C$122) -> 1.5 | F7: =CHOOSE(F30+1,1.5,3,4.5,Inputs!$C$122) -> 1.5 | G7: =CHOOSE(G30+1,1.5,3,4.5,Inputs!$C$122) -> 1.5 | H7: =CHOOSE(H30+1,1.5,3,4.5,Inputs!$C$122) -> 1.5 | I7: =CHOOSE(I30+1,1.5,3,4.5,Inputs!$C$122) -> 1.5 | J7: =CHOOSE(J30+1,1.5,3,4.5,Inputs!$C$122) -> 1.5 | K7: =CHOOSE(K30+1,1.5,3,4.5,Inputs!$C$122) -> 1.5 | L7: =CHOOSE(L30+1,1.5,3,4.5,Inputs!$C$122) -> 3 | ... S7: =CHOOSE(S30+1,1.5,3,4.5,Inputs!$C$122) -> 5.73
A8: Lead marketing (formula: 2.5, then 4.0 cap at pay step 1; KPI 10k IG followers; has shares) | B8: Rp m | C8: =SUM(E8:G8) -> 7.5 | D8: =SUM(H8:S8) -> 42 | E8: =IF(E30>=1,4,2.5) -> 2.5 | F8: =IF(F30>=1,4,2.5) -> 2.5 | G8: =IF(G30>=1,4,2.5) -> 2.5 | H8: =IF(H30>=1,4,2.5) -> 2.5 | I8: =IF(I30>=1,4,2.5) -> 2.5 | J8: =IF(J30>=1,4,2.5) -> 2.5 | K8: =IF(K30>=1,4,2.5) -> 2.5 | L8: =IF(L30>=1,4,2.5) -> 4 | ... S8: =IF(S30>=1,4,2.5) -> 4
A9: Psychologists, paid part-time: PIC now + 1 more from Jan-27 (no full-time hire in 2027) | B9: Rp m | C9: =SUM(E9:G9) -> 6.9 | D9: =SUM(H9:S9) -> 55.2 | E9: 2.3 | F9: 2.3 | G9: 2.3 | H9: 4.6 | I9: 4.6 | J9: 4.6 | K9: 4.6 | L9: 4.6 | M9: 4.6 | N9: 4.6 | O9: 4.6 | P9: 4.6 | Q9: 4.6 | R9: 4.6 | S9: 4.6
A10: Interns, not Magang (2 people) | B10: Rp m | C10: =SUM(E10:G10) -> 6 | D10: =SUM(H10:S10) -> 24 | E10: 2 | F10: 2 | G10: 2 | H10: 2 | I10: 2 | J10: 2 | K10: 2 | L10: 2 | M10: 2 | N10: 2 | O10: 2 | P10: 2 | Q10: 2 | R10: 2 | S10: 2
A11: Founders: Rp10m now (one founder paid); Rp25m from Mar-27 = room for both (second founder's start: to decide) | B11: Rp m | C11: =SUM(E11:G11) -> 30 | D11: =SUM(H11:S11) -> 270 | E11: 10 | F11: 10 | G11: 10 | H11: 10 | I11: 10 | J11: 25 | K11: 25 | L11: 25 | M11: 25 | N11: 25 | O11: 25 | P11: 25 | Q11: 25 | R11: 25 | S11: 25
A12: Extra IG ads (Rp3.5m moved from lead marketing; Rp1m is already in the software budget) | B12: Rp m | C12: =SUM(E12:G12) -> 0 | D12: =SUM(H12:S12) -> 42 | E12: 0 | F12: 0 | G12: 0 | H12: 3.5 | I12: 3.5 | J12: 3.5 | K12: 3.5 | L12: 3.5 | M12: 3.5 | N12: 3.5 | O12: 3.5 | P12: 3.5 | Q12: 3.5 | R12: 3.5 | S12: 3.5
A13: Lead Partnership, non-psychologist (formula: from Inputs) | B13: Rp m | C13: =SUM(E13:G13) -> 0 | D13: =SUM(H13:S13) -> 18 | E13: =IF(Volume!E6>=IFERROR(MATCH(Inputs!$C$125,Volume!$E$4:$S$4,0),99),Inputs!$C$124,0) -> 0 | F13: =IF(Volume!F6>=IFERROR(MATCH(Inputs!$C$125,Volume!$E$4:$S$4,0),99),Inputs!$C$124,0) -> 0 | G13: =IF(Volume!G6>=IFERROR(MATCH(Inputs!$C$125,Volume!$E$4:$S$4,0),99),Inputs!$C$124,0) -> 0 | H13: =IF(Volume!H6>=IFERROR(MATCH(Inputs!$C$125,Volume!$E$4:$S$4,0),99),Inputs!$C$124,0) -> 0 | I13: =IF(Volume!I6>=IFERROR(MATCH(Inputs!$C$125,Volume!$E$4:$S$4,0),99),Inputs!$C$124,0) -> 0 | J13: =IF(Volume!J6>=IFERROR(MATCH(Inputs!$C$125,Volume!$E$4:$S$4,0),99),Inputs!$C$124,0) -> 0 | K13: =IF(Volume!K6>=IFERROR(MATCH(Inputs!$C$125,Volume!$E$4:$S$4,0),99),Inputs!$C$124,0) -> 0 | L13: =IF(Volume!L6>=IFERROR(MATCH(Inputs!$C$125,Volume!$E$4:$S$4,0),99),Inputs!$C$124,0) -> 0 | ... S13: =IF(Volume!S6>=IFERROR(MATCH(Inputs!$C$125,Volume!$E$4:$S$4,0),99),Inputs!$C$124,0) -> 6
A14: BPJS + THR paid on staff pay? (1 = yes) | B14: flag | C14: =MAX(E14:G14) -> 0 | D14: =MAX(H14:S14) -> 1 | E14: 0 | F14: 0 | G14: 0 | H14: 1 | I14: 1 | J14: 1 | K14: 1 | L14: 1 | M14: 1 | N14: 1 | O14: 1 | P14: 1 | Q14: 1 | R14: 1 | S14: 1
A15: Team cost incl. BPJS and THR (staff + psychologist + interns) | B15: Rp m | C15: =SUM(E15:G15) -> 32.49664 | D15: =SUM(H15:S15) -> 278.65783 | E15: =(E6+E7+E8+E9+E13)*(1+Inputs!$C$106*E14)+E10 -> 10.305526 | F15: =(F6+F7+F8+F9+F13)*(1+Inputs!$C$106*F14)+F10 -> 11.09467 | G15: =(G6+G7+G8+G9+G13)*(1+Inputs!$C$106*G14)+G10 -> 11.096445 | H15: =(H6+H7+H8+H9+H13)*(1+Inputs!$C$106*H14)+H10 -> 15.471059 | I15: =(I6+I7+I8+I9+I13)*(1+Inputs!$C$106*I14)+I10 -> 15.87185 | J15: =(J6+J7+J8+J9+J13)*(1+Inputs!$C$106*J14)+J10 -> 15.994963 | K15: =(K6+K7+K8+K9+K13)*(1+Inputs!$C$106*K14)+K10 -> 16.31953 | L15: =(L6+L7+L8+L9+L13)*(1+Inputs!$C$106*L14)+L10 -> 19.870432 | ... S15: =(S6+S7+S8+S9+S13)*(1+Inputs!$C$106*S14)+S10 -> 32.7508
A16: Total pay plan (team + founders + extra ads) | B16: Rp m | C16: =SUM(E16:G16) -> 62.49664 | D16: =SUM(H16:S16) -> 590.65783 | E16: =E15+E11+E12 -> 20.305526 | F16: =F15+F11+F12 -> 21.09467 | G16: =G15+G11+G12 -> 21.096445 | H16: =H15+H11+H12 -> 28.971059 | I16: =I15+I11+I12 -> 29.37185 | J16: =J15+J11+J12 -> 44.494963 | K16: =K15+K11+K12 -> 44.81953 | L16: =L15+L11+L12 -> 48.370432 | ... S16: =S15+S11+S12 -> 61.2508
A18: Running cost by group: all fixed costs a month (Rp million)
A19: Founders | B19: Rp m | C19: =SUM(E19:G19) -> 30 | D19: =SUM(H19:S19) -> 270 | E19: =Capacity_OPEX!E26 -> 10 | F19: =Capacity_OPEX!F26 -> 10 | G19: =Capacity_OPEX!G26 -> 10 | H19: =Capacity_OPEX!H26 -> 10 | I19: =Capacity_OPEX!I26 -> 10 | J19: =Capacity_OPEX!J26 -> 25 | K19: =Capacity_OPEX!K26 -> 25 | L19: =Capacity_OPEX!L26 -> 25 | ... S19: =Capacity_OPEX!S26 -> 25
A20: Team: staff, psychologist, interns, BPJS, THR | B20: Rp m | C20: =SUM(E20:G20) -> 32.49664 | D20: =SUM(H20:S20) -> 278.65783 | E20: =Capacity_OPEX!E22+Capacity_OPEX!E37 -> 10.305526 | F20: =Capacity_OPEX!F22+Capacity_OPEX!F37 -> 11.09467 | G20: =Capacity_OPEX!G22+Capacity_OPEX!G37 -> 11.096445 | H20: =Capacity_OPEX!H22+Capacity_OPEX!H37 -> 15.471059 | I20: =Capacity_OPEX!I22+Capacity_OPEX!I37 -> 15.87185 | J20: =Capacity_OPEX!J22+Capacity_OPEX!J37 -> 15.994963 | K20: =Capacity_OPEX!K22+Capacity_OPEX!K37 -> 16.31953 | L20: =Capacity_OPEX!L22+Capacity_OPEX!L37 -> 19.870432 | ... S20: =Capacity_OPEX!S22+Capacity_OPEX!S37 -> 32.7508
A21: Marketing: software and IG ads | B21: Rp m | C21: =SUM(E21:G21) -> 6.23975 | D21: =SUM(H21:S21) -> 69.587941 | E21: =Capacity_OPEX!E23+Capacity_OPEX!E38 -> 2.0799167 | F21: =Capacity_OPEX!F23+Capacity_OPEX!F38 -> 2.0799167 | G21: =Capacity_OPEX!G23+Capacity_OPEX!G38 -> 2.0799167 | H21: =Capacity_OPEX!H23+Capacity_OPEX!H38 -> 5.6113079 | I21: =Capacity_OPEX!I23+Capacity_OPEX!I38 -> 5.6137318 | J21: =Capacity_OPEX!J23+Capacity_OPEX!J38 -> 5.6163429 | K21: =Capacity_OPEX!K23+Capacity_OPEX!K38 -> 5.6813039 | L21: =Capacity_OPEX!L23+Capacity_OPEX!L38 -> 5.6899995 | ... S21: =Capacity_OPEX!S23+Capacity_OPEX!S38 -> 6.0820877
A22: Office and accountant | B22: Rp m | C22: =SUM(E22:G22) -> 21.9 | D22: =SUM(H22:S22) -> 87.6 | E22: =Capacity_OPEX!E24+Capacity_OPEX!E25 -> 7.3 | F22: =Capacity_OPEX!F24+Capacity_OPEX!F25 -> 7.3 | G22: =Capacity_OPEX!G24+Capacity_OPEX!G25 -> 7.3 | H22: =Capacity_OPEX!H24+Capacity_OPEX!H25 -> 7.3 | I22: =Capacity_OPEX!I24+Capacity_OPEX!I25 -> 7.3 | J22: =Capacity_OPEX!J24+Capacity_OPEX!J25 -> 7.3 | K22: =Capacity_OPEX!K24+Capacity_OPEX!K25 -> 7.3 | L22: =Capacity_OPEX!L24+Capacity_OPEX!L25 -> 7.3 | ... S22: =Capacity_OPEX!S24+Capacity_OPEX!S25 -> 7.3
A23: Sales and delivery support: co-founder, travel, project manager, 2nd admin, trainer training | B23: Rp m | C23: =SUM(E23:G23) -> 6 | D23: =SUM(H23:S23) -> 177.08 | E23: =Capacity_OPEX!E27+Capacity_OPEX!E28+Capacity_OPEX!E29+Capacity_OPEX!E30+Capacity_OPEX!E31+Capacity_OPEX!E39 -> 2 | F23: =Capacity_OPEX!F27+Capacity_OPEX!F28+Capacity_OPEX!F29+Capacity_OPEX!F30+Capacity_OPEX!F31+Capacity_OPEX!F39 -> 2 | G23: =Capacity_OPEX!G27+Capacity_OPEX!G28+Capacity_OPEX!G29+Capacity_OPEX!G30+Capacity_OPEX!G31+Capacity_OPEX!G39 -> 2 | H23: =Capacity_OPEX!H27+Capacity_OPEX!H28+Capacity_OPEX!H29+Capacity_OPEX!H30+Capacity_OPEX!H31+Capacity_OPEX!H39 -> 4.5 | I23: =Capacity_OPEX!I27+Capacity_OPEX!I28+Capacity_OPEX!I29+Capacity_OPEX!I30+Capacity_OPEX!I31+Capacity_OPEX!I39 -> 4 | J23: =Capacity_OPEX!J27+Capacity_OPEX!J28+Capacity_OPEX!J29+Capacity_OPEX!J30+Capacity_OPEX!J31+Capacity_OPEX!J39 -> 8.5 | K23: =Capacity_OPEX!K27+Capacity_OPEX!K28+Capacity_OPEX!K29+Capacity_OPEX!K30+Capacity_OPEX!K31+Capacity_OPEX!K39 -> 4 | L23: =Capacity_OPEX!L27+Capacity_OPEX!L28+Capacity_OPEX!L29+Capacity_OPEX!L30+Capacity_OPEX!L31+Capacity_OPEX!L39 -> 9.5 | ... S23: =Capacity_OPEX!S27+Capacity_OPEX!S28+Capacity_OPEX!S29+Capacity_OPEX!S30+Capacity_OPEX!S31+Capacity_OPEX!S39 -> 26.18
A24: Total running cost (equals Capacity_OPEX total) | B24: Rp m | C24: =SUM(E24:G24) -> 96.63639 | D24: =SUM(H24:S24) -> 882.92578 | E24: =SUM(E19:E23) -> 31.685442 | F24: =SUM(F19:F23) -> 32.474586 | G24: =SUM(G19:G23) -> 32.476361 | H24: =SUM(H19:H23) -> 42.882367 | I24: =SUM(I19:I23) -> 42.785582 | J24: =SUM(J19:J23) -> 62.411306 | K24: =SUM(K19:K23) -> 58.300834 | L24: =SUM(L19:L23) -> 67.360432 | ... S24: =SUM(S19:S23) -> 97.312888
A25: Check: difference to Capacity_OPEX total (must be 0) | B25: Rp m | C25: =SUM(E25:G25) -> 0 | D25: =SUM(H25:S25) -> 0 | E25: =ROUND(E24-Capacity_OPEX!E32,6) -> 0 | F25: =ROUND(F24-Capacity_OPEX!F32,6) -> 0 | G25: =ROUND(G24-Capacity_OPEX!G32,6) -> 0 | H25: =ROUND(H24-Capacity_OPEX!H32,6) -> 0 | I25: =ROUND(I24-Capacity_OPEX!I32,6) -> 0 | J25: =ROUND(J24-Capacity_OPEX!J32,6) -> 0 | K25: =ROUND(K24-Capacity_OPEX!K32,6) -> 0 | L25: =ROUND(L24-Capacity_OPEX!L32,6) -> 0 | ... S25: =ROUND(S24-Capacity_OPEX!S32,6) -> 0
A27: Pay steps: unlocked by sales, not by date (founders, 5 Oct 2026)
A28: Average sales of the previous 3 months (Rp m) | E28: =0 -> 0 | F28: =AVERAGE(PnL!E12) -> 20.428617 | G28: =AVERAGE(PnL!F12,PnL!E12) -> 21.230361 | H28: =AVERAGE(PnL!G12,PnL!F12,PnL!E12) -> 21.519004 | I28: =AVERAGE(PnL!H12,PnL!G12,PnL!F12) -> 22.312428 | J28: =AVERAGE(PnL!I12,PnL!H12,PnL!G12) -> 38.911805 | K28: =AVERAGE(PnL!J12,PnL!I12,PnL!H12) -> 90.076417 | L28: =AVERAGE(PnL!K12,PnL!J12,PnL!I12) -> 119.19593 | M28: =AVERAGE(PnL!L12,PnL!K12,PnL!J12) -> 161.83637 | N28: =AVERAGE(PnL!M12,PnL!L12,PnL!K12) -> 133.49219 | O28: =AVERAGE(PnL!N12,PnL!M12,PnL!L12) -> 197.45457 | ... S28: =AVERAGE(PnL!R12,PnL!Q12,PnL!P12) -> 335.78963
A29: Highest so far (a pay step never goes back down) | E29: =E28 -> 0 | F29: =MAX(E29,F28) -> 20.428617 | G29: =MAX(F29,G28) -> 21.230361 | H29: =MAX(G29,H28) -> 21.519004 | I29: =MAX(H29,I28) -> 22.312428 | J29: =MAX(I29,J28) -> 38.911805 | K29: =MAX(J29,K28) -> 90.076417 | L29: =MAX(K29,L28) -> 119.19593 | M29: =MAX(L29,M28) -> 161.83637 | ... S29: =MAX(R29,S28) -> 335.78963
A30: Pay step unlocked this month (0 to 3) | E30: =(E29>=Inputs!$C$123)+(E29>=Inputs!$C$126)+(E29>=Inputs!$C$127) -> 0 | F30: =(F29>=Inputs!$C$123)+(F29>=Inputs!$C$126)+(F29>=Inputs!$C$127) -> 0 | G30: =(G29>=Inputs!$C$123)+(G29>=Inputs!$C$126)+(G29>=Inputs!$C$127) -> 0 | H30: =(H29>=Inputs!$C$123)+(H29>=Inputs!$C$126)+(H29>=Inputs!$C$127) -> 0 | I30: =(I29>=Inputs!$C$123)+(I29>=Inputs!$C$126)+(I29>=Inputs!$C$127) -> 0 | J30: =(J29>=Inputs!$C$123)+(J29>=Inputs!$C$126)+(J29>=Inputs!$C$127) -> 0 | K30: =(K29>=Inputs!$C$123)+(K29>=Inputs!$C$126)+(K29>=Inputs!$C$127) -> 0 | L30: =(L29>=Inputs!$C$123)+(L29>=Inputs!$C$126)+(L29>=Inputs!$C$127) -> 1 | ... S30: =(S29>=Inputs!$C$123)+(S29>=Inputs!$C$126)+(S29>=Inputs!$C$127) -> 3

Sheet Volume
A1: Event volume plan (from your v10 file, moved to Oct 2026 - Dec 2027)
A2: Rp million unless stated. Q4 2026 and FY 2027 columns are totals (or averages / peaks where stated).
A4: Line | B4: Unit | C4: Q4 2026 | D4: FY 2027 | E4: Oct-26 | F4: Nov-26 | G4: Dec-26 | H4: Jan-27 | I4: Feb-27 | J4: Mar-27 | K4: Apr-27 | L4: May-27 | M4: Jun-27 | N4: Jul-27 | O4: Aug-27 | P4: Sep-27 | Q4: Oct-27 | R4: Nov-27 | S4: Dec-27
A5: Timeline helpers
A6: Month number | B6: # | E6: 1 | F6: 2 | G6: 3 | H6: 4 | I6: 5 | J6: 6 | K6: 7 | L6: 8 | M6: 9 | N6: 10 | O6: 11 | P6: 12 | Q6: 13 | R6: 14 | S6: 15
A7: Is 2027? (1 = yes) | B7: flag | E7: 0 | F7: 0 | G7: 0 | H7: 1 | I7: 1 | J7: 1 | K7: 1 | L7: 1 | M7: 1 | N7: 1 | O7: 1 | P7: 1 | Q7: 1 | R7: 1 | S7: 1
A8: Is Jan-Jun 2027? (1 = yes) | B8: flag | E8: 0 | F8: 0 | G8: 0 | H8: 1 | I8: 1 | J8: 1 | K8: 1 | L8: 1 | M8: 1 | N8: 0 | O8: 0 | P8: 0 | Q8: 0 | R8: 0 | S8: 0
A9: Scenario switch: new B2B events allowed (1 = yes) | B9: flag | E9: =IF(AND(OR(Inputs!$C$6=2,Inputs!$C$6=4),E8=1),0,1) -> 1 | F9: =IF(AND(OR(Inputs!$C$6=2,Inputs!$C$6=4),F8=1),0,1) -> 1 | G9: =IF(AND(OR(Inputs!$C$6=2,Inputs!$C$6=4),G8=1),0,1) -> 1 | H9: =IF(AND(OR(Inputs!$C$6=2,Inputs!$C$6=4),H8=1),0,1) -> 1 | I9: =IF(AND(OR(Inputs!$C$6=2,Inputs!$C$6=4),I8=1),0,1) -> 1 | J9: =IF(AND(OR(Inputs!$C$6=2,Inputs!$C$6=4),J8=1),0,1) -> 1 | K9: =IF(AND(OR(Inputs!$C$6=2,Inputs!$C$6=4),K8=1),0,1) -> 1 | L9: =IF(AND(OR(Inputs!$C$6=2,Inputs!$C$6=4),L8=1),0,1) -> 1 | ... S9: =IF(AND(OR(Inputs!$C$6=2,Inputs!$C$6=4),S8=1),0,1) -> 1
A10: Scenario factor: BI volume | B10: x | E10: =IF(OR(Inputs!$C$6=3,Inputs!$C$6=4),1-Inputs!$C$7,1) -> 1 | F10: =IF(OR(Inputs!$C$6=3,Inputs!$C$6=4),1-Inputs!$C$7,1) -> 1 | G10: =IF(OR(Inputs!$C$6=3,Inputs!$C$6=4),1-Inputs!$C$7,1) -> 1 | H10: =IF(OR(Inputs!$C$6=3,Inputs!$C$6=4),1-Inputs!$C$7,1) -> 1 | I10: =IF(OR(Inputs!$C$6=3,Inputs!$C$6=4),1-Inputs!$C$7,1) -> 1 | J10: =IF(OR(Inputs!$C$6=3,Inputs!$C$6=4),1-Inputs!$C$7,1) -> 1 | K10: =IF(OR(Inputs!$C$6=3,Inputs!$C$6=4),1-Inputs!$C$7,1) -> 1 | L10: =IF(OR(Inputs!$C$6=3,Inputs!$C$6=4),1-Inputs!$C$7,1) -> 1 | ... S10: =IF(OR(Inputs!$C$6=3,Inputs!$C$6=4),1-Inputs!$C$7,1) -> 1
A11: New prices active this month? (1 = yes) | B11: flag | E11: =IF(AND(Inputs!$C$85=2,E6>=IFERROR(MATCH(Inputs!$C$86,$E$4:$S$4,0),99)),1,0) -> 0 | F11: =IF(AND(Inputs!$C$85=2,F6>=IFERROR(MATCH(Inputs!$C$86,$E$4:$S$4,0),99)),1,0) -> 0 | G11: =IF(AND(Inputs!$C$85=2,G6>=IFERROR(MATCH(Inputs!$C$86,$E$4:$S$4,0),99)),1,0) -> 0 | H11: =IF(AND(Inputs!$C$85=2,H6>=IFERROR(MATCH(Inputs!$C$86,$E$4:$S$4,0),99)),1,0) -> 1 | I11: =IF(AND(Inputs!$C$85=2,I6>=IFERROR(MATCH(Inputs!$C$86,$E$4:$S$4,0),99)),1,0) -> 1 | J11: =IF(AND(Inputs!$C$85=2,J6>=IFERROR(MATCH(Inputs!$C$86,$E$4:$S$4,0),99)),1,0) -> 1 | K11: =IF(AND(Inputs!$C$85=2,K6>=IFERROR(MATCH(Inputs!$C$86,$E$4:$S$4,0),99)),1,0) -> 1 | L11: =IF(AND(Inputs!$C$85=2,L6>=IFERROR(MATCH(Inputs!$C$86,$E$4:$S$4,0),99)),1,0) -> 1 | ... S11: =IF(AND(Inputs!$C$85=2,S6>=IFERROR(MATCH(Inputs!$C$86,$E$4:$S$4,0),99)),1,0) -> 1
A12: Price plan factor: B2B volume kept | B12: x | E12: =IF(E11=1,Inputs!$C$98,1) -> 1 | F12: =IF(F11=1,Inputs!$C$98,1) -> 1 | G12: =IF(G11=1,Inputs!$C$98,1) -> 1 | H12: =IF(H11=1,Inputs!$C$98,1) -> 1 | I12: =IF(I11=1,Inputs!$C$98,1) -> 1 | J12: =IF(J11=1,Inputs!$C$98,1) -> 1 | K12: =IF(K11=1,Inputs!$C$98,1) -> 1 | L12: =IF(L11=1,Inputs!$C$98,1) -> 1 | ... S12: =IF(S11=1,Inputs!$C$98,1) -> 1
A14: Base plan volumes (blue = your v10 plan; edit here)
A15: Flagship regulator ToT | B15: events | C15: =SUM(E15:G15) -> 1 | D15: =SUM(H15:S15) -> 5 | E15: 0 | F15: 1 | G15: 0 | H15: 0 | I15: 0 | J15: 1 | K15: 0 | L15: 1 | M15: 0 | N15: 1 | O15: 0 | P15: 1 | Q15: 0 | R15: 1 | S15: 0
A16: KPW / LPS regional ToT | B16: events | C16: =SUM(E16:G16) -> 10 | D16: =SUM(H16:S16) -> 17 | E16: 2 | F16: 3 | G16: 5 | H16: 0 | I16: 0 | J16: 1 | K16: 0 | L16: 1 | M16: 1 | N16: 1 | O16: 1 | P16: 2 | Q16: 2 | R16: 3 | S16: 5
A17: Bank KCP events | B17: events | C17: =SUM(E17:G17) -> 2 | D17: =SUM(H17:S17) -> 4 | E17: 1 | F17: 1 | G17: 0 | H17: 0 | I17: 0 | J17: 0 | K17: 1 | L17: 0 | M17: 0 | N17: 1 | O17: 0 | P17: 0 | Q17: 1 | R17: 1 | S17: 0
A18: Bank EAP contracts active | B18: contracts | C18: =MAX(E18:G18) -> 1 | D18: =MAX(H18:S18) -> 1 | E18: 1 | F18: 1 | G18: 1 | H18: 1 | I18: 1 | J18: 1 | K18: 1 | L18: 1 | M18: 1 | N18: 1 | O18: 1 | P18: 1 | Q18: 1 | R18: 1 | S18: 1
A19: B2C mass events | B19: events | C19: =SUM(E19:G19) -> 3 | D19: =SUM(H19:S19) -> 5 | E19: 1 | F19: 1 | G19: 1 | H19: 1 | I19: 1 | J19: 0 | K19: 0 | L19: 0 | M19: 0 | N19: 0 | O19: 0 | P19: 0 | Q19: 1 | R19: 1 | S19: 1
A20: B2C counseling clients | B20: clients | C20: =SUM(E20:G20) -> 6 | D20: =SUM(H20:S20) -> 23 | E20: 2 | F20: 2 | G20: 2 | H20: 3 | I20: 2 | J20: 1 | K20: 1 | L20: 0 | M20: 2 | N20: 1 | O20: 3 | P20: 4 | Q20: 2 | R20: 2 | S20: 2
A22: Volumes used in the model (after scenario)
A23: Flagship regulator ToT | B23: events | C23: =SUM(E23:G23) -> 0 | D23: =SUM(H23:S23) -> 5 | E23: =E15*E9*E12*E10*(1-E34) -> 0 | F23: =F15*F9*F12*F10*(1-F34) -> 0 | G23: =G15*G9*G12*G10*(1-G34) -> 0 | H23: =H15*H9*H12*H10*(1-H34) -> 0 | I23: =I15*I9*I12*I10*(1-I34) -> 0 | J23: =J15*J9*J12*J10*(1-J34) -> 1 | K23: =K15*K9*K12*K10*(1-K34) -> 0 | L23: =L15*L9*L12*L10*(1-L34) -> 1 | ... S23: =S15*S9*S12*S10*(1-S34) -> 0
A24: KPW / LPS regional ToT | B24: events | C24: =SUM(E24:G24) -> 0 | D24: =SUM(H24:S24) -> 17 | E24: =E16*E9*E12*(1-Inputs!$C$83*(1-E10))*(1-E34) -> 0 | F24: =F16*F9*F12*(1-Inputs!$C$83*(1-F10))*(1-F34) -> 0 | G24: =G16*G9*G12*(1-Inputs!$C$83*(1-G10))*(1-G34) -> 0 | H24: =H16*H9*H12*(1-Inputs!$C$83*(1-H10))*(1-H34) -> 0 | I24: =I16*I9*I12*(1-Inputs!$C$83*(1-I10))*(1-I34) -> 0 | J24: =J16*J9*J12*(1-Inputs!$C$83*(1-J10))*(1-J34) -> 1 | K24: =K16*K9*K12*(1-Inputs!$C$83*(1-K10))*(1-K34) -> 0 | L24: =L16*L9*L12*(1-Inputs!$C$83*(1-L10))*(1-L34) -> 1 | ... S24: =S16*S9*S12*(1-Inputs!$C$83*(1-S10))*(1-S34) -> 5
A25: Bank KCP events (incl. growth-plan bank days) | B25: events | C25: =SUM(E25:G25) -> 0 | D25: =SUM(H25:S25) -> 7 | E25: =E17*E9*E12*(1-E34)+E36 -> 0 | F25: =F17*F9*F12*(1-F34)+F36 -> 0 | G25: =G17*G9*G12*(1-G34)+G36 -> 0 | H25: =H17*H9*H12*(1-H34)+H36 -> 0 | I25: =I17*I9*I12*(1-I34)+I36 -> 0 | J25: =J17*J9*J12*(1-J34)+J36 -> 0 | K25: =K17*K9*K12*(1-K34)+K36 -> 1 | L25: =L17*L9*L12*(1-L34)+L36 -> 0 | ... S25: =S17*S9*S12*(1-S34)+S36 -> 1
A26: Bank EAP contracts active (existing + growth plan) | B26: contracts | C26: =MAX(E26:G26) -> 1 | D26: =MAX(H26:S26) -> 3 | E26: =E18+E35 -> 1 | F26: =F18+F35 -> 1 | G26: =G18+G35 -> 1 | H26: =H18+H35 -> 1 | I26: =I18+I35 -> 2 | J26: =J18+J35 -> 2 | K26: =K18+K35 -> 2 | L26: =L18+L35 -> 2 | ... S26: =S18+S35 -> 3
A27: B2C mass events | B27: events | C27: =SUM(E27:G27) -> 1 | D27: =SUM(H27:S27) -> 4 | E27: =E19*(1-E34*Inputs!$C$103)+Inputs!$C$105*IF(Volume!E6=IFERROR(MATCH(Inputs!$C$128,$E$4:$S$4,0),99),1,0)+Inputs!$C$131*IF(E6=IFERROR(MATCH(Inputs!$C$141,$E$4:$S$4,0),99),1,0) -> 1 | F27: =F19*(1-F34*Inputs!$C$103)+Inputs!$C$105*IF(Volume!F6=IFERROR(MATCH(Inputs!$C$128,$E$4:$S$4,0),99),1,0)+Inputs!$C$131*IF(F6=IFERROR(MATCH(Inputs!$C$141,$E$4:$S$4,0),99),1,0) -> 0 | G27: =G19*(1-G34*Inputs!$C$103)+Inputs!$C$105*IF(Volume!G6=IFERROR(MATCH(Inputs!$C$128,$E$4:$S$4,0),99),1,0)+Inputs!$C$131*IF(G6=IFERROR(MATCH(Inputs!$C$141,$E$4:$S$4,0),99),1,0) -> 0 | H27: =H19*(1-H34*Inputs!$C$103)+Inputs!$C$105*IF(Volume!H6=IFERROR(MATCH(Inputs!$C$128,$E$4:$S$4,0),99),1,0)+Inputs!$C$131*IF(H6=IFERROR(MATCH(Inputs!$C$141,$E$4:$S$4,0),99),1,0) -> 0 | I27: =I19*(1-I34*Inputs!$C$103)+Inputs!$C$105*IF(Volume!I6=IFERROR(MATCH(Inputs!$C$128,$E$4:$S$4,0),99),1,0)+Inputs!$C$131*IF(I6=IFERROR(MATCH(Inputs!$C$141,$E$4:$S$4,0),99),1,0) -> 1 | J27: =J19*(1-J34*Inputs!$C$103)+Inputs!$C$105*IF(Volume!J6=IFERROR(MATCH(Inputs!$C$128,$E$4:$S$4,0),99),1,0)+Inputs!$C$131*IF(J6=IFERROR(MATCH(Inputs!$C$141,$E$4:$S$4,0),99),1,0) -> 0 | K27: =K19*(1-K34*Inputs!$C$103)+Inputs!$C$105*IF(Volume!K6=IFERROR(MATCH(Inputs!$C$128,$E$4:$S$4,0),99),1,0)+Inputs!$C$131*IF(K6=IFERROR(MATCH(Inputs!$C$141,$E$4:$S$4,0),99),1,0) -> 0 | L27: =L19*(1-L34*Inputs!$C$103)+Inputs!$C$105*IF(Volume!L6=IFERROR(MATCH(Inputs!$C$128,$E$4:$S$4,0),99),1,0)+Inputs!$C$131*IF(L6=IFERROR(MATCH(Inputs!$C$141,$E$4:$S$4,0),99),1,0) -> 0 | ... S27: =S19*(1-S34*Inputs!$C$103)+Inputs!$C$105*IF(Volume!S6=IFERROR(MATCH(Inputs!$C$128,$E$4:$S$4,0),99),1,0)+Inputs!$C$131*IF(S6=IFERROR(MATCH(Inputs!$C$141,$E$4:$S$4,0),99),1,0) -> 1
A28: B2C counseling sessions (B2C funnel sheet when the growth plan is on) | B28: clients | C28: =SUM(E28:G28) -> 8.572957 | D28: =SUM(H28:S28) -> 232.15351 | E28: =IF(Inputs!$C$105=1,B2C!E26,E20) -> 2.0897425 | F28: =IF(Inputs!$C$105=1,B2C!F26,F20) -> 3.1894014 | G28: =IF(Inputs!$C$105=1,B2C!G26,G20) -> 3.293813 | H28: =IF(Inputs!$C$105=1,B2C!H26,H20) -> 4.453031 | I28: =IF(Inputs!$C$105=1,B2C!I26,I20) -> 9.2996649 | J28: =IF(Inputs!$C$105=1,B2C!J26,J20) -> 6.5868875 | K28: =IF(Inputs!$C$105=1,B2C!K26,K20) -> 13.9167 | L28: =IF(Inputs!$C$105=1,B2C!L26,L20) -> 14.46018 | ... S28: =IF(Inputs!$C$105=1,B2C!S26,S20) -> 28.315986
A29: Total B2B events (Flagship + KPW/LPS + KCP) | B29: events | C29: =SUM(E29:G29) -> 0 | D29: =SUM(H29:S29) -> 29 | E29: =E23+E24+E25 -> 0 | F29: =F23+F24+F25 -> 0 | G29: =G23+G24+G25 -> 0 | H29: =H23+H24+H25 -> 0 | I29: =I23+I24+I25 -> 0 | J29: =J23+J24+J25 -> 2 | K29: =K23+K24+K25 -> 1 | L29: =L23+L24+L25 -> 2 | ... S29: =S23+S24+S25 -> 6
A31: Notes: v15 adds the timing switch and the growth plan (Inputs sections 11 and 12). v16 adds the EAP channel, LPS / OJK and schools (rows 38-50, Inputs section 14, Channels sheet).
A33: Timing and growth plan (v15)
A34: Pipeline gap: no new sales yet (1 = yes) | B34: flag | C34: =MAX(E34:G34) -> 1 | D34: =MAX(H34:S34) -> 1 | E34: =IF(AND(Inputs!$C$101=1,E6<IFERROR(MATCH(Inputs!$C$102,$E$4:$S$4,0),1)),1,0) -> 1 | F34: =IF(AND(Inputs!$C$101=1,F6<IFERROR(MATCH(Inputs!$C$102,$E$4:$S$4,0),1)),1,0) -> 1 | G34: =IF(AND(Inputs!$C$101=1,G6<IFERROR(MATCH(Inputs!$C$102,$E$4:$S$4,0),1)),1,0) -> 1 | H34: =IF(AND(Inputs!$C$101=1,H6<IFERROR(MATCH(Inputs!$C$102,$E$4:$S$4,0),1)),1,0) -> 1 | I34: =IF(AND(Inputs!$C$101=1,I6<IFERROR(MATCH(Inputs!$C$102,$E$4:$S$4,0),1)),1,0) -> 1 | J34: =IF(AND(Inputs!$C$101=1,J6<IFERROR(MATCH(Inputs!$C$102,$E$4:$S$4,0),1)),1,0) -> 0 | K34: =IF(AND(Inputs!$C$101=1,K6<IFERROR(MATCH(Inputs!$C$102,$E$4:$S$4,0),1)),1,0) -> 0 | L34: =IF(AND(Inputs!$C$101=1,L6<IFERROR(MATCH(Inputs!$C$102,$E$4:$S$4,0),1)),1,0) -> 0 | ... S34: =IF(AND(Inputs!$C$101=1,S6<IFERROR(MATCH(Inputs!$C$102,$E$4:$S$4,0),1)),1,0) -> 0
A35: New EAP contracts active (growth plan) | B35: contracts | C35: =MAX(E35:G35) -> 0 | D35: =MAX(H35:S35) -> 2 | E35: =Inputs!$C$105*(IF(E6>=IFERROR(MATCH(Inputs!$C$107,$E$4:$S$4,0),99),1,0)+IF(E6>=IFERROR(MATCH(Inputs!$C$108,$E$4:$S$4,0),99),1,0)) -> 0 | F35: =Inputs!$C$105*(IF(F6>=IFERROR(MATCH(Inputs!$C$107,$E$4:$S$4,0),99),1,0)+IF(F6>=IFERROR(MATCH(Inputs!$C$108,$E$4:$S$4,0),99),1,0)) -> 0 | G35: =Inputs!$C$105*(IF(G6>=IFERROR(MATCH(Inputs!$C$107,$E$4:$S$4,0),99),1,0)+IF(G6>=IFERROR(MATCH(Inputs!$C$108,$E$4:$S$4,0),99),1,0)) -> 0 | H35: =Inputs!$C$105*(IF(H6>=IFERROR(MATCH(Inputs!$C$107,$E$4:$S$4,0),99),1,0)+IF(H6>=IFERROR(MATCH(Inputs!$C$108,$E$4:$S$4,0),99),1,0)) -> 0 | I35: =Inputs!$C$105*(IF(I6>=IFERROR(MATCH(Inputs!$C$107,$E$4:$S$4,0),99),1,0)+IF(I6>=IFERROR(MATCH(Inputs!$C$108,$E$4:$S$4,0),99),1,0)) -> 1 | J35: =Inputs!$C$105*(IF(J6>=IFERROR(MATCH(Inputs!$C$107,$E$4:$S$4,0),99),1,0)+IF(J6>=IFERROR(MATCH(Inputs!$C$108,$E$4:$S$4,0),99),1,0)) -> 1 | K35: =Inputs!$C$105*(IF(K6>=IFERROR(MATCH(Inputs!$C$107,$E$4:$S$4,0),99),1,0)+IF(K6>=IFERROR(MATCH(Inputs!$C$108,$E$4:$S$4,0),99),1,0)) -> 1 | L35: =Inputs!$C$105*(IF(L6>=IFERROR(MATCH(Inputs!$C$107,$E$4:$S$4,0),99),1,0)+IF(L6>=IFERROR(MATCH(Inputs!$C$108,$E$4:$S$4,0),99),1,0)) -> 1 | ... S35: =Inputs!$C$105*(IF(S6>=IFERROR(MATCH(Inputs!$C$107,$E$4:$S$4,0),99),1,0)+IF(S6>=IFERROR(MATCH(Inputs!$C$108,$E$4:$S$4,0),99),1,0)) -> 2
A36: Bank training days (growth plan) | B36: days | C36: =SUM(E36:G36) -> 0 | D36: =SUM(H36:S36) -> 3 | E36: =Inputs!$C$105*IF(E6>=IFERROR(MATCH(Inputs!$C$111,$E$4:$S$4,0),99),Inputs!$C$112,0)*(1-E34) -> 0 | F36: =Inputs!$C$105*IF(F6>=IFERROR(MATCH(Inputs!$C$111,$E$4:$S$4,0),99),Inputs!$C$112,0)*(1-F34) -> 0 | G36: =Inputs!$C$105*IF(G6>=IFERROR(MATCH(Inputs!$C$111,$E$4:$S$4,0),99),Inputs!$C$112,0)*(1-G34) -> 0 | H36: =Inputs!$C$105*IF(H6>=IFERROR(MATCH(Inputs!$C$111,$E$4:$S$4,0),99),Inputs!$C$112,0)*(1-H34) -> 0 | I36: =Inputs!$C$105*IF(I6>=IFERROR(MATCH(Inputs!$C$111,$E$4:$S$4,0),99),Inputs!$C$112,0)*(1-I34) -> 0 | J36: =Inputs!$C$105*IF(J6>=IFERROR(MATCH(Inputs!$C$111,$E$4:$S$4,0),99),Inputs!$C$112,0)*(1-J34) -> 0 | K36: =Inputs!$C$105*IF(K6>=IFERROR(MATCH(Inputs!$C$111,$E$4:$S$4,0),99),Inputs!$C$112,0)*(1-K34) -> 0 | L36: =Inputs!$C$105*IF(L6>=IFERROR(MATCH(Inputs!$C$111,$E$4:$S$4,0),99),Inputs!$C$112,0)*(1-L34) -> 0 | ... S36: =Inputs!$C$105*IF(S6>=IFERROR(MATCH(Inputs!$C$111,$E$4:$S$4,0),99),Inputs!$C$112,0)*(1-S34) -> 1
A38: v16: EAP channel, LPS / OJK, schools
A39: New BI KPw EAP packages (new offices) | B39: packages | C39: =SUM(E39:G39) -> 1 | D39: =SUM(H39:S39) -> 10 | E39: =Inputs!$C$131*Channels!E15 -> 0 | F39: =Inputs!$C$131*Channels!F15 -> 1 | G39: =Inputs!$C$131*Channels!G15 -> 0 | H39: =Inputs!$C$131*Channels!H15 -> 0 | I39: =Inputs!$C$131*Channels!I15 -> 1 | J39: =Inputs!$C$131*Channels!J15 -> 1 | K39: =Inputs!$C$131*Channels!K15 -> 1 | L39: =Inputs!$C$131*Channels!L15 -> 1 | ... S39: =Inputs!$C$131*Channels!S15 -> 0
A40: Commit-2 second terms (bought upfront with the first) | B40: packages | C40: =SUM(E40:G40) -> 0 | D40: =SUM(H40:S40) -> 3.2 | E40: =0*Inputs!$C$145 -> 0 | F40: =0*Inputs!$C$145 -> 0 | G40: =0*Inputs!$C$145 -> 0 | H40: =E39*Inputs!$C$145 -> 0 | I40: =F39*Inputs!$C$145 -> 0.4 | J40: =G39*Inputs!$C$145 -> 0 | K40: =H39*Inputs!$C$145 -> 0 | L40: =I39*Inputs!$C$145 -> 0.4 | M40: =J39*Inputs!$C$145 -> 0.4 | N40: =K39*Inputs!$C$145 -> 0.4 | O40: =L39*Inputs!$C$145 -> 0.4 | ... S40: =P39*Inputs!$C$145 -> 0.4
A41: Renewals at full price (no Commit-2) | B41: packages | C41: =SUM(E41:G41) -> 0 | D41: =SUM(H41:S41) -> 1.44 | E41: =0*(1-Inputs!$C$145)*Inputs!$C$149 -> 0 | F41: =0*(1-Inputs!$C$145)*Inputs!$C$149 -> 0 | G41: =0*(1-Inputs!$C$145)*Inputs!$C$149 -> 0 | H41: =E39*(1-Inputs!$C$145)*Inputs!$C$149 -> 0 | I41: =F39*(1-Inputs!$C$145)*Inputs!$C$149 -> 0.18 | J41: =G39*(1-Inputs!$C$145)*Inputs!$C$149 -> 0 | K41: =H39*(1-Inputs!$C$145)*Inputs!$C$149 -> 0 | L41: =I39*(1-Inputs!$C$145)*Inputs!$C$149 -> 0.18 | M41: =J39*(1-Inputs!$C$145)*Inputs!$C$149 -> 0.18 | N41: =K39*(1-Inputs!$C$145)*Inputs!$C$149 -> 0.18 | O41: =L39*(1-Inputs!$C$145)*Inputs!$C$149 -> 0.18 | ... S41: =P39*(1-Inputs!$C$145)*Inputs!$C$149 -> 0.18
A42: Active BI KPw packages (3 months each) | B42: packages | C42: =MAX(E42:G42) -> 1 | D42: =MAX(H42:S42) -> 5.16 | E42: =E39+E40+E41 -> 0 | F42: =F39+F40+F41+E39+E40+E41 -> 1 | G42: =G39+G40+G41+F39+F40+F41+E39+E40+E41 -> 1 | H42: =H39+H40+H41+G39+G40+G41+F39+F40+F41 -> 1 | I42: =I39+I40+I41+H39+H40+H41+G39+G40+G41 -> 1.58 | J42: =J39+J40+J41+I39+I40+I41+H39+H40+H41 -> 2.58 | K42: =K39+K40+K41+J39+J40+J41+I39+I40+I41 -> 3.58 | L42: =L39+L40+L41+K39+K40+K41+J39+J40+J41 -> 3.58 | M42: =M39+M40+M41+L39+L40+L41+K39+K40+K41 -> 3.16 | N42: =N39+N40+N41+M39+M40+M41+L39+L40+L41 -> 3.74 | ... S42: =S39+S40+S41+R39+R40+R41+Q39+Q40+Q41 -> 4.74
A43: BI KPw counseling sessions delivered | B43: sessions | C43: =SUM(E43:G43) -> 17.7 | D43: =SUM(H43:S43) -> 373.293 | E43: =E42*Inputs!$C$144/3 -> 0 | F43: =F42*Inputs!$C$144/3 -> 8.85 | G43: =G42*Inputs!$C$144/3 -> 8.85 | H43: =H42*Inputs!$C$144/3 -> 8.85 | I43: =I42*Inputs!$C$144/3 -> 13.983 | J43: =J42*Inputs!$C$144/3 -> 22.833 | K43: =K42*Inputs!$C$144/3 -> 31.683 | L43: =L42*Inputs!$C$144/3 -> 31.683 | ... S43: =S42*Inputs!$C$144/3 -> 41.949
A44: Trainings sold to EAP clients: BI KPw | B44: events | C44: =SUM(E44:G44) -> 0 | D44: =SUM(H44:S44) -> 1.75 | E44: =Inputs!$C$131*Inputs!$C$151*0*(1-E34) -> 0 | F44: =Inputs!$C$131*Inputs!$C$151*0*(1-F34) -> 0 | G44: =Inputs!$C$131*Inputs!$C$151*0*(1-G34) -> 0 | H44: =Inputs!$C$131*Inputs!$C$151*E39*(1-H34) -> 0 | I44: =Inputs!$C$131*Inputs!$C$151*F39*(1-I34) -> 0 | J44: =Inputs!$C$131*Inputs!$C$151*G39*(1-J34) -> 0 | K44: =Inputs!$C$131*Inputs!$C$151*H39*(1-K34) -> 0 | L44: =Inputs!$C$131*Inputs!$C$151*I39*(1-L34) -> 0.25 | M44: =Inputs!$C$131*Inputs!$C$151*J39*(1-M34) -> 0.25 | N44: =Inputs!$C$131*Inputs!$C$151*K39*(1-N34) -> 0.25 | O44: =Inputs!$C$131*Inputs!$C$151*L39*(1-O34) -> 0.25 | ... S44: =Inputs!$C$131*Inputs!$C$151*P39*(1-S34) -> 0.25
A45: Trainings sold to EAP clients: new enterprise contracts | B45: events | C45: =SUM(E45:G45) -> 0 | D45: =SUM(H45:S45) -> 0.5 | E45: =Inputs!$C$131*Inputs!$C$151*0*(1-E34) -> 0 | F45: =Inputs!$C$131*Inputs!$C$151*0*(1-F34) -> 0 | G45: =Inputs!$C$131*Inputs!$C$151*0*(1-G34) -> 0 | H45: =Inputs!$C$131*Inputs!$C$151*MAX(0,E35-0)*(1-H34) -> 0 | I45: =Inputs!$C$131*Inputs!$C$151*MAX(0,F35-E35)*(1-I34) -> 0 | J45: =Inputs!$C$131*Inputs!$C$151*MAX(0,G35-F35)*(1-J34) -> 0 | K45: =Inputs!$C$131*Inputs!$C$151*MAX(0,H35-G35)*(1-K34) -> 0 | L45: =Inputs!$C$131*Inputs!$C$151*MAX(0,I35-H35)*(1-L34) -> 0.25 | M45: =Inputs!$C$131*Inputs!$C$151*MAX(0,J35-I35)*(1-M34) -> 0 | N45: =Inputs!$C$131*Inputs!$C$151*MAX(0,K35-J35)*(1-N34) -> 0 | O45: =Inputs!$C$131*Inputs!$C$151*MAX(0,L35-K35)*(1-O34) -> 0 | P45: =Inputs!$C$131*Inputs!$C$151*MAX(0,M35-L35)*(1-P34) -> 0 | ... S45: =Inputs!$C$131*Inputs!$C$151*MAX(0,P35-O35)*(1-S34) -> 0
A46: LPS / OJK programs (secondary target) | B46: events | C46: =SUM(E46:G46) -> 0 | D46: =SUM(H46:S46) -> 2.04 | E46: =Inputs!$C$131*IF(E6>=IFERROR(MATCH(Inputs!$C$153,$E$4:$S$4,0),99),Inputs!$C$154,0)*(1-E34) -> 0 | F46: =Inputs!$C$131*IF(F6>=IFERROR(MATCH(Inputs!$C$153,$E$4:$S$4,0),99),Inputs!$C$154,0)*(1-F34) -> 0 | G46: =Inputs!$C$131*IF(G6>=IFERROR(MATCH(Inputs!$C$153,$E$4:$S$4,0),99),Inputs!$C$154,0)*(1-G34) -> 0 | H46: =Inputs!$C$131*IF(H6>=IFERROR(MATCH(Inputs!$C$153,$E$4:$S$4,0),99),Inputs!$C$154,0)*(1-H34) -> 0 | I46: =Inputs!$C$131*IF(I6>=IFERROR(MATCH(Inputs!$C$153,$E$4:$S$4,0),99),Inputs!$C$154,0)*(1-I34) -> 0 | J46: =Inputs!$C$131*IF(J6>=IFERROR(MATCH(Inputs!$C$153,$E$4:$S$4,0),99),Inputs!$C$154,0)*(1-J34) -> 0 | K46: =Inputs!$C$131*IF(K6>=IFERROR(MATCH(Inputs!$C$153,$E$4:$S$4,0),99),Inputs!$C$154,0)*(1-K34) -> 0 | L46: =Inputs!$C$131*IF(L6>=IFERROR(MATCH(Inputs!$C$153,$E$4:$S$4,0),99),Inputs!$C$154,0)*(1-L34) -> 0 | ... S46: =Inputs!$C$131*IF(S6>=IFERROR(MATCH(Inputs!$C$153,$E$4:$S$4,0),99),Inputs!$C$154,0)*(1-S34) -> 0.34
A47: Schools tested | B47: schools | C47: =SUM(E47:G47) -> 0 | D47: =SUM(H47:S47) -> 6 | E47: =Inputs!$C$131*Channels!E16 -> 0 | F47: =Inputs!$C$131*Channels!F16 -> 0 | G47: =Inputs!$C$131*Channels!G16 -> 0 | H47: =Inputs!$C$131*Channels!H16 -> 0 | I47: =Inputs!$C$131*Channels!I16 -> 1 | J47: =Inputs!$C$131*Channels!J16 -> 0 | K47: =Inputs!$C$131*Channels!K16 -> 0 | L47: =Inputs!$C$131*Channels!L16 -> 0 | ... S47: =Inputs!$C$131*Channels!S16 -> 0
A48: Students tested | B48: students | C48: =SUM(E48:G48) -> 0 | D48: =SUM(H48:S48) -> 480 | E48: =E47*Inputs!$C$158 -> 0 | F48: =F47*Inputs!$C$158 -> 0 | G48: =G47*Inputs!$C$158 -> 0 | H48: =H47*Inputs!$C$158 -> 0 | I48: =I47*Inputs!$C$158 -> 80 | J48: =J47*Inputs!$C$158 -> 0 | K48: =K47*Inputs!$C$158 -> 0 | L48: =L47*Inputs!$C$158 -> 0 | ... S48: =S47*Inputs!$C$158 -> 0
A49: Paid counseling through channels (KPw add-ons + school follow-ups) | B49: sessions | C49: =SUM(E49:G49) -> 2 | D49: =SUM(H49:S49) -> 66.18 | E49: =Inputs!$C$131*(E42*Inputs!$C$150+E48*Inputs!$C$159) -> 0 | F49: =Inputs!$C$131*(F42*Inputs!$C$150+F48*Inputs!$C$159) -> 1 | G49: =Inputs!$C$131*(G42*Inputs!$C$150+G48*Inputs!$C$159) -> 1 | H49: =Inputs!$C$131*(H42*Inputs!$C$150+H48*Inputs!$C$159) -> 1 | I49: =Inputs!$C$131*(I42*Inputs!$C$150+I48*Inputs!$C$159) -> 5.58 | J49: =Inputs!$C$131*(J42*Inputs!$C$150+J48*Inputs!$C$159) -> 2.58 | K49: =Inputs!$C$131*(K42*Inputs!$C$150+K48*Inputs!$C$159) -> 3.58 | L49: =Inputs!$C$131*(L42*Inputs!$C$150+L48*Inputs!$C$159) -> 3.58 | ... S49: =Inputs!$C$131*(S42*Inputs!$C$150+S48*Inputs!$C$159) -> 4.74
A50: BI KPw package value signed this month (Rp m) | B50: Rp m | C50: =SUM(E50:G50) -> 15.2145 | D50: =SUM(H50:S50) -> 221.697 | E50: =Inputs!$C$142*(E39*(1-Inputs!$C$145*Inputs!$C$146)+E40*(1-Inputs!$C$146)+E41) -> 0 | F50: =Inputs!$C$142*(F39*(1-Inputs!$C$145*Inputs!$C$146)+F40*(1-Inputs!$C$146)+F41) -> 15.2145 | G50: =Inputs!$C$142*(G39*(1-Inputs!$C$145*Inputs!$C$146)+G40*(1-Inputs!$C$146)+G41) -> 0 | H50: =Inputs!$C$142*(H39*(1-Inputs!$C$145*Inputs!$C$146)+H40*(1-Inputs!$C$146)+H41) -> 0 | I50: =Inputs!$C$142*(I39*(1-Inputs!$C$145*Inputs!$C$146)+I40*(1-Inputs!$C$146)+I41) -> 23.9085 | J50: =Inputs!$C$142*(J39*(1-Inputs!$C$145*Inputs!$C$146)+J40*(1-Inputs!$C$146)+J41) -> 15.2145 | K50: =Inputs!$C$142*(K39*(1-Inputs!$C$145*Inputs!$C$146)+K40*(1-Inputs!$C$146)+K41) -> 15.2145 | L50: =Inputs!$C$142*(L39*(1-Inputs!$C$145*Inputs!$C$146)+L40*(1-Inputs!$C$146)+L41) -> 23.9085 | ... S50: =Inputs!$C$142*(S39*(1-Inputs!$C$145*Inputs!$C$146)+S40*(1-Inputs!$C$146)+S41) -> 8.694

Sheet Unit_Economics
A1: Pillar 1 - Unit economics and B2B customer acquisition cost (Rp million)
A3: Product | B3: Price | C3: Delivery cost | D3: Extra travel (if you pay) | E3: Coreitera fee (assessment cost) | F3: Total delivery cost | G3: Contribution (profit per event) | H3: Contribution % | I3: Price / external cost | J3: Meets your 3x rule? | K3: Handler-days | L3: Contribution per handler-day | M3: Coreitera revenue per event (memo) | N3: Old price (before new prices start) | O3: Old delivery cost
A4: Flagship regulator ToT | B4: =IF(Inputs!$C$85=2,Inputs!$C$87+Inputs!$C$93*Inputs!$C$63*Inputs!$C$92,Inputs!$C$9) -> 100 | C4: =Inputs!$C$16 -> 25 | D4: 0 | E4: =IF(Inputs!$C$85=2,Inputs!$C$93*Inputs!$C$63*Inputs!$C$62,IF(Inputs!$C$61=1,0,Inputs!$C$63*Inputs!$C$62)) -> 3 | F4: =C4+D4+E4 -> 28 | G4: =B4-F4 -> 72 | H4: =IF(B4=0,0,G4/B4) -> 0.72 | I4: =IF(C4+D4=0,0,B4/(C4+D4)) -> 4 | J4: =IF(I4>=3,"Yes","No - below 3x") -> Yes | K4: =Inputs!$C$26*Inputs!$C$30 -> 12 | L4: =IF(K4=0,0,G4/K4) -> 6 | M4: =Inputs!$C$63*Inputs!$C$62 -> 3 | N4: =Inputs!$C$9 -> 85 | O4: =C4+D4+IF(Inputs!$C$61=1,0,Inputs!$C$63*Inputs!$C$62) -> 25
A5: KPW / LPS regional ToT | B5: =IF(Inputs!$C$85=2,Inputs!$C$88+Inputs!$C$94*Inputs!$C$64*Inputs!$C$92,Inputs!$C$10) -> 28.5 | C5: =Inputs!$C$17 -> 8 | D5: =IF(Inputs!$C$22=1,0,Inputs!$C$27*Inputs!$C$23*Inputs!$C$24) -> 0 | E5: =IF(Inputs!$C$85=2,Inputs!$C$94*Inputs!$C$64*Inputs!$C$62,IF(Inputs!$C$61=1,0,Inputs!$C$64*Inputs!$C$62)) -> 2.25 | F5: =C5+D5+E5 -> 10.25 | G5: =B5-F5 -> 18.25 | H5: =IF(B5=0,0,G5/B5) -> 0.64035088 | I5: =IF(C5+D5=0,0,B5/(C5+D5)) -> 3.5625 | J5: =IF(I5>=3,"Yes","No - below 3x") -> Yes | K5: =Inputs!$C$27*Inputs!$C$31 -> 2 | L5: =IF(K5=0,0,G5/K5) -> 9.125 | M5: =Inputs!$C$64*Inputs!$C$62 -> 2.25 | N5: =Inputs!$C$10 -> 20 | O5: =C5+D5+IF(Inputs!$C$61=1,0,Inputs!$C$64*Inputs!$C$62) -> 8
A6: Bank KCP event | B6: =IF(Inputs!$C$85=2,(1-Inputs!$C$91)*Inputs!$C$89+Inputs!$C$91*Inputs!$C$90+Inputs!$C$95*Inputs!$C$65*Inputs!$C$92,Inputs!$C$11) -> 53.5 | C6: =Inputs!$C$18 -> 12 | D6: 0 | E6: =IF(Inputs!$C$85=2,Inputs!$C$95*Inputs!$C$65*Inputs!$C$62,IF(Inputs!$C$61=1,0,Inputs!$C$65*Inputs!$C$62)) -> 3 | F6: =C6+D6+E6 -> 15 | G6: =B6-F6 -> 38.5 | H6: =IF(B6=0,0,G6/B6) -> 0.71962617 | I6: =IF(C6+D6=0,0,B6/(C6+D6)) -> 4.4583333 | J6: =IF(I6>=3,"Yes","No - below 3x") -> Yes | K6: =Inputs!$C$28*Inputs!$C$32 -> 2 | L6: =IF(K6=0,0,G6/K6) -> 19.25 | M6: =Inputs!$C$65*Inputs!$C$62 -> 3 | N6: =Inputs!$C$11 -> 35 | O6: =C6+D6+IF(Inputs!$C$61=1,0,Inputs!$C$65*Inputs!$C$62) -> 12
A7: Bank EAP (per month) | B7: =Inputs!$C$12 -> 15 | C7: =Inputs!$C$19 -> 5 | D7: 0 | E7: 0 | F7: =C7+D7+E7 -> 5 | G7: =B7-F7 -> 10 | H7: =IF(B7=0,0,G7/B7) -> 0.66666667 | I7: =IF(C7+D7=0,0,B7/(C7+D7)) -> 3 | J7: =IF(I7>=3,"Yes","No - below 3x") -> Yes | K7: 0 | L7: =IF(K7=0,0,G7/K7) -> 0 | M7: 0 | N7: =Inputs!$C$12 -> 15 | O7: =C7+D7+0 -> 5
A8: B2C mass event | B8: =Inputs!$C$13 -> 4.144 | C8: =Inputs!$C$20 -> 2.73 | D8: 0 | E8: =IF(Inputs!$C$61=1,0,Inputs!$C$66*Inputs!$C$62) -> 0 | F8: =C8+D8+E8 -> 2.73 | G8: =B8-F8 -> 1.414 | H8: =IF(B8=0,0,G8/B8) -> 0.34121622 | I8: =IF(C8+D8=0,0,B8/(C8+D8)) -> 1.5179487 | J8: =IF(I8>=3,"Yes","No - below 3x") -> No - below 3x | K8: =Inputs!$C$29*Inputs!$C$33 -> 2 | L8: =IF(K8=0,0,G8/K8) -> 0.707 | M8: =Inputs!$C$66*Inputs!$C$62 -> 3.75 | N8: =Inputs!$C$13 -> 4.144 | O8: =C8+D8+IF(Inputs!$C$61=1,0,Inputs!$C$66*Inputs!$C$62) -> 2.73
A10: B2B customer acquisition cost (CAC)
A11: Sales cost per year (sales travel + Account Manager if hired; founder time not costed) | B11: =IF(Inputs!$C$52=1,(Inputs!$C$53+Inputs!$C$55)*12,Inputs!$C$55*12) -> 24
A12: New B2B clients won per year | B12: =Inputs!$C$70 -> 4
A13: CAC: cost to win one new B2B client | B13: =IF(B12=0,0,B11/B12) -> 6
A14: Events needed to pay back CAC: Flagship | B14: =IF(G4<=0,0,B13/G4) -> 0.083333333
A15: Events needed to pay back CAC: KPW / LPS | B15: =IF(G5<=0,0,B13/G5) -> 0.32876712
A16: Events needed to pay back CAC: Bank KCP | B16: =IF(G6<=0,0,B13/G6) -> 0.15584416
A17: Months of EAP needed to pay back CAC | B17: =IF(G7<=0,0,B13/G7) -> 0.6
A19: How to read: Contribution = price minus everything you pay to deliver that one event. It is what is left to pay fixed costs.
A20: Your pricing rule is price at least 3x the delivery cost paid outside the group (Coreitera fees stay inside). Rows marked 'No' break that rule.
A21: CAC counts only direct sales spend. Founder time is not costed here because founders are paid a fixed salary.
A22: Coreitera revenue per event is a memo: it is money paid between your own companies, so it cancels out in the combined profit.

Sheet Rate_Card
A1: Rate card - elite boutique pricing by client tier (Rp million)
A2: Rule: price close to the buyer's ceiling for regulators, and against the big-trainer alternative for banks. Never below 3x delivery cost. Prices here always show the new rate card, whatever the active price plan.
A4: Tier and product | B4: What caps the price | C4: Training price | D4: Days | E4: Price per day | F4: Assessment per participant | G4: Participants | H4: Package price (training + assessment) | I4: External delivery cost (excl. Coreitera) | J4: Price / external cost | K4: Meets 3x? | L4: Per day vs big-trainer rate | M4: Best contract shape
A5: Tier 1 regulator - Flagship ToT (BI, OJK, LPS) | B5: Budget ceiling per activity; past contracts set the anchor | C5: =Inputs!$C$87 -> 94 | D5: =Inputs!$C$30 -> 3 | E5: =IF(D5=0,0,C5/D5) -> 31.333333 | F5: =Inputs!$C$92*Inputs!$C$93 -> 0.15 | G5: =Inputs!$C$63 -> 40 | H5: =C5+F5*G5 -> 100 | I5: =Inputs!$C$16 -> 25 | J5: =IF(I5=0,0,H5/I5) -> 4 | K5: =IF(J5>=3,"Yes","No") -> Yes | L5: =IF((Inputs!$C$96*Inputs!$C$11)=0,0,E5/(Inputs!$C$96*Inputs!$C$11)) -> 0.35809524 | M5: Yearly framework contract with central procurement
A6: Tier 1 regulator - Regional ToT (BI KPW, LPS) | B6: Budget ceiling per activity | C6: =Inputs!$C$88 -> 24 | D6: =Inputs!$C$31 -> 1 | E6: =IF(D6=0,0,C6/D6) -> 24 | F6: =Inputs!$C$92*Inputs!$C$94 -> 0.15 | G6: =Inputs!$C$64 -> 30 | H6: =C6+F6*G6 -> 28.5 | I6: =Inputs!$C$17 -> 8 | J6: =IF(I6=0,0,H6/I6) -> 3.5625 | K6: =IF(J6>=3,"Yes","No") -> Yes | L6: =IF((Inputs!$C$96*Inputs!$C$11)=0,0,E6/(Inputs!$C$96*Inputs!$C$11)) -> 0.27428571 | M6: Framework + work order (SPK) per office
A7: State-owned bank (BRI, Mandiri, BNI, BTN) | B7: Vendor tender and price competition | C7: =Inputs!$C$89 -> 45 | D7: =Inputs!$C$32 -> 1 | E7: =IF(D7=0,0,C7/D7) -> 45 | F7: =Inputs!$C$92*Inputs!$C$95 -> 0.15 | G7: =Inputs!$C$65 -> 40 | H7: =C7+F7*G7 -> 51 | I7: =Inputs!$C$18 -> 12 | J7: =IF(I7=0,0,H7/I7) -> 4.25 | K7: =IF(J7>=3,"Yes","No") -> Yes | L7: =IF((Inputs!$C$96*Inputs!$C$11)=0,0,E7/(Inputs!$C$96*Inputs!$C$11)) -> 0.51428571 | M7: Multi-branch yearly framework (10+ groups), 30% down payment
A8: Private big bank (BCA and others) | B8: Value vs big trainers (2-3x your old rate) | C8: =Inputs!$C$90 -> 55 | D8: =Inputs!$C$32 -> 1 | E8: =IF(D8=0,0,C8/D8) -> 55 | F8: =Inputs!$C$92*Inputs!$C$95 -> 0.15 | G8: =Inputs!$C$65 -> 40 | H8: =C8+F8*G8 -> 61 | I8: =Inputs!$C$18 -> 12 | J8: =IF(I8=0,0,H8/I8) -> 5.0833333 | K8: =IF(J8>=3,"Yes","No") -> Yes | L8: =IF((Inputs!$C$96*Inputs!$C$11)=0,0,E8/(Inputs!$C$96*Inputs!$C$11)) -> 0.62857143 | M8: Annual learning partnership + EAP priced per employee
A9: Reference: big-trainer day rate charged to banks | B9: Your old bank rate x the multiple you gave (2-3x, midpoint). | E9: =(Inputs!$C$96*Inputs!$C$11) -> 87.5
A11: Bank packages (good / better / best) - per group per day
A12: Package | B12: What is included | C12: State-owned bank | E12: Private bank
A13: Essential | B13: Training day only | C13: =C7 -> 45 | E13: =C8 -> 55
A14: Signature (lead offer) | B14: Training + pre/post assessment + impact report | C14: =H7 -> 51 | E14: =H8 -> 61
A15: Elite | B15: Signature + cascade licence for trainers + 3 months follow-up | C15: =H7*(1+Inputs!$C$97) -> 66.3 | E15: =H8*(1+Inputs!$C$97) -> 79.3
A17: Volume-loss test: how many events can you lose and still earn more?
A18: Product | B18: Profit per event, old price | C18: Profit per event, new package | D18: Max share of events you can lose | E18: Meaning
A19: Flagship ToT | B19: =Inputs!$C$9-Inputs!$C$16 -> 60 | C19: =H5-I5-Inputs!$C$93*G5*Inputs!$C$62 -> 72 | D19: =IF(C19<=0,0,1-B19/C19) -> 0.16666667 | E19: ="Lose fewer than "&TEXT(D19,"0%")&" of these events and profit still goes up." -> Lose fewer than 17% of these events and profit still goes up.
A20: KPW / LPS ToT | B20: =Inputs!$C$10-Inputs!$C$17 -> 12 | C20: =H6-I6-Inputs!$C$94*G6*Inputs!$C$62 -> 18.25 | D20: =IF(C20<=0,0,1-B20/C20) -> 0.34246575 | E20: ="Lose fewer than "&TEXT(D20,"0%")&" of these events and profit still goes up." -> Lose fewer than 34% of these events and profit still goes up.
A21: Bank event (state-owned) | B21: =Inputs!$C$11-Inputs!$C$18 -> 23 | C21: =H7-I7-Inputs!$C$95*G7*Inputs!$C$62 -> 36 | D21: =IF(C21<=0,0,1-B21/C21) -> 0.36111111 | E21: ="Lose fewer than "&TEXT(D21,"0%")&" of these events and profit still goes up." -> Lose fewer than 36% of these events and profit still goes up.
A22: Bank event (private) | B22: =Inputs!$C$11-Inputs!$C$18 -> 23 | C22: =H8-I8-Inputs!$C$95*G8*Inputs!$C$62 -> 46 | D22: =IF(C22<=0,0,1-B22/C22) -> 0.5 | E22: ="Lose fewer than "&TEXT(D22,"0%")&" of these events and profit still goes up." -> Lose fewer than 50% of these events and profit still goes up.
A24: Pricing rules (all tiers)
A25: 1. Price units: per group per day (training), per participant (assessment), per employee per month (EAP), per year (cascade licence). Never one lump sum.
A26: 2. Floor: never below 3x the delivery cost paid outside the group. The Coreitera fee is excluded because it stays inside your own companies.
A27: 3. Pilot discount: at most 20%, once per client, recorded as a sales cost, and tied to a follow-on contract.
A28: 4. Volume discount: 5% for 5+ groups a year, 10% for 10+ groups. Never more than 10%.
A29: 5. Travel and venue: paid by the client, or billed at cost plus 10%.
A30: 6. Payment: 30% down payment for bank contracts above Rp100m. Regulators keep current terms.
A31: 7. Regulators: never raise the price of an old item. Add new items (assessment, licence, follow-up), which get a fresh budget ceiling.
A32: 8. Elite boutique position: always clearly below big trainers, never the cheapest. Compete on more services and a measured result.

Sheet Pricing_Scheme
A1: Pricing scheme: a small intro, the list price, and Commit-2 (two terms bought upfront, lower overall price)
A2: First principle: a discount is worth giving only if it buys something worth more than it costs: a second sale we would otherwise lose, cash earlier, and one less sales cycle. Rp million.
A4: Scheme inputs (from Inputs)
A5: Commit-2 discount on the overall price | C5: =Inputs!$C$146 -> 0.05
A6: Chance a buyer comes back for a second term without Commit-2 (renewal) | C6: =Inputs!$C$149 -> 0.3
A7: Commit-2 bonus: 2 free penyuluhan, TJ cost / value to client | C7: =Inputs!$C$147 -> 0.2 | D7: =Inputs!$C$148 -> 2
A8: Product | B8: Intro offer (small scope, full unit price) | C8: Intro price | D8: List price (one term or event) | E8: Delivery cost | F8: Commit-2 price (two terms) | G8: Client saves (cash + bonus value) | H8: Profit: one term at list | I8: Profit: Commit-2 (two terms, after bonus cost) | J8: Break-even: Commit-2 wins if renewal is below | K8: Largest cash discount that still wins | L8: Verdict
A9: BI KPw EAP package (3 months) | B9: Sapa: 15 sessions, no screening | C9: =Channels!$B$5 -> 7.5 | D9: =Inputs!$C$142 -> 15.525 | E9: =Inputs!$C$143 -> 11.98725 | F9: =2*D9*(1-$C$5) -> 29.4975 | G9: =TEXT((2*D9-F9+$D$7)/(2*D9),"0%")&" (Rp"&TEXT(2*D9-F9+$D$7,"0.0")&"m)" -> 11% (Rp3.6m) | H9: =D9-E9 -> 3.53775 | I9: =F9-2*E9-$C$7 -> 5.323 | J9: =IF(H9<=0,0,I9/H9-1) -> 0.50462865 | K9: =1-(E9+(1+$C$6)*(D9-E9)/2+$C$7/2)/D9 -> 0.073314815 | L9: =IF(K9<0.03,"Price too thin for any discount: raise the list price first",IF($C$5<=K9,"Offer Commit-2: "&TEXT($C$5,"0%")&" off + 2 free penyuluhan, 50% at signing","Cash discount too deep: max "&TEXT(K9,"0%"))) -> Offer Commit-2: 5% off + 2 free penyuluhan, 50% at signing
A10: Regional ToT (BI KPw, LPS, OJK) | B10: 2-hour penyuluhan or webinar for staff | C10: 5 | D10: =Unit_Economics!$B$5 -> 28.5 | E10: =Unit_Economics!$F$5 -> 10.25 | F10: =2*D10*(1-$C$5) -> 54.15 | G10: =TEXT((2*D10-F10+$D$7)/(2*D10),"0%")&" (Rp"&TEXT(2*D10-F10+$D$7,"0.0")&"m)" -> 9% (Rp4.9m) | H10: =D10-E10 -> 18.25 | I10: =F10-2*E10-$C$7 -> 33.45 | J10: =IF(H10<=0,0,I10/H10-1) -> 0.83287671 | K10: =1-(E10+(1+$C$6)*(D10-E10)/2+$C$7/2)/D10 -> 0.22061404 | L10: =IF(K10<0.03,"Price too thin for any discount: raise the list price first",IF($C$5<=K10,"Offer Commit-2: "&TEXT($C$5,"0%")&" off + 2 free penyuluhan, 50% at signing","Cash discount too deep: max "&TEXT(K10,"0%"))) -> Offer Commit-2: 5% off + 2 free penyuluhan, 50% at signing
A11: State bank training day | B11: Half-day workshop for one branch | C11: =Unit_Economics!$B$6/2 -> 26.75 | D11: =Unit_Economics!$B$6 -> 53.5 | E11: =Unit_Economics!$F$6 -> 15 | F11: =2*D11*(1-$C$5) -> 101.65 | G11: =TEXT((2*D11-F11+$D$7)/(2*D11),"0%")&" (Rp"&TEXT(2*D11-F11+$D$7,"0.0")&"m)" -> 7% (Rp7.4m) | H11: =D11-E11 -> 38.5 | I11: =F11-2*E11-$C$7 -> 71.45 | J11: =IF(H11<=0,0,I11/H11-1) -> 0.85584416 | K11: =1-(E11+(1+$C$6)*(D11-E11)/2+$C$7/2)/D11 -> 0.25 | L11: =IF(K11<0.03,"Price too thin for any discount: raise the list price first",IF($C$5<=K11,"Offer Commit-2: "&TEXT($C$5,"0%")&" off + 2 free penyuluhan, 50% at signing","Cash discount too deep: max "&TEXT(K11,"0%"))) -> Offer Commit-2: 5% off + 2 free penyuluhan, 50% at signing
A12: Enterprise EAP (6 months) | B12: 3-month pilot, same monthly price | C12: =Unit_Economics!$B$7*3 -> 45 | D12: =Unit_Economics!$B$7*6 -> 90 | E12: =Unit_Economics!$C$7*6 -> 30 | F12: =2*D12*(1-$C$5) -> 171 | G12: =TEXT((2*D12-F12+$D$7)/(2*D12),"0%")&" (Rp"&TEXT(2*D12-F12+$D$7,"0.0")&"m)" -> 6% (Rp11.0m) | H12: =D12-E12 -> 60 | I12: =F12-2*E12-$C$7 -> 110.8 | J12: =IF(H12<=0,0,I12/H12-1) -> 0.84666667 | K12: =1-(E12+(1+$C$6)*(D12-E12)/2+$C$7/2)/D12 -> 0.23222222 | L12: =IF(K12<0.03,"Price too thin for any discount: raise the list price first",IF($C$5<=K12,"Offer Commit-2: "&TEXT($C$5,"0%")&" off + 2 free penyuluhan, 50% at signing","Cash discount too deep: max "&TEXT(K12,"0%"))) -> Offer Commit-2: 5% off + 2 free penyuluhan, 50% at signing
A13: School test (one school, one grade) | B13: One class of 30 students | C13: =30*Inputs!$C$155 -> 9 | D13: =Inputs!$C$158*Inputs!$C$155 -> 24 | E13: =Inputs!$C$158*(Inputs!$C$156+Inputs!$C$157*(Inputs!$C$155-Inputs!$C$156)) -> 14.8 | F13: =2*D13*(1-$C$5) -> 45.6 | G13: =TEXT((2*D13-F13+$D$7)/(2*D13),"0%")&" (Rp"&TEXT(2*D13-F13+$D$7,"0.0")&"m)" -> 9% (Rp4.4m) | H13: =D13-E13 -> 9.2 | I13: =F13-2*E13-$C$7 -> 15.8 | J13: =IF(H13<=0,0,I13/H13-1) -> 0.7173913 | K13: =1-(E13+(1+$C$6)*(D13-E13)/2+$C$7/2)/D13 -> 0.13 | L13: =IF(K13<0.03,"Price too thin for any discount: raise the list price first",IF($C$5<=K13,"Offer Commit-2: "&TEXT($C$5,"0%")&" off + 2 free penyuluhan, 50% at signing","Cash discount too deep: max "&TEXT(K13,"0%"))) -> Offer Commit-2: 5% off + 2 free penyuluhan, 50% at signing
A14: Flagship ToT (BI head office) | B14: None: sell on the past contract | D14: =Unit_Economics!$B$4 -> 100 | E14: =Unit_Economics!$F$4 -> 28 | F14: =2*D14*(1-$C$5) -> 190 | G14: =TEXT((2*D14-F14+$D$7)/(2*D14),"0%")&" (Rp"&TEXT(2*D14-F14+$D$7,"0.0")&"m)" -> 6% (Rp12.0m) | H14: =D14-E14 -> 72 | I14: =F14-2*E14-$C$7 -> 133.8 | J14: =IF(H14<=0,0,I14/H14-1) -> 0.85833333 | K14: =1-(E14+(1+$C$6)*(D14-E14)/2+$C$7/2)/D14 -> 0.251 | L14: ="No Commit discount: BI never lets an old price rise again. Ask a 30% down payment instead." -> No Commit discount: BI never lets an old price rise again. Ask a 30% down payment instead.
A17: Rules for every offer:
A18: 1. Intro = smaller scope at the full unit price, never a lower unit price. BI and other regulators will not accept a price rise on an item they bought before (Rate_Card rule 7), so a cheap unit price becomes the permanent price.
A19: 2. The intro fee is credited to Commit-2 if the client signs within 60 days. The intro is a step to the bigger sale.
A20: 3. Commit-2 = two terms (or two events) in one SPK, both dates fixed, 50% paid at signing. Give 'cheaper overall' as 5% off + 2 free penyuluhan (the client sees about 11% of value; TJ gives about 6%). Never above column K.
A21: 4. Floor: after the discount each term must still earn at least 30% (EAP) or 3x the external cost (training).
A22: 5. BI head office: no Commit discount; ask a 30% down payment. Regional offices: Commit-2 on packages is fine (one office, one budget year).
A23: 6. B2C: the entry price is the Tier 1-2 session (Rp500k online). The 4-session package (10% off) is the B2C Commit: offer it after the first session (Inputs b2c_pack).
A24: How to read column J: if fewer buyers than this would come back on their own, Commit-2 earns more than selling one term at a time. Column K is the deepest discount that still wins at today's renewal guess.

Sheet Capacity_OPEX
A1: Pillar 2 - Capacity and step-function fixed costs
A2: Rp million unless stated. Q4 2026 and FY 2027 columns are totals (or averages / peaks where stated).
A4: Line | B4: Unit | C4: Q4 2026 | D4: FY 2027 | E4: Oct-26 | F4: Nov-26 | G4: Dec-26 | H4: Jan-27 | I4: Feb-27 | J4: Mar-27 | K4: Apr-27 | L4: May-27 | M4: Jun-27 | N4: Jul-27 | O4: Aug-27 | P4: Sep-27 | Q4: Oct-27 | R4: Nov-27 | S4: Dec-27
A5: Delivery capacity
A6: Handler placements (people x events) | B6: placements | C6: =SUM(E6:G6) -> 2 | D6: =SUM(H6:S6) -> 84.58 | E6: =Volume!E23*Inputs!$C$26+Volume!E24*Inputs!$C$27+Volume!E25*Inputs!$C$28+Volume!E27*Inputs!$C$29+(Volume!E44+Volume!E45+Volume!E46)*Inputs!$C$27 -> 2 | F6: =Volume!F23*Inputs!$C$26+Volume!F24*Inputs!$C$27+Volume!F25*Inputs!$C$28+Volume!F27*Inputs!$C$29+(Volume!F44+Volume!F45+Volume!F46)*Inputs!$C$27 -> 0 | G6: =Volume!G23*Inputs!$C$26+Volume!G24*Inputs!$C$27+Volume!G25*Inputs!$C$28+Volume!G27*Inputs!$C$29+(Volume!G44+Volume!G45+Volume!G46)*Inputs!$C$27 -> 0 | H6: =Volume!H23*Inputs!$C$26+Volume!H24*Inputs!$C$27+Volume!H25*Inputs!$C$28+Volume!H27*Inputs!$C$29+(Volume!H44+Volume!H45+Volume!H46)*Inputs!$C$27 -> 0 | I6: =Volume!I23*Inputs!$C$26+Volume!I24*Inputs!$C$27+Volume!I25*Inputs!$C$28+Volume!I27*Inputs!$C$29+(Volume!I44+Volume!I45+Volume!I46)*Inputs!$C$27 -> 2 | J6: =Volume!J23*Inputs!$C$26+Volume!J24*Inputs!$C$27+Volume!J25*Inputs!$C$28+Volume!J27*Inputs!$C$29+(Volume!J44+Volume!J45+Volume!J46)*Inputs!$C$27 -> 6 | K6: =Volume!K23*Inputs!$C$26+Volume!K24*Inputs!$C$27+Volume!K25*Inputs!$C$28+Volume!K27*Inputs!$C$29+(Volume!K44+Volume!K45+Volume!K46)*Inputs!$C$27 -> 2 | L6: =Volume!L23*Inputs!$C$26+Volume!L24*Inputs!$C$27+Volume!L25*Inputs!$C$28+Volume!L27*Inputs!$C$29+(Volume!L44+Volume!L45+Volume!L46)*Inputs!$C$27 -> 7 | ... S6: =Volume!S23*Inputs!$C$26+Volume!S24*Inputs!$C$27+Volume!S25*Inputs!$C$28+Volume!S27*Inputs!$C$29+(Volume!S44+Volume!S45+Volume!S46)*Inputs!$C$27 -> 15.18
A7: Handler-days (placements x days per event) | B7: days | C7: =SUM(E7:G7) -> 2 | D7: =SUM(H7:S7) -> 124.58 | E7: =Volume!E23*Inputs!$C$26*Inputs!$C$30+Volume!E24*Inputs!$C$27*Inputs!$C$31+Volume!E25*Inputs!$C$28*Inputs!$C$32+Volume!E27*Inputs!$C$29*Inputs!$C$33+(Volume!E44+Volume!E45+Volume!E46)*Inputs!$C$27*Inputs!$C$31 -> 2 | F7: =Volume!F23*Inputs!$C$26*Inputs!$C$30+Volume!F24*Inputs!$C$27*Inputs!$C$31+Volume!F25*Inputs!$C$28*Inputs!$C$32+Volume!F27*Inputs!$C$29*Inputs!$C$33+(Volume!F44+Volume!F45+Volume!F46)*Inputs!$C$27*Inputs!$C$31 -> 0 | G7: =Volume!G23*Inputs!$C$26*Inputs!$C$30+Volume!G24*Inputs!$C$27*Inputs!$C$31+Volume!G25*Inputs!$C$28*Inputs!$C$32+Volume!G27*Inputs!$C$29*Inputs!$C$33+(Volume!G44+Volume!G45+Volume!G46)*Inputs!$C$27*Inputs!$C$31 -> 0 | H7: =Volume!H23*Inputs!$C$26*Inputs!$C$30+Volume!H24*Inputs!$C$27*Inputs!$C$31+Volume!H25*Inputs!$C$28*Inputs!$C$32+Volume!H27*Inputs!$C$29*Inputs!$C$33+(Volume!H44+Volume!H45+Volume!H46)*Inputs!$C$27*Inputs!$C$31 -> 0 | I7: =Volume!I23*Inputs!$C$26*Inputs!$C$30+Volume!I24*Inputs!$C$27*Inputs!$C$31+Volume!I25*Inputs!$C$28*Inputs!$C$32+Volume!I27*Inputs!$C$29*Inputs!$C$33+(Volume!I44+Volume!I45+Volume!I46)*Inputs!$C$27*Inputs!$C$31 -> 2 | J7: =Volume!J23*Inputs!$C$26*Inputs!$C$30+Volume!J24*Inputs!$C$27*Inputs!$C$31+Volume!J25*Inputs!$C$28*Inputs!$C$32+Volume!J27*Inputs!$C$29*Inputs!$C$33+(Volume!J44+Volume!J45+Volume!J46)*Inputs!$C$27*Inputs!$C$31 -> 14 | K7: =Volume!K23*Inputs!$C$26*Inputs!$C$30+Volume!K24*Inputs!$C$27*Inputs!$C$31+Volume!K25*Inputs!$C$28*Inputs!$C$32+Volume!K27*Inputs!$C$29*Inputs!$C$33+(Volume!K44+Volume!K45+Volume!K46)*Inputs!$C$27*Inputs!$C$31 -> 2 | L7: =Volume!L23*Inputs!$C$26*Inputs!$C$30+Volume!L24*Inputs!$C$27*Inputs!$C$31+Volume!L25*Inputs!$C$28*Inputs!$C$32+Volume!L27*Inputs!$C$29*Inputs!$C$33+(Volume!L44+Volume!L45+Volume!L46)*Inputs!$C$27*Inputs!$C$31 -> 15 | ... S7: =Volume!S23*Inputs!$C$26*Inputs!$C$30+Volume!S24*Inputs!$C$27*Inputs!$C$31+Volume!S25*Inputs!$C$28*Inputs!$C$32+Volume!S27*Inputs!$C$29*Inputs!$C$33+(Volume!S44+Volume!S45+Volume!S46)*Inputs!$C$27*Inputs!$C$31 -> 15.18
A8: Facilitators needed this month (placements / max events each) | B8: people | C8: =MAX(E8:G8) -> 1 | D8: =MAX(H8:S8) -> 9 | E8: =ROUNDUP(E6/Inputs!$C$34,0) -> 1 | F8: =ROUNDUP(F6/Inputs!$C$34,0) -> 0 | G8: =ROUNDUP(G6/Inputs!$C$34,0) -> 0 | H8: =ROUNDUP(H6/Inputs!$C$34,0) -> 0 | I8: =ROUNDUP(I6/Inputs!$C$34,0) -> 1 | J8: =ROUNDUP(J6/Inputs!$C$34,0) -> 3 | K8: =ROUNDUP(K6/Inputs!$C$34,0) -> 1 | L8: =ROUNDUP(L6/Inputs!$C$34,0) -> 4 | ... S8: =ROUNDUP(S6/Inputs!$C$34,0) -> 8
A9: Certified facilitator pool (grows when needed, never shrinks) | B9: people | C9: =G9 -> 2 | D9: =S9 -> 9 | E9: =MAX(Inputs!$C$35,E8) -> 2 | F9: =MAX(E9,F8) -> 2 | G9: =MAX(F9,G8) -> 2 | H9: =MAX(G9,H8) -> 2 | I9: =MAX(H9,I8) -> 2 | J9: =MAX(I9,J8) -> 3 | K9: =MAX(J9,K8) -> 3 | L9: =MAX(K9,L8) -> 4 | M9: =MAX(L9,M8) -> 4 | ... S9: =MAX(R9,S8) -> 9
A10: New facilitators to certify this month | B10: people | C10: =SUM(E10:G10) -> 0 | D10: =SUM(H10:S10) -> 7 | E10: =E9-Inputs!$C$35 -> 0 | F10: =F9-E9 -> 0 | G10: =G9-F9 -> 0 | H10: =H9-G9 -> 0 | I10: =I9-H9 -> 0 | J10: =J9-I9 -> 1 | K10: =K9-J9 -> 0 | L10: =L9-K9 -> 1 | M10: =M9-L9 -> 0 | ... S10: =S9-R9 -> 0
A11: Your plan (11 by Nov 2026) minus need: spare facilitators | B11: people | C11: =MIN(E11:G11) -> 10 | D11: =MIN(H11:S11) -> 2 | E11: =Inputs!$C$36-E8 -> 10 | F11: =Inputs!$C$36-F8 -> 11 | G11: =Inputs!$C$36-G8 -> 11 | H11: =Inputs!$C$36-H8 -> 11 | I11: =Inputs!$C$36-I8 -> 10 | J11: =Inputs!$C$36-J8 -> 8 | K11: =Inputs!$C$36-K8 -> 10 | L11: =Inputs!$C$36-L8 -> 7 | ... S11: =Inputs!$C$36-S8 -> 3
A13: Step triggers
A14: B2B events, average of last 3 months | B14: events | C14: =MAX(E14:G14) -> 0 | D14: =MAX(H14:S14) -> 5.3333333 | E14: =AVERAGE(Volume!E29:E29) -> 0 | F14: =AVERAGE(Volume!E29:F29) -> 0 | G14: =AVERAGE(Volume!E29:G29) -> 0 | H14: =AVERAGE(Volume!F29:H29) -> 0 | I14: =AVERAGE(Volume!G29:I29) -> 0 | J14: =AVERAGE(Volume!H29:J29) -> 0.66666667 | K14: =AVERAGE(Volume!I29:K29) -> 1 | L14: =AVERAGE(Volume!J29:L29) -> 1.6666667 | M14: =AVERAGE(Volume!K29:M29) -> 1.3333333 | N14: =AVERAGE(Volume!L29:N29) -> 2 | ... S14: =AVERAGE(Volume!Q29:S29) -> 5.3333333
A15: Project Manager hired? (1 = yes; starts the month after the trigger) | B15: flag | C15: =G15 -> 0 | D15: =S15 -> 1 | E15: =0 -> 0 | F15: =IF(OR(E15=1,E14>=Inputs!$C$57),1,0) -> 0 | G15: =IF(OR(F15=1,F14>=Inputs!$C$57),1,0) -> 0 | H15: =IF(OR(G15=1,G14>=Inputs!$C$57),1,0) -> 0 | I15: =IF(OR(H15=1,H14>=Inputs!$C$57),1,0) -> 0 | J15: =IF(OR(I15=1,I14>=Inputs!$C$57),1,0) -> 0 | K15: =IF(OR(J15=1,J14>=Inputs!$C$57),1,0) -> 0 | L15: =IF(OR(K15=1,K14>=Inputs!$C$57),1,0) -> 0 | M15: =IF(OR(L15=1,L14>=Inputs!$C$57),1,0) -> 0 | ... S15: =IF(OR(R15=1,R14>=Inputs!$C$57),1,0) -> 1
A16: Account Manager active? (1 = yes) | B16: flag | C16: =G16 -> 0 | D16: =S16 -> 0 | E16: =IF(AND(Inputs!$C$52=1,Volume!E6>=IFERROR(MATCH(Inputs!$C$54,Volume!$E$4:$S$4,0),99)),1,0) -> 0 | F16: =IF(AND(Inputs!$C$52=1,Volume!F6>=IFERROR(MATCH(Inputs!$C$54,Volume!$E$4:$S$4,0),99)),1,0) -> 0 | G16: =IF(AND(Inputs!$C$52=1,Volume!G6>=IFERROR(MATCH(Inputs!$C$54,Volume!$E$4:$S$4,0),99)),1,0) -> 0 | H16: =IF(AND(Inputs!$C$52=1,Volume!H6>=IFERROR(MATCH(Inputs!$C$54,Volume!$E$4:$S$4,0),99)),1,0) -> 0 | I16: =IF(AND(Inputs!$C$52=1,Volume!I6>=IFERROR(MATCH(Inputs!$C$54,Volume!$E$4:$S$4,0),99)),1,0) -> 0 | J16: =IF(AND(Inputs!$C$52=1,Volume!J6>=IFERROR(MATCH(Inputs!$C$54,Volume!$E$4:$S$4,0),99)),1,0) -> 0 | K16: =IF(AND(Inputs!$C$52=1,Volume!K6>=IFERROR(MATCH(Inputs!$C$54,Volume!$E$4:$S$4,0),99)),1,0) -> 0 | L16: =IF(AND(Inputs!$C$52=1,Volume!L6>=IFERROR(MATCH(Inputs!$C$54,Volume!$E$4:$S$4,0),99)),1,0) -> 0 | ... S16: =IF(AND(Inputs!$C$52=1,Volume!S6>=IFERROR(MATCH(Inputs!$C$54,Volume!$E$4:$S$4,0),99)),1,0) -> 0
A17: Founder salaries active? (1 = yes) | B17: flag | C17: =G17 -> 0 | D17: =S17 -> 1 | E17: =IF(Volume!E6>=IFERROR(MATCH(Inputs!$C$51,Volume!$E$4:$S$4,0),99),1,0) -> 0 | F17: =IF(Volume!F6>=IFERROR(MATCH(Inputs!$C$51,Volume!$E$4:$S$4,0),99),1,0) -> 0 | G17: =IF(Volume!G6>=IFERROR(MATCH(Inputs!$C$51,Volume!$E$4:$S$4,0),99),1,0) -> 0 | H17: =IF(Volume!H6>=IFERROR(MATCH(Inputs!$C$51,Volume!$E$4:$S$4,0),99),1,0) -> 1 | I17: =IF(Volume!I6>=IFERROR(MATCH(Inputs!$C$51,Volume!$E$4:$S$4,0),99),1,0) -> 1 | J17: =IF(Volume!J6>=IFERROR(MATCH(Inputs!$C$51,Volume!$E$4:$S$4,0),99),1,0) -> 1 | K17: =IF(Volume!K6>=IFERROR(MATCH(Inputs!$C$51,Volume!$E$4:$S$4,0),99),1,0) -> 1 | L17: =IF(Volume!L6>=IFERROR(MATCH(Inputs!$C$51,Volume!$E$4:$S$4,0),99),1,0) -> 1 | ... S17: =IF(Volume!S6>=IFERROR(MATCH(Inputs!$C$51,Volume!$E$4:$S$4,0),99),1,0) -> 1
A18: Invoices to send this month | B18: invoices | C18: =MAX(E18:G18) -> 3.33 | D18: =MAX(H18:S18) -> 14.5 | E18: =Volume!E23+Volume!E24+Volume!E25+Volume!E26+Volume!E27+Inputs!$C$59+Volume!E39+Volume!E40+Volume!E41+Volume!E44+Volume!E45+Volume!E46+Volume!E47 -> 3.33 | F18: =Volume!F23+Volume!F24+Volume!F25+Volume!F26+Volume!F27+Inputs!$C$59+Volume!F39+Volume!F40+Volume!F41+Volume!F44+Volume!F45+Volume!F46+Volume!F47 -> 3.33 | G18: =Volume!G23+Volume!G24+Volume!G25+Volume!G26+Volume!G27+Inputs!$C$59+Volume!G39+Volume!G40+Volume!G41+Volume!G44+Volume!G45+Volume!G46+Volume!G47 -> 2.33 | H18: =Volume!H23+Volume!H24+Volume!H25+Volume!H26+Volume!H27+Inputs!$C$59+Volume!H39+Volume!H40+Volume!H41+Volume!H44+Volume!H45+Volume!H46+Volume!H47 -> 2.33 | I18: =Volume!I23+Volume!I24+Volume!I25+Volume!I26+Volume!I27+Inputs!$C$59+Volume!I39+Volume!I40+Volume!I41+Volume!I44+Volume!I45+Volume!I46+Volume!I47 -> 6.91 | J18: =Volume!J23+Volume!J24+Volume!J25+Volume!J26+Volume!J27+Inputs!$C$59+Volume!J39+Volume!J40+Volume!J41+Volume!J44+Volume!J45+Volume!J46+Volume!J47 -> 6.33 | K18: =Volume!K23+Volume!K24+Volume!K25+Volume!K26+Volume!K27+Inputs!$C$59+Volume!K39+Volume!K40+Volume!K41+Volume!K44+Volume!K45+Volume!K46+Volume!K47 -> 5.33 | L18: =Volume!L23+Volume!L24+Volume!L25+Volume!L26+Volume!L27+Inputs!$C$59+Volume!L39+Volume!L40+Volume!L41+Volume!L44+Volume!L45+Volume!L46+Volume!L47 -> 7.41 | ... S18: =Volume!S23+Volume!S24+Volume!S25+Volume!S26+Volume!S27+Inputs!$C$59+Volume!S39+Volume!S40+Volume!S41+Volume!S44+Volume!S45+Volume!S46+Volume!S47 -> 12.5
A19: Second admin hired? (1 = yes; stays once hired) | B19: flag | C19: =G19 -> 0 | D19: =S19 -> 1 | E19: =IF(E18>Inputs!$C$58,1,0) -> 0 | F19: =IF(OR(E19=1,F18>Inputs!$C$58),1,0) -> 0 | G19: =IF(OR(F19=1,G18>Inputs!$C$58),1,0) -> 0 | H19: =IF(OR(G19=1,H18>Inputs!$C$58),1,0) -> 0 | I19: =IF(OR(H19=1,I18>Inputs!$C$58),1,0) -> 0 | J19: =IF(OR(I19=1,J18>Inputs!$C$58),1,0) -> 0 | K19: =IF(OR(J19=1,K18>Inputs!$C$58),1,0) -> 0 | L19: =IF(OR(K19=1,L18>Inputs!$C$58),1,0) -> 0 | M19: =IF(OR(L19=1,M18>Inputs!$C$58),1,0) -> 0 | ... S19: =IF(OR(R19=1,S18>Inputs!$C$58),1,0) -> 1
A21: Fixed costs per month (Rp million)
A22: L0 Base team (your 2027 list: 6 people) | B22: Rp m | C22: =SUM(E22:G22) -> 33.9 | D22: =SUM(H22:S22) -> 135.6 | E22: =Inputs!$C$39+Inputs!$C$40+Inputs!$C$41+Inputs!$C$42+Inputs!$C$43+Inputs!$C$44 -> 11.3 | F22: =Inputs!$C$39+Inputs!$C$40+Inputs!$C$41+Inputs!$C$42+Inputs!$C$43+Inputs!$C$44 -> 11.3 | G22: =Inputs!$C$39+Inputs!$C$40+Inputs!$C$41+Inputs!$C$42+Inputs!$C$43+Inputs!$C$44 -> 11.3 | H22: =Inputs!$C$39+Inputs!$C$40+Inputs!$C$41+Inputs!$C$42+Inputs!$C$43+Inputs!$C$44 -> 11.3 | I22: =Inputs!$C$39+Inputs!$C$40+Inputs!$C$41+Inputs!$C$42+Inputs!$C$43+Inputs!$C$44 -> 11.3 | J22: =Inputs!$C$39+Inputs!$C$40+Inputs!$C$41+Inputs!$C$42+Inputs!$C$43+Inputs!$C$44 -> 11.3 | K22: =Inputs!$C$39+Inputs!$C$40+Inputs!$C$41+Inputs!$C$42+Inputs!$C$43+Inputs!$C$44 -> 11.3 | L22: =Inputs!$C$39+Inputs!$C$40+Inputs!$C$41+Inputs!$C$42+Inputs!$C$43+Inputs!$C$44 -> 11.3 | ... S22: =Inputs!$C$39+Inputs!$C$40+Inputs!$C$41+Inputs!$C$42+Inputs!$C$43+Inputs!$C$44 -> 11.3
A23: L0 Software and IG ads | B23: Rp m | C23: =SUM(E23:G23) -> 6.23975 | D23: =SUM(H23:S23) -> 24.959 | E23: =Inputs!$C$45 -> 2.0799167 | F23: =Inputs!$C$45 -> 2.0799167 | G23: =Inputs!$C$45 -> 2.0799167 | H23: =Inputs!$C$45 -> 2.0799167 | I23: =Inputs!$C$45 -> 2.0799167 | J23: =Inputs!$C$45 -> 2.0799167 | K23: =Inputs!$C$45 -> 2.0799167 | L23: =Inputs!$C$45 -> 2.0799167 | ... S23: =Inputs!$C$45 -> 2.0799167
A24: L0 Office | B24: Rp m | C24: =SUM(E24:G24) -> 17.4 | D24: =SUM(H24:S24) -> 69.6 | E24: =Inputs!$C$46 -> 5.8 | F24: =Inputs!$C$46 -> 5.8 | G24: =Inputs!$C$46 -> 5.8 | H24: =Inputs!$C$46 -> 5.8 | I24: =Inputs!$C$46 -> 5.8 | J24: =Inputs!$C$46 -> 5.8 | K24: =Inputs!$C$46 -> 5.8 | L24: =Inputs!$C$46 -> 5.8 | ... S24: =Inputs!$C$46 -> 5.8
A25: L0 Accountant / tax (estimate) | B25: Rp m | C25: =SUM(E25:G25) -> 4.5 | D25: =SUM(H25:S25) -> 18 | E25: =Inputs!$C$47 -> 1.5 | F25: =Inputs!$C$47 -> 1.5 | G25: =Inputs!$C$47 -> 1.5 | H25: =Inputs!$C$47 -> 1.5 | I25: =Inputs!$C$47 -> 1.5 | J25: =Inputs!$C$47 -> 1.5 | K25: =Inputs!$C$47 -> 1.5 | L25: =Inputs!$C$47 -> 1.5 | ... S25: =Inputs!$C$47 -> 1.5
A26: Founder salaries (Pay_Plan when the growth plan is on) | B26: Rp m | C26: =SUM(E26:G26) -> 30 | D26: =SUM(H26:S26) -> 270 | E26: =IF(Inputs!$C$105=1,Pay_Plan!E11,E17*(Inputs!$C$49+Inputs!$C$50)) -> 10 | F26: =IF(Inputs!$C$105=1,Pay_Plan!F11,F17*(Inputs!$C$49+Inputs!$C$50)) -> 10 | G26: =IF(Inputs!$C$105=1,Pay_Plan!G11,G17*(Inputs!$C$49+Inputs!$C$50)) -> 10 | H26: =IF(Inputs!$C$105=1,Pay_Plan!H11,H17*(Inputs!$C$49+Inputs!$C$50)) -> 10 | I26: =IF(Inputs!$C$105=1,Pay_Plan!I11,I17*(Inputs!$C$49+Inputs!$C$50)) -> 10 | J26: =IF(Inputs!$C$105=1,Pay_Plan!J11,J17*(Inputs!$C$49+Inputs!$C$50)) -> 25 | K26: =IF(Inputs!$C$105=1,Pay_Plan!K11,K17*(Inputs!$C$49+Inputs!$C$50)) -> 25 | L26: =IF(Inputs!$C$105=1,Pay_Plan!L11,L17*(Inputs!$C$49+Inputs!$C$50)) -> 25 | ... S26: =IF(Inputs!$C$105=1,Pay_Plan!S11,S17*(Inputs!$C$49+Inputs!$C$50)) -> 25
A27: L1 Account Manager | B27: Rp m | C27: =SUM(E27:G27) -> 0 | D27: =SUM(H27:S27) -> 0 | E27: =E16*Inputs!$C$53 -> 0 | F27: =F16*Inputs!$C$53 -> 0 | G27: =G16*Inputs!$C$53 -> 0 | H27: =H16*Inputs!$C$53 -> 0 | I27: =I16*Inputs!$C$53 -> 0 | J27: =J16*Inputs!$C$53 -> 0 | K27: =K16*Inputs!$C$53 -> 0 | L27: =L16*Inputs!$C$53 -> 0 | ... S27: =S16*Inputs!$C$53 -> 0
A28: L1 Sales travel (from Oct-26 when the growth plan is on: we pitch now) | B28: Rp m | C28: =SUM(E28:G28) -> 6 | D28: =SUM(H28:S28) -> 24 | E28: =IF(Inputs!$C$105=1,Inputs!$C$55,IF(Volume!E6>=IFERROR(MATCH(Inputs!$C$54,Volume!$E$4:$S$4,0),99),Inputs!$C$55,0)) -> 2 | F28: =IF(Inputs!$C$105=1,Inputs!$C$55,IF(Volume!F6>=IFERROR(MATCH(Inputs!$C$54,Volume!$E$4:$S$4,0),99),Inputs!$C$55,0)) -> 2 | G28: =IF(Inputs!$C$105=1,Inputs!$C$55,IF(Volume!G6>=IFERROR(MATCH(Inputs!$C$54,Volume!$E$4:$S$4,0),99),Inputs!$C$55,0)) -> 2 | H28: =IF(Inputs!$C$105=1,Inputs!$C$55,IF(Volume!H6>=IFERROR(MATCH(Inputs!$C$54,Volume!$E$4:$S$4,0),99),Inputs!$C$55,0)) -> 2 | I28: =IF(Inputs!$C$105=1,Inputs!$C$55,IF(Volume!I6>=IFERROR(MATCH(Inputs!$C$54,Volume!$E$4:$S$4,0),99),Inputs!$C$55,0)) -> 2 | J28: =IF(Inputs!$C$105=1,Inputs!$C$55,IF(Volume!J6>=IFERROR(MATCH(Inputs!$C$54,Volume!$E$4:$S$4,0),99),Inputs!$C$55,0)) -> 2 | K28: =IF(Inputs!$C$105=1,Inputs!$C$55,IF(Volume!K6>=IFERROR(MATCH(Inputs!$C$54,Volume!$E$4:$S$4,0),99),Inputs!$C$55,0)) -> 2 | L28: =IF(Inputs!$C$105=1,Inputs!$C$55,IF(Volume!L6>=IFERROR(MATCH(Inputs!$C$54,Volume!$E$4:$S$4,0),99),Inputs!$C$55,0)) -> 2 | ... S28: =IF(Inputs!$C$105=1,Inputs!$C$55,IF(Volume!S6>=IFERROR(MATCH(Inputs!$C$54,Volume!$E$4:$S$4,0),99),Inputs!$C$55,0)) -> 2
A29: L2 Project Manager (per project when the growth plan is on) | B29: Rp m | C29: =SUM(E29:G29) -> 0 | D29: =SUM(H29:S29) -> 78.58 | E29: =IF(Inputs!$C$105=1,Inputs!$C$114*E43,E15*Inputs!$C$56) -> 0 | F29: =IF(Inputs!$C$105=1,Inputs!$C$114*F43,F15*Inputs!$C$56) -> 0 | G29: =IF(Inputs!$C$105=1,Inputs!$C$114*G43,G15*Inputs!$C$56) -> 0 | H29: =IF(Inputs!$C$105=1,Inputs!$C$114*H43,H15*Inputs!$C$56) -> 0 | I29: =IF(Inputs!$C$105=1,Inputs!$C$114*I43,I15*Inputs!$C$56) -> 2 | J29: =IF(Inputs!$C$105=1,Inputs!$C$114*J43,J15*Inputs!$C$56) -> 4 | K29: =IF(Inputs!$C$105=1,Inputs!$C$114*K43,K15*Inputs!$C$56) -> 2 | L29: =IF(Inputs!$C$105=1,Inputs!$C$114*L43,L15*Inputs!$C$56) -> 5 | ... S29: =IF(Inputs!$C$105=1,Inputs!$C$114*S43,S15*Inputs!$C$56) -> 13.18
A30: L2 Second admin | B30: Rp m | C30: =SUM(E30:G30) -> 0 | D30: =SUM(H30:S30) -> 9 | E30: =E19*Inputs!$C$43 -> 0 | F30: =F19*Inputs!$C$43 -> 0 | G30: =G19*Inputs!$C$43 -> 0 | H30: =H19*Inputs!$C$43 -> 0 | I30: =I19*Inputs!$C$43 -> 0 | J30: =J19*Inputs!$C$43 -> 0 | K30: =K19*Inputs!$C$43 -> 0 | L30: =L19*Inputs!$C$43 -> 0 | ... S30: =S19*Inputs!$C$43 -> 3
A31: L3 Facilitator certification (one-off, ahead of need) | B31: Rp m | C31: =SUM(E31:G31) -> 0 | D31: =SUM(H31:S31) -> 17.5 | E31: =E47*Inputs!$C$37 -> 0 | F31: =F47*Inputs!$C$37 -> 0 | G31: =G47*Inputs!$C$37 -> 0 | H31: =H47*Inputs!$C$37 -> 2.5 | I31: =I47*Inputs!$C$37 -> 0 | J31: =J47*Inputs!$C$37 -> 2.5 | K31: =K47*Inputs!$C$37 -> 0 | L31: =L47*Inputs!$C$37 -> 2.5 | ... S31: =S47*Inputs!$C$37 -> 0
A32: Total fixed cost | B32: Rp m | C32: =SUM(E32:G32) -> 96.63639 | D32: =SUM(H32:S32) -> 882.92578 | E32: =SUM(E22:E31)+E40 -> 31.685442 | F32: =SUM(F22:F31)+F40 -> 32.474586 | G32: =SUM(G22:G31)+G40 -> 32.476361 | H32: =SUM(H22:H31)+H40 -> 42.882367 | I32: =SUM(I22:I31)+I40 -> 42.785582 | J32: =SUM(J22:J31)+J40 -> 62.411306 | K32: =SUM(K22:K31)+K40 -> 58.300834 | L32: =SUM(L22:L31)+L40 -> 67.360432 | ... S32: =SUM(S22:S31)+S40 -> 97.312888
A34: Growth plan fixed costs (v15)
A35: Growth plan on? (1 = yes) | B35: flag | C35: =MAX(E35:G35) -> 1 | D35: =MAX(H35:S35) -> 1 | E35: =Inputs!$C$105 -> 1 | F35: =Inputs!$C$105 -> 1 | G35: =Inputs!$C$105 -> 1 | H35: =Inputs!$C$105 -> 1 | I35: =Inputs!$C$105 -> 1 | J35: =Inputs!$C$105 -> 1 | K35: =Inputs!$C$105 -> 1 | L35: =Inputs!$C$105 -> 1 | ... S35: =Inputs!$C$105 -> 1
A36: BPJS + THR paid? (Pay_Plan) | B36: flag | C36: =MAX(E36:G36) -> 0 | D36: =MAX(H36:S36) -> 1 | E36: =E35*Pay_Plan!E14 -> 0 | F36: =F35*Pay_Plan!F14 -> 0 | G36: =G35*Pay_Plan!G14 -> 0 | H36: =H35*Pay_Plan!H14 -> 1 | I36: =I35*Pay_Plan!I14 -> 1 | J36: =J35*Pay_Plan!J14 -> 1 | K36: =K35*Pay_Plan!K14 -> 1 | L36: =L35*Pay_Plan!L14 -> 1 | ... S36: =S35*Pay_Plan!S14 -> 1
A37: Team pay change vs the 2027 budget (Pay_Plan, incl. BPJS and THR) | B37: Rp m | C37: =SUM(E37:G37) -> -1.4033597 | D37: =SUM(H37:S37) -> 143.05783 | E37: =E35*(Pay_Plan!E15-E22) -> -0.99447438 | F37: =F35*(Pay_Plan!F15-F22) -> -0.20533018 | G37: =G35*(Pay_Plan!G15-G22) -> -0.20355518 | H37: =H35*(Pay_Plan!H15-H22) -> 4.1710588 | I37: =I35*(Pay_Plan!I15-I22) -> 4.5718503 | J37: =J35*(Pay_Plan!J15-J22) -> 4.6949629 | K37: =K35*(Pay_Plan!K15-K22) -> 5.01953 | L37: =L35*(Pay_Plan!L15-L22) -> 8.5704322 | ... S37: =S35*(Pay_Plan!S15-S22) -> 21.4508
A38: Extra IG ads (Pay_Plan) + referral rewards (B2C sheet) | B38: Rp m | C38: =SUM(E38:G38) -> 0 | D38: =SUM(H38:S38) -> 44.628941 | E38: =E35*(Pay_Plan!E12+B2C!E53) -> 0 | F38: =F35*(Pay_Plan!F12+B2C!F53) -> 0 | G38: =G35*(Pay_Plan!G12+B2C!G53) -> 0 | H38: =H35*(Pay_Plan!H12+B2C!H53) -> 3.5313912 | I38: =I35*(Pay_Plan!I12+B2C!I53) -> 3.5338151 | J38: =J35*(Pay_Plan!J12+B2C!J53) -> 3.5364262 | K38: =K35*(Pay_Plan!K12+B2C!K53) -> 3.6013872 | L38: =L35*(Pay_Plan!L12+B2C!L53) -> 3.6100829 | ... S38: =S35*(Pay_Plan!S12+B2C!S53) -> 4.002171
A39: Sales co-founder | B39: Rp m | C39: =SUM(E39:G39) -> 0 | D39: =SUM(H39:S39) -> 48 | E39: =Inputs!$C$105*IF(Volume!E6>=IFERROR(MATCH(Inputs!$C$110,Volume!$E$4:$S$4,0),99),Inputs!$C$109,0) -> 0 | F39: =Inputs!$C$105*IF(Volume!F6>=IFERROR(MATCH(Inputs!$C$110,Volume!$E$4:$S$4,0),99),Inputs!$C$109,0) -> 0 | G39: =Inputs!$C$105*IF(Volume!G6>=IFERROR(MATCH(Inputs!$C$110,Volume!$E$4:$S$4,0),99),Inputs!$C$109,0) -> 0 | H39: =Inputs!$C$105*IF(Volume!H6>=IFERROR(MATCH(Inputs!$C$110,Volume!$E$4:$S$4,0),99),Inputs!$C$109,0) -> 0 | I39: =Inputs!$C$105*IF(Volume!I6>=IFERROR(MATCH(Inputs!$C$110,Volume!$E$4:$S$4,0),99),Inputs!$C$109,0) -> 0 | J39: =Inputs!$C$105*IF(Volume!J6>=IFERROR(MATCH(Inputs!$C$110,Volume!$E$4:$S$4,0),99),Inputs!$C$109,0) -> 0 | K39: =Inputs!$C$105*IF(Volume!K6>=IFERROR(MATCH(Inputs!$C$110,Volume!$E$4:$S$4,0),99),Inputs!$C$109,0) -> 0 | L39: =Inputs!$C$105*IF(Volume!L6>=IFERROR(MATCH(Inputs!$C$110,Volume!$E$4:$S$4,0),99),Inputs!$C$109,0) -> 0 | ... S39: =Inputs!$C$105*IF(Volume!S6>=IFERROR(MATCH(Inputs!$C$110,Volume!$E$4:$S$4,0),99),Inputs!$C$109,0) -> 8
A40: Growth plan fixed cost | B40: Rp m | C40: =SUM(E40:G40) -> -1.4033597 | D40: =SUM(H40:S40) -> 235.68678 | E40: =SUM(E37:E39) -> -0.99447438 | F40: =SUM(F37:F39) -> -0.20533018 | G40: =SUM(G37:G39) -> -0.20355518 | H40: =SUM(H37:H39) -> 7.70245 | I40: =SUM(I37:I39) -> 8.1056654 | J40: =SUM(J37:J39) -> 8.2313892 | K40: =SUM(K37:K39) -> 8.6209172 | L40: =SUM(L37:L39) -> 12.180515 | ... S40: =SUM(S37:S39) -> 33.452971
A42: Operations load (COO review)
A43: B2B projects this month (one event, training or school = one project) | B43: projects | C43: =SUM(E43:G43) -> 0 | D43: =SUM(H43:S43) -> 39.29 | E43: =Volume!E29+Volume!E44+Volume!E45+Volume!E46+Volume!E47 -> 0 | F43: =Volume!F29+Volume!F44+Volume!F45+Volume!F46+Volume!F47 -> 0 | G43: =Volume!G29+Volume!G44+Volume!G45+Volume!G46+Volume!G47 -> 0 | H43: =Volume!H29+Volume!H44+Volume!H45+Volume!H46+Volume!H47 -> 0 | I43: =Volume!I29+Volume!I44+Volume!I45+Volume!I46+Volume!I47 -> 1 | J43: =Volume!J29+Volume!J44+Volume!J45+Volume!J46+Volume!J47 -> 2 | K43: =Volume!K29+Volume!K44+Volume!K45+Volume!K46+Volume!K47 -> 1 | L43: =Volume!L29+Volume!L44+Volume!L45+Volume!L46+Volume!L47 -> 2.5 | ... S43: =Volume!S29+Volume!S44+Volume!S45+Volume!S46+Volume!S47 -> 6.59
A44: Project managers needed | B44: people | C44: =MAX(E44:G44) -> 0 | D44: =MAX(H44:S44) -> 4 | E44: =ROUNDUP(E43/Inputs!$C$115,0) -> 0 | F44: =ROUNDUP(F43/Inputs!$C$115,0) -> 0 | G44: =ROUNDUP(G43/Inputs!$C$115,0) -> 0 | H44: =ROUNDUP(H43/Inputs!$C$115,0) -> 0 | I44: =ROUNDUP(I43/Inputs!$C$115,0) -> 1 | J44: =ROUNDUP(J43/Inputs!$C$115,0) -> 1 | K44: =ROUNDUP(K43/Inputs!$C$115,0) -> 1 | L44: =ROUNDUP(L43/Inputs!$C$115,0) -> 2 | ... S44: =ROUNDUP(S43/Inputs!$C$115,0) -> 4
A45: Load on one project manager (100% = full) | B45: % | C45: =MAX(E45:G45) -> 0 | D45: =MAX(H45:S45) -> 3.795 | E45: =E43/Inputs!$C$115 -> 0 | F45: =F43/Inputs!$C$115 -> 0 | G45: =G43/Inputs!$C$115 -> 0 | H45: =H43/Inputs!$C$115 -> 0 | I45: =I43/Inputs!$C$115 -> 0.5 | J45: =J43/Inputs!$C$115 -> 1 | K45: =K43/Inputs!$C$115 -> 0.5 | L45: =L43/Inputs!$C$115 -> 1.25 | ... S45: =S43/Inputs!$C$115 -> 3.295
A46: Trainer load (placements / what the trainer pool can do) | B46: % | C46: =MAX(E46:G46) -> 0.5 | D46: =MAX(H46:S46) -> 1 | E46: =IF(E9=0,0,E6/(E9*Inputs!$C$34)) -> 0.5 | F46: =IF(F9=0,0,F6/(F9*Inputs!$C$34)) -> 0 | G46: =IF(G9=0,0,G6/(G9*Inputs!$C$34)) -> 0 | H46: =IF(H9=0,0,H6/(H9*Inputs!$C$34)) -> 0 | I46: =IF(I9=0,0,I6/(I9*Inputs!$C$34)) -> 0.5 | J46: =IF(J9=0,0,J6/(J9*Inputs!$C$34)) -> 1 | K46: =IF(K9=0,0,K6/(K9*Inputs!$C$34)) -> 0.33333333 | L46: =IF(L9=0,0,L6/(L9*Inputs!$C$34)) -> 0.875 | ... S46: =IF(S9=0,0,S6/(S9*Inputs!$C$34)) -> 0.84333333
A47: Trainers to certify this month (ahead of need) | B47: people | C47: =SUM(E47:G47) -> 0 | D47: =SUM(H47:S47) -> 7 | E47: =IF(Inputs!$C$105=1,IFERROR(INDEX($E$10:$S$10,Volume!E6+Inputs!$C$116),0),E10) -> 0 | F47: =IF(Inputs!$C$105=1,IFERROR(INDEX($E$10:$S$10,Volume!F6+Inputs!$C$116),0),F10) -> 0 | G47: =IF(Inputs!$C$105=1,IFERROR(INDEX($E$10:$S$10,Volume!G6+Inputs!$C$116),0),G10) -> 0 | H47: =IF(Inputs!$C$105=1,IFERROR(INDEX($E$10:$S$10,Volume!H6+Inputs!$C$116),0),H10) -> 1 | I47: =IF(Inputs!$C$105=1,IFERROR(INDEX($E$10:$S$10,Volume!I6+Inputs!$C$116),0),I10) -> 0 | J47: =IF(Inputs!$C$105=1,IFERROR(INDEX($E$10:$S$10,Volume!J6+Inputs!$C$116),0),J10) -> 1 | K47: =IF(Inputs!$C$105=1,IFERROR(INDEX($E$10:$S$10,Volume!K6+Inputs!$C$116),0),K10) -> 0 | L47: =IF(Inputs!$C$105=1,IFERROR(INDEX($E$10:$S$10,Volume!L6+Inputs!$C$116),0),L10) -> 1 | ... S47: =IF(Inputs!$C$105=1,IFERROR(INDEX($E$10:$S$10,Volume!S6+Inputs!$C$116),0),S10) -> 0

Sheet PnL
A1: Profit and loss by month (Rp million) - money counted when the event is delivered
A2: Rp million unless stated. Q4 2026 and FY 2027 columns are totals (or averages / peaks where stated).
A4: Line | B4: Unit | C4: Q4 2026 | D4: FY 2027 | E4: Oct-26 | F4: Nov-26 | G4: Dec-26 | H4: Jan-27 | I4: Feb-27 | J4: Mar-27 | K4: Apr-27 | L4: May-27 | M4: Jun-27 | N4: Jul-27 | O4: Aug-27 | P4: Sep-27 | Q4: Oct-27 | R4: Nov-27 | S4: Dec-27
A5: Revenue
A6: Flagship regulator ToT | B6: Rp m | C6: =SUM(E6:G6) -> 0 | D6: =SUM(H6:S6) -> 500 | E6: =Volume!E23*IF(Volume!E11=1,Unit_Economics!$B$4,Unit_Economics!$N$4) -> 0 | F6: =Volume!F23*IF(Volume!F11=1,Unit_Economics!$B$4,Unit_Economics!$N$4) -> 0 | G6: =Volume!G23*IF(Volume!G11=1,Unit_Economics!$B$4,Unit_Economics!$N$4) -> 0 | H6: =Volume!H23*IF(Volume!H11=1,Unit_Economics!$B$4,Unit_Economics!$N$4) -> 0 | I6: =Volume!I23*IF(Volume!I11=1,Unit_Economics!$B$4,Unit_Economics!$N$4) -> 0 | J6: =Volume!J23*IF(Volume!J11=1,Unit_Economics!$B$4,Unit_Economics!$N$4) -> 100 | K6: =Volume!K23*IF(Volume!K11=1,Unit_Economics!$B$4,Unit_Economics!$N$4) -> 0 | L6: =Volume!L23*IF(Volume!L11=1,Unit_Economics!$B$4,Unit_Economics!$N$4) -> 100 | ... S6: =Volume!S23*IF(Volume!S11=1,Unit_Economics!$B$4,Unit_Economics!$N$4) -> 0
A7: KPW / LPS regional ToT | B7: Rp m | C7: =SUM(E7:G7) -> 0 | D7: =SUM(H7:S7) -> 484.5 | E7: =Volume!E24*IF(Volume!E11=1,Unit_Economics!$B$5,Unit_Economics!$N$5) -> 0 | F7: =Volume!F24*IF(Volume!F11=1,Unit_Economics!$B$5,Unit_Economics!$N$5) -> 0 | G7: =Volume!G24*IF(Volume!G11=1,Unit_Economics!$B$5,Unit_Economics!$N$5) -> 0 | H7: =Volume!H24*IF(Volume!H11=1,Unit_Economics!$B$5,Unit_Economics!$N$5) -> 0 | I7: =Volume!I24*IF(Volume!I11=1,Unit_Economics!$B$5,Unit_Economics!$N$5) -> 0 | J7: =Volume!J24*IF(Volume!J11=1,Unit_Economics!$B$5,Unit_Economics!$N$5) -> 28.5 | K7: =Volume!K24*IF(Volume!K11=1,Unit_Economics!$B$5,Unit_Economics!$N$5) -> 0 | L7: =Volume!L24*IF(Volume!L11=1,Unit_Economics!$B$5,Unit_Economics!$N$5) -> 28.5 | ... S7: =Volume!S24*IF(Volume!S11=1,Unit_Economics!$B$5,Unit_Economics!$N$5) -> 142.5
A8: Bank KCP events | B8: Rp m | C8: =SUM(E8:G8) -> 0 | D8: =SUM(H8:S8) -> 374.5 | E8: =Volume!E25*IF(Volume!E11=1,Unit_Economics!$B$6,Unit_Economics!$N$6) -> 0 | F8: =Volume!F25*IF(Volume!F11=1,Unit_Economics!$B$6,Unit_Economics!$N$6) -> 0 | G8: =Volume!G25*IF(Volume!G11=1,Unit_Economics!$B$6,Unit_Economics!$N$6) -> 0 | H8: =Volume!H25*IF(Volume!H11=1,Unit_Economics!$B$6,Unit_Economics!$N$6) -> 0 | I8: =Volume!I25*IF(Volume!I11=1,Unit_Economics!$B$6,Unit_Economics!$N$6) -> 0 | J8: =Volume!J25*IF(Volume!J11=1,Unit_Economics!$B$6,Unit_Economics!$N$6) -> 0 | K8: =Volume!K25*IF(Volume!K11=1,Unit_Economics!$B$6,Unit_Economics!$N$6) -> 53.5 | L8: =Volume!L25*IF(Volume!L11=1,Unit_Economics!$B$6,Unit_Economics!$N$6) -> 0 | ... S8: =Volume!S25*IF(Volume!S11=1,Unit_Economics!$B$6,Unit_Economics!$N$6) -> 53.5
A9: Bank EAP | B9: Rp m | C9: =SUM(E9:G9) -> 45 | D9: =SUM(H9:S9) -> 435 | E9: =Volume!E26*IF(Volume!E11=1,Unit_Economics!$B$7,Unit_Economics!$N$7) -> 15 | F9: =Volume!F26*IF(Volume!F11=1,Unit_Economics!$B$7,Unit_Economics!$N$7) -> 15 | G9: =Volume!G26*IF(Volume!G11=1,Unit_Economics!$B$7,Unit_Economics!$N$7) -> 15 | H9: =Volume!H26*IF(Volume!H11=1,Unit_Economics!$B$7,Unit_Economics!$N$7) -> 15 | I9: =Volume!I26*IF(Volume!I11=1,Unit_Economics!$B$7,Unit_Economics!$N$7) -> 30 | J9: =Volume!J26*IF(Volume!J11=1,Unit_Economics!$B$7,Unit_Economics!$N$7) -> 30 | K9: =Volume!K26*IF(Volume!K11=1,Unit_Economics!$B$7,Unit_Economics!$N$7) -> 30 | L9: =Volume!L26*IF(Volume!L11=1,Unit_Economics!$B$7,Unit_Economics!$N$7) -> 30 | ... S9: =Volume!S26*IF(Volume!S11=1,Unit_Economics!$B$7,Unit_Economics!$N$7) -> 45
A10: B2C mass events | B10: Rp m | C10: =SUM(E10:G10) -> 4.144 | D10: =SUM(H10:S10) -> 16.576 | E10: =Volume!E27*IF(Volume!E11=1,Unit_Economics!$B$8,Unit_Economics!$N$8) -> 4.144 | F10: =Volume!F27*IF(Volume!F11=1,Unit_Economics!$B$8,Unit_Economics!$N$8) -> 0 | G10: =Volume!G27*IF(Volume!G11=1,Unit_Economics!$B$8,Unit_Economics!$N$8) -> 0 | H10: =Volume!H27*IF(Volume!H11=1,Unit_Economics!$B$8,Unit_Economics!$N$8) -> 0 | I10: =Volume!I27*IF(Volume!I11=1,Unit_Economics!$B$8,Unit_Economics!$N$8) -> 4.144 | J10: =Volume!J27*IF(Volume!J11=1,Unit_Economics!$B$8,Unit_Economics!$N$8) -> 0 | K10: =Volume!K27*IF(Volume!K11=1,Unit_Economics!$B$8,Unit_Economics!$N$8) -> 0 | L10: =Volume!L27*IF(Volume!L11=1,Unit_Economics!$B$8,Unit_Economics!$N$8) -> 0 | ... S10: =Volume!S27*IF(Volume!S11=1,Unit_Economics!$B$8,Unit_Economics!$N$8) -> 4.144
A11: B2C counseling | B11: Rp m | C11: =SUM(E11:G11) -> 5.270011 | D11: =SUM(H11:S11) -> 142.71057 | E11: =Volume!E28*Inputs!$C$14 -> 1.284617 | F11: =Volume!F28*Inputs!$C$14 -> 1.9606048 | G11: =Volume!G28*Inputs!$C$14 -> 2.0247892 | H11: =Volume!H28*Inputs!$C$14 -> 2.7373895 | I11: =Volume!I28*Inputs!$C$14 -> 5.7167365 | J11: =Volume!J28*Inputs!$C$14 -> 4.0491244 | K11: =Volume!K28*Inputs!$C$14 -> 8.5549431 | L11: =Volume!L28*Inputs!$C$14 -> 8.8890339 | ... S11: =Volume!S28*Inputs!$C$14 -> 17.406545
A12: Total revenue (incl. v16 lines, row 51) | B12: Rp m | C12: =SUM(E12:G12) -> 64.557011 | D12: =SUM(H12:S12) -> 2432.5546 | E12: =SUM(E6:E11)+E51 -> 20.428617 | F12: =SUM(F6:F11)+F51 -> 22.032105 | G12: =SUM(G6:G11)+G51 -> 22.096289 | H12: =SUM(H6:H11)+H51 -> 22.808889 | I12: =SUM(I6:I11)+I51 -> 71.830236 | J12: =SUM(J6:J11)+J51 -> 175.59012 | K12: =SUM(K6:K11)+K51 -> 110.16744 | L12: =SUM(L6:L11)+L51 -> 199.75153 | ... S12: =SUM(S6:S11)+S51 -> 303.27404
A14: Delivery cost
A15: Flagship | B15: Rp m | C15: =SUM(E15:G15) -> 0 | D15: =SUM(H15:S15) -> 140 | E15: =Volume!E23*IF(Volume!E11=1,Unit_Economics!$F$4,Unit_Economics!$O$4) -> 0 | F15: =Volume!F23*IF(Volume!F11=1,Unit_Economics!$F$4,Unit_Economics!$O$4) -> 0 | G15: =Volume!G23*IF(Volume!G11=1,Unit_Economics!$F$4,Unit_Economics!$O$4) -> 0 | H15: =Volume!H23*IF(Volume!H11=1,Unit_Economics!$F$4,Unit_Economics!$O$4) -> 0 | I15: =Volume!I23*IF(Volume!I11=1,Unit_Economics!$F$4,Unit_Economics!$O$4) -> 0 | J15: =Volume!J23*IF(Volume!J11=1,Unit_Economics!$F$4,Unit_Economics!$O$4) -> 28 | K15: =Volume!K23*IF(Volume!K11=1,Unit_Economics!$F$4,Unit_Economics!$O$4) -> 0 | L15: =Volume!L23*IF(Volume!L11=1,Unit_Economics!$F$4,Unit_Economics!$O$4) -> 28 | ... S15: =Volume!S23*IF(Volume!S11=1,Unit_Economics!$F$4,Unit_Economics!$O$4) -> 0
A16: KPW / LPS | B16: Rp m | C16: =SUM(E16:G16) -> 0 | D16: =SUM(H16:S16) -> 174.25 | E16: =Volume!E24*IF(Volume!E11=1,Unit_Economics!$F$5,Unit_Economics!$O$5) -> 0 | F16: =Volume!F24*IF(Volume!F11=1,Unit_Economics!$F$5,Unit_Economics!$O$5) -> 0 | G16: =Volume!G24*IF(Volume!G11=1,Unit_Economics!$F$5,Unit_Economics!$O$5) -> 0 | H16: =Volume!H24*IF(Volume!H11=1,Unit_Economics!$F$5,Unit_Economics!$O$5) -> 0 | I16: =Volume!I24*IF(Volume!I11=1,Unit_Economics!$F$5,Unit_Economics!$O$5) -> 0 | J16: =Volume!J24*IF(Volume!J11=1,Unit_Economics!$F$5,Unit_Economics!$O$5) -> 10.25 | K16: =Volume!K24*IF(Volume!K11=1,Unit_Economics!$F$5,Unit_Economics!$O$5) -> 0 | L16: =Volume!L24*IF(Volume!L11=1,Unit_Economics!$F$5,Unit_Economics!$O$5) -> 10.25 | ... S16: =Volume!S24*IF(Volume!S11=1,Unit_Economics!$F$5,Unit_Economics!$O$5) -> 51.25
A17: Bank KCP | B17: Rp m | C17: =SUM(E17:G17) -> 0 | D17: =SUM(H17:S17) -> 105 | E17: =Volume!E25*IF(Volume!E11=1,Unit_Economics!$F$6,Unit_Economics!$O$6) -> 0 | F17: =Volume!F25*IF(Volume!F11=1,Unit_Economics!$F$6,Unit_Economics!$O$6) -> 0 | G17: =Volume!G25*IF(Volume!G11=1,Unit_Economics!$F$6,Unit_Economics!$O$6) -> 0 | H17: =Volume!H25*IF(Volume!H11=1,Unit_Economics!$F$6,Unit_Economics!$O$6) -> 0 | I17: =Volume!I25*IF(Volume!I11=1,Unit_Economics!$F$6,Unit_Economics!$O$6) -> 0 | J17: =Volume!J25*IF(Volume!J11=1,Unit_Economics!$F$6,Unit_Economics!$O$6) -> 0 | K17: =Volume!K25*IF(Volume!K11=1,Unit_Economics!$F$6,Unit_Economics!$O$6) -> 15 | L17: =Volume!L25*IF(Volume!L11=1,Unit_Economics!$F$6,Unit_Economics!$O$6) -> 0 | ... S17: =Volume!S25*IF(Volume!S11=1,Unit_Economics!$F$6,Unit_Economics!$O$6) -> 15
A18: Bank EAP | B18: Rp m | C18: =SUM(E18:G18) -> 15 | D18: =SUM(H18:S18) -> 145 | E18: =Volume!E26*IF(Volume!E11=1,Unit_Economics!$F$7,Unit_Economics!$O$7) -> 5 | F18: =Volume!F26*IF(Volume!F11=1,Unit_Economics!$F$7,Unit_Economics!$O$7) -> 5 | G18: =Volume!G26*IF(Volume!G11=1,Unit_Economics!$F$7,Unit_Economics!$O$7) -> 5 | H18: =Volume!H26*IF(Volume!H11=1,Unit_Economics!$F$7,Unit_Economics!$O$7) -> 5 | I18: =Volume!I26*IF(Volume!I11=1,Unit_Economics!$F$7,Unit_Economics!$O$7) -> 10 | J18: =Volume!J26*IF(Volume!J11=1,Unit_Economics!$F$7,Unit_Economics!$O$7) -> 10 | K18: =Volume!K26*IF(Volume!K11=1,Unit_Economics!$F$7,Unit_Economics!$O$7) -> 10 | L18: =Volume!L26*IF(Volume!L11=1,Unit_Economics!$F$7,Unit_Economics!$O$7) -> 10 | ... S18: =Volume!S26*IF(Volume!S11=1,Unit_Economics!$F$7,Unit_Economics!$O$7) -> 15
A19: B2C events | B19: Rp m | C19: =SUM(E19:G19) -> 2.73 | D19: =SUM(H19:S19) -> 10.92 | E19: =Volume!E27*IF(Volume!E11=1,Unit_Economics!$F$8,Unit_Economics!$O$8) -> 2.73 | F19: =Volume!F27*IF(Volume!F11=1,Unit_Economics!$F$8,Unit_Economics!$O$8) -> 0 | G19: =Volume!G27*IF(Volume!G11=1,Unit_Economics!$F$8,Unit_Economics!$O$8) -> 0 | H19: =Volume!H27*IF(Volume!H11=1,Unit_Economics!$F$8,Unit_Economics!$O$8) -> 0 | I19: =Volume!I27*IF(Volume!I11=1,Unit_Economics!$F$8,Unit_Economics!$O$8) -> 2.73 | J19: =Volume!J27*IF(Volume!J11=1,Unit_Economics!$F$8,Unit_Economics!$O$8) -> 0 | K19: =Volume!K27*IF(Volume!K11=1,Unit_Economics!$F$8,Unit_Economics!$O$8) -> 0 | L19: =Volume!L27*IF(Volume!L11=1,Unit_Economics!$F$8,Unit_Economics!$O$8) -> 0 | ... S19: =Volume!S27*IF(Volume!S11=1,Unit_Economics!$F$8,Unit_Economics!$O$8) -> 2.73
A20: B2C counseling | B20: Rp m | C20: =SUM(E20:G20) -> 3.8241711 | D20: =SUM(H20:S20) -> 103.55759 | E20: =E11*Inputs!$C$21 -> 0.93217929 | F20: =F11*Inputs!$C$21 -> 1.4227083 | G20: =G11*Inputs!$C$21 -> 1.4692835 | H20: =H11*Inputs!$C$21 -> 1.9863802 | I20: =I11*Inputs!$C$21 -> 4.1483364 | J20: =J11*Inputs!$C$21 -> 2.9382376 | K20: =K11*Inputs!$C$21 -> 6.2078744 | L20: =L11*Inputs!$C$21 -> 6.4503065 | ... S20: =S11*Inputs!$C$21 -> 12.631018
A21: Total delivery cost (incl. v16 lines, row 57) | B21: Rp m | C21: =SUM(E21:G21) -> 29.625671 | D21: =SUM(H21:S21) -> 980.84082 | E21: =SUM(E15:E20)+E57 -> 8.6621793 | F21: =SUM(F15:F20)+F57 -> 10.498458 | G21: =SUM(G15:G20)+G57 -> 10.465034 | H21: =SUM(H15:H20)+H57 -> 10.98213 | I21: =SUM(I15:I20)+I57 -> 38.071621 | J21: =SUM(J15:J20)+J57 -> 61.577273 | K21: =SUM(K15:K20)+K57 -> 45.592659 | L21: =SUM(L15:L20)+L57 -> 74.210092 | ... S21: =SUM(S15:S20)+S57 -> 121.59837
A23: Gross profit | B23: Rp m | C23: =SUM(E23:G23) -> 34.93134 | D23: =SUM(H23:S23) -> 1451.7137 | E23: =E12-E21 -> 11.766438 | F23: =F12-F21 -> 11.533647 | G23: =G12-G21 -> 11.631256 | H23: =H12-H21 -> 11.826759 | I23: =I12-I21 -> 33.758615 | J23: =J12-J21 -> 114.01285 | K23: =K12-K21 -> 64.574784 | L23: =L12-L21 -> 125.54144 | ... S23: =S12-S21 -> 181.67567
A24: Gross margin | B24: % | C24: =IF(C12=0,0,C23/C12) -> 0.54109289 | D24: =IF(D12=0,0,D23/D12) -> 0.59678569 | E24: =IF(E12=0,0,E23/E12) -> 0.57597818 | F24: =IF(F12=0,0,F23/F12) -> 0.52349272 | G24: =IF(G12=0,0,G23/G12) -> 0.52638955 | H24: =IF(H12=0,0,H23/H12) -> 0.51851535 | I24: =IF(I12=0,0,I23/I12) -> 0.46997778 | J24: =IF(J12=0,0,J23/J12) -> 0.64931244 | ... S24: =IF(S12=0,0,S23/S12) -> 0.59904787
A26: Fixed costs (from Capacity_OPEX)
A27: Base: team, software, office, accountant (+ pay plan and extra ads) | B27: Rp m | C27: =SUM(E27:G27) -> 60.63639 | D27: =SUM(H27:S27) -> 435.84578 | E27: =Capacity_OPEX!E22+Capacity_OPEX!E23+Capacity_OPEX!E24+Capacity_OPEX!E25+Capacity_OPEX!E37+Capacity_OPEX!E38 -> 19.685442 | F27: =Capacity_OPEX!F22+Capacity_OPEX!F23+Capacity_OPEX!F24+Capacity_OPEX!F25+Capacity_OPEX!F37+Capacity_OPEX!F38 -> 20.474586 | G27: =Capacity_OPEX!G22+Capacity_OPEX!G23+Capacity_OPEX!G24+Capacity_OPEX!G25+Capacity_OPEX!G37+Capacity_OPEX!G38 -> 20.476361 | H27: =Capacity_OPEX!H22+Capacity_OPEX!H23+Capacity_OPEX!H24+Capacity_OPEX!H25+Capacity_OPEX!H37+Capacity_OPEX!H38 -> 28.382367 | I27: =Capacity_OPEX!I22+Capacity_OPEX!I23+Capacity_OPEX!I24+Capacity_OPEX!I25+Capacity_OPEX!I37+Capacity_OPEX!I38 -> 28.785582 | J27: =Capacity_OPEX!J22+Capacity_OPEX!J23+Capacity_OPEX!J24+Capacity_OPEX!J25+Capacity_OPEX!J37+Capacity_OPEX!J38 -> 28.911306 | K27: =Capacity_OPEX!K22+Capacity_OPEX!K23+Capacity_OPEX!K24+Capacity_OPEX!K25+Capacity_OPEX!K37+Capacity_OPEX!K38 -> 29.300834 | L27: =Capacity_OPEX!L22+Capacity_OPEX!L23+Capacity_OPEX!L24+Capacity_OPEX!L25+Capacity_OPEX!L37+Capacity_OPEX!L38 -> 32.860432 | ... S27: =Capacity_OPEX!S22+Capacity_OPEX!S23+Capacity_OPEX!S24+Capacity_OPEX!S25+Capacity_OPEX!S37+Capacity_OPEX!S38 -> 46.132888
A28: Founder salaries | B28: Rp m | C28: =SUM(E28:G28) -> 30 | D28: =SUM(H28:S28) -> 270 | E28: =Capacity_OPEX!E26 -> 10 | F28: =Capacity_OPEX!F26 -> 10 | G28: =Capacity_OPEX!G26 -> 10 | H28: =Capacity_OPEX!H26 -> 10 | I28: =Capacity_OPEX!I26 -> 10 | J28: =Capacity_OPEX!J26 -> 25 | K28: =Capacity_OPEX!K26 -> 25 | L28: =Capacity_OPEX!L26 -> 25 | ... S28: =Capacity_OPEX!S26 -> 25
A29: B2B sales (co-founder, Account Manager, travel) | B29: Rp m | C29: =SUM(E29:G29) -> 6 | D29: =SUM(H29:S29) -> 72 | E29: =Capacity_OPEX!E27+Capacity_OPEX!E28+Capacity_OPEX!E39 -> 2 | F29: =Capacity_OPEX!F27+Capacity_OPEX!F28+Capacity_OPEX!F39 -> 2 | G29: =Capacity_OPEX!G27+Capacity_OPEX!G28+Capacity_OPEX!G39 -> 2 | H29: =Capacity_OPEX!H27+Capacity_OPEX!H28+Capacity_OPEX!H39 -> 2 | I29: =Capacity_OPEX!I27+Capacity_OPEX!I28+Capacity_OPEX!I39 -> 2 | J29: =Capacity_OPEX!J27+Capacity_OPEX!J28+Capacity_OPEX!J39 -> 2 | K29: =Capacity_OPEX!K27+Capacity_OPEX!K28+Capacity_OPEX!K39 -> 2 | L29: =Capacity_OPEX!L27+Capacity_OPEX!L28+Capacity_OPEX!L39 -> 2 | ... S29: =Capacity_OPEX!S27+Capacity_OPEX!S28+Capacity_OPEX!S39 -> 10
A30: Delivery capacity (PM, 2nd admin, certification) | B30: Rp m | C30: =SUM(E30:G30) -> 0 | D30: =SUM(H30:S30) -> 105.08 | E30: =Capacity_OPEX!E29+Capacity_OPEX!E30+Capacity_OPEX!E31 -> 0 | F30: =Capacity_OPEX!F29+Capacity_OPEX!F30+Capacity_OPEX!F31 -> 0 | G30: =Capacity_OPEX!G29+Capacity_OPEX!G30+Capacity_OPEX!G31 -> 0 | H30: =Capacity_OPEX!H29+Capacity_OPEX!H30+Capacity_OPEX!H31 -> 2.5 | I30: =Capacity_OPEX!I29+Capacity_OPEX!I30+Capacity_OPEX!I31 -> 2 | J30: =Capacity_OPEX!J29+Capacity_OPEX!J30+Capacity_OPEX!J31 -> 6.5 | K30: =Capacity_OPEX!K29+Capacity_OPEX!K30+Capacity_OPEX!K31 -> 2 | L30: =Capacity_OPEX!L29+Capacity_OPEX!L30+Capacity_OPEX!L31 -> 7.5 | ... S30: =Capacity_OPEX!S29+Capacity_OPEX!S30+Capacity_OPEX!S31 -> 16.18
A31: Total fixed cost | B31: Rp m | C31: =SUM(E31:G31) -> 96.63639 | D31: =SUM(H31:S31) -> 882.92578 | E31: =SUM(E27:E30) -> 31.685442 | F31: =SUM(F27:F30) -> 32.474586 | G31: =SUM(G27:G30) -> 32.476361 | H31: =SUM(H27:H30) -> 42.882367 | I31: =SUM(I27:I30) -> 42.785582 | J31: =SUM(J27:J30) -> 62.411306 | K31: =SUM(K27:K30) -> 58.300834 | L31: =SUM(L27:L30) -> 67.360432 | ... S31: =SUM(S27:S30) -> 97.312888
A33: Profit before tax | B33: Rp m | C33: =SUM(E33:G33) -> -61.70505 | D33: =SUM(H33:S33) -> 568.78797 | E33: =E23-E31 -> -19.919005 | F33: =F23-F31 -> -20.94094 | G33: =G23-G31 -> -20.845106 | H33: =H23-H31 -> -31.055607 | I33: =I23-I31 -> -9.026967 | J33: =J23-J31 -> 51.601546 | K33: =K23-K31 -> 6.2739499 | L33: =L23-L31 -> 58.181011 | ... S33: =S23-S31 -> 84.362784
A34: Income tax (final tax on revenue) | B34: Rp m | C34: =SUM(E34:G34) -> 0.32278505 | D34: =SUM(H34:S34) -> 12.162773 | E34: =E12*Inputs!$C$80 -> 0.10214308 | F34: =F12*Inputs!$C$80 -> 0.11016052 | G34: =G12*Inputs!$C$80 -> 0.11048145 | H34: =H12*Inputs!$C$80 -> 0.11404445 | I34: =I12*Inputs!$C$80 -> 0.35915118 | J34: =J12*Inputs!$C$80 -> 0.87795062 | K34: =K12*Inputs!$C$80 -> 0.55083722 | L34: =L12*Inputs!$C$80 -> 0.99875767 | ... S34: =S12*Inputs!$C$80 -> 1.5163702
A35: Net profit | B35: Rp m | C35: =SUM(E35:G35) -> -62.027835 | D35: =SUM(H35:S35) -> 556.6252 | E35: =E33-E34 -> -20.021148 | F35: =F33-F34 -> -21.0511 | G35: =G33-G34 -> -20.955587 | H35: =H33-H34 -> -31.169652 | I35: =I33-I34 -> -9.3861181 | J35: =J33-J34 -> 50.723595 | K35: =K33-K34 -> 5.7231127 | L35: =L33-L34 -> 57.182253 | ... S35: =S33-S34 -> 82.846414
A36: Net margin | B36: % | C36: =IF(C12=0,0,C35/C12) -> -0.9608226 | D36: =IF(D12=0,0,D35/D12) -> 0.22882331 | E36: =IF(E12=0,0,E35/E12) -> -0.98005399 | F36: =IF(F12=0,0,F35/F12) -> -0.95547387 | G36: =IF(G12=0,0,G35/G12) -> -0.94837586 | H36: =IF(H12=0,0,H35/H12) -> -1.3665572 | I36: =IF(I12=0,0,I35/I12) -> -0.13067085 | J36: =IF(J12=0,0,J35/J12) -> 0.28887499 | ... S36: =IF(S12=0,0,S35/S12) -> 0.27317344
A37: Net profit if founders were not paid (for comparison) | B37: Rp m | C37: =SUM(E37:G37) -> -32.027835 | D37: =SUM(H37:S37) -> 826.6252 | E37: =E35+E28 -> -10.021148 | F37: =F35+F28 -> -11.0511 | G37: =G35+G28 -> -10.955587 | H37: =H35+H28 -> -21.169652 | I37: =I35+I28 -> 0.61388186 | J37: =J35+J28 -> 75.723595 | K37: =K35+K28 -> 30.723113 | L37: =L35+L28 -> 82.182253 | ... S37: =S35+S28 -> 107.84641
A39: Concentration and memo lines
A40: Revenue from BI (Flagship + BI share of KPW; v16 adds BI EAP, KPw packages and their trainings) | B40: Rp m | C40: =SUM(E40:G40) -> 55.143 | D40: =SUM(H40:S40) -> 1354.703 | E40: =E6+E7*Inputs!$C$83+Inputs!$C$131*(IF(Volume!E26=0,0,E9*Volume!E18/Volume!E26*Inputs!$C$152)+E47+IF(Volume!E44+Volume!E45=0,0,E48*Volume!E44/(Volume!E44+Volume!E45))) -> 15 | F40: =F6+F7*Inputs!$C$83+Inputs!$C$131*(IF(Volume!F26=0,0,F9*Volume!F18/Volume!F26*Inputs!$C$152)+F47+IF(Volume!F44+Volume!F45=0,0,F48*Volume!F44/(Volume!F44+Volume!F45))) -> 20.0715 | G40: =G6+G7*Inputs!$C$83+Inputs!$C$131*(IF(Volume!G26=0,0,G9*Volume!G18/Volume!G26*Inputs!$C$152)+G47+IF(Volume!G44+Volume!G45=0,0,G48*Volume!G44/(Volume!G44+Volume!G45))) -> 20.0715 | H40: =H6+H7*Inputs!$C$83+Inputs!$C$131*(IF(Volume!H26=0,0,H9*Volume!H18/Volume!H26*Inputs!$C$152)+H47+IF(Volume!H44+Volume!H45=0,0,H48*Volume!H44/(Volume!H44+Volume!H45))) -> 20.0715 | I40: =I6+I7*Inputs!$C$83+Inputs!$C$131*(IF(Volume!I26=0,0,I9*Volume!I18/Volume!I26*Inputs!$C$152)+I47+IF(Volume!I44+Volume!I45=0,0,I48*Volume!I44/(Volume!I44+Volume!I45))) -> 22.9695 | J40: =J6+J7*Inputs!$C$83+Inputs!$C$131*(IF(Volume!J26=0,0,J9*Volume!J18/Volume!J26*Inputs!$C$152)+J47+IF(Volume!J44+Volume!J45=0,0,J48*Volume!J44/(Volume!J44+Volume!J45))) -> 152.266 | K40: =K6+K7*Inputs!$C$83+Inputs!$C$131*(IF(Volume!K26=0,0,K9*Volume!K18/Volume!K26*Inputs!$C$152)+K47+IF(Volume!K44+Volume!K45=0,0,K48*Volume!K44/(Volume!K44+Volume!K45))) -> 33.1125 | L40: =L6+L7*Inputs!$C$83+Inputs!$C$131*(IF(Volume!L26=0,0,L9*Volume!L18/Volume!L26*Inputs!$C$152)+L47+IF(Volume!L44+Volume!L45=0,0,L48*Volume!L44/(Volume!L44+Volume!L45))) -> 164.4625 | ... S40: =S6+S7*Inputs!$C$83+Inputs!$C$131*(IF(Volume!S26=0,0,S9*Volume!S18/Volume!S26*Inputs!$C$152)+S47+IF(Volume!S44+Volume!S45=0,0,S48*Volume!S44/(Volume!S44+Volume!S45))) -> 167.1585
A41: BI share of revenue | B41: % | C41: =IF(C12=0,0,C40/C12) -> 0.85417523 | D41: =IF(D12=0,0,D40/D12) -> 0.55690549 | E41: =IF(E12=0,0,E40/E12) -> 0.7342641 | F41: =IF(F12=0,0,F40/F12) -> 0.91101146 | G41: =IF(G12=0,0,G40/G12) -> 0.90836519 | H41: =IF(H12=0,0,H40/H12) -> 0.87998585 | I41: =IF(I12=0,0,I40/I12) -> 0.31977481 | J41: =IF(J12=0,0,J40/J12) -> 0.86716722 | ... S41: =IF(S12=0,0,S40/S12) -> 0.55117971
A42: B2B revenue (incl. EAP channel, LPS / OJK and schools) | B42: Rp m | C42: =SUM(E42:G42) -> 55.143 | D42: =SUM(H42:S42) -> 2273.268 | E42: =SUM(E6:E9)+E51 -> 15 | F42: =SUM(F6:F9)+F51 -> 20.0715 | G42: =SUM(G6:G9)+G51 -> 20.0715 | H42: =SUM(H6:H9)+H51 -> 20.0715 | I42: =SUM(I6:I9)+I51 -> 61.9695 | J42: =SUM(J6:J9)+J51 -> 171.541 | K42: =SUM(K6:K9)+K51 -> 101.6125 | L42: =SUM(L6:L9)+L51 -> 190.8625 | ... S42: =SUM(S6:S9)+S51 -> 281.7235
A43: Memo: Coreitera assessment revenue (paid by TJ) | B43: Rp m | C43: =SUM(E43:G43) -> 3.75 | D43: =SUM(H43:S43) -> 89.25 | E43: =(Volume!E23*Inputs!$C$63+Volume!E24*Inputs!$C$64+Volume!E25*Inputs!$C$65+Volume!E27*Inputs!$C$66)*Inputs!$C$62 -> 3.75 | F43: =(Volume!F23*Inputs!$C$63+Volume!F24*Inputs!$C$64+Volume!F25*Inputs!$C$65+Volume!F27*Inputs!$C$66)*Inputs!$C$62 -> 0 | G43: =(Volume!G23*Inputs!$C$63+Volume!G24*Inputs!$C$64+Volume!G25*Inputs!$C$65+Volume!G27*Inputs!$C$66)*Inputs!$C$62 -> 0 | H43: =(Volume!H23*Inputs!$C$63+Volume!H24*Inputs!$C$64+Volume!H25*Inputs!$C$65+Volume!H27*Inputs!$C$66)*Inputs!$C$62 -> 0 | I43: =(Volume!I23*Inputs!$C$63+Volume!I24*Inputs!$C$64+Volume!I25*Inputs!$C$65+Volume!I27*Inputs!$C$66)*Inputs!$C$62 -> 3.75 | J43: =(Volume!J23*Inputs!$C$63+Volume!J24*Inputs!$C$64+Volume!J25*Inputs!$C$65+Volume!J27*Inputs!$C$66)*Inputs!$C$62 -> 5.25 | K43: =(Volume!K23*Inputs!$C$63+Volume!K24*Inputs!$C$64+Volume!K25*Inputs!$C$65+Volume!K27*Inputs!$C$66)*Inputs!$C$62 -> 3 | L43: =(Volume!L23*Inputs!$C$63+Volume!L24*Inputs!$C$64+Volume!L25*Inputs!$C$65+Volume!L27*Inputs!$C$66)*Inputs!$C$62 -> 5.25 | ... S43: =(Volume!S23*Inputs!$C$63+Volume!S24*Inputs!$C$64+Volume!S25*Inputs!$C$65+Volume!S27*Inputs!$C$66)*Inputs!$C$62 -> 18
A44: Memo: Theta counseling revenue (paid by TJ) | B44: Rp m | C44: =SUM(E44:G44) -> 2.8136478 | D44: =SUM(H44:S44) -> 44.772326 | E44: =(Volume!E28+Volume!E26*Inputs!$C$68+Volume!E43)*Inputs!$C$67 -> 0.60448713 | F44: =(Volume!F28+Volume!F26*Inputs!$C$68+Volume!F43)*Inputs!$C$67 -> 1.1019701 | G44: =(Volume!G28+Volume!G26*Inputs!$C$68+Volume!G43)*Inputs!$C$67 -> 1.1071906 | H44: =(Volume!H28+Volume!H26*Inputs!$C$68+Volume!H43)*Inputs!$C$67 -> 1.1651515 | I44: =(Volume!I28+Volume!I26*Inputs!$C$68+Volume!I43)*Inputs!$C$67 -> 2.1641332 | J44: =(Volume!J28+Volume!J26*Inputs!$C$68+Volume!J43)*Inputs!$C$67 -> 2.4709944 | K44: =(Volume!K28+Volume!K26*Inputs!$C$68+Volume!K43)*Inputs!$C$67 -> 3.279985 | L44: =(Volume!L28+Volume!L26*Inputs!$C$68+Volume!L43)*Inputs!$C$67 -> 3.307159 | ... S44: =(Volume!S28+Volume!S26*Inputs!$C$68+Volume!S43)*Inputs!$C$67 -> 5.0132493
A46: v16 new lines: EAP channel, LPS / OJK, schools
A47: Revenue: BI KPw EAP packages (spread over 3 months) | B47: Rp m | C47: =SUM(E47:G47) -> 10.143 | D47: =SUM(H47:S47) -> 213.003 | E47: =(Volume!E50+0+0)/3 -> 0 | F47: =(Volume!F50+Volume!E50+0)/3 -> 5.0715 | G47: =(Volume!G50+Volume!F50+Volume!E50)/3 -> 5.0715 | H47: =(Volume!H50+Volume!G50+Volume!F50)/3 -> 5.0715 | I47: =(Volume!I50+Volume!H50+Volume!G50)/3 -> 7.9695 | J47: =(Volume!J50+Volume!I50+Volume!H50)/3 -> 13.041 | K47: =(Volume!K50+Volume!J50+Volume!I50)/3 -> 18.1125 | L47: =(Volume!L50+Volume!K50+Volume!J50)/3 -> 18.1125 | M47: =(Volume!M50+Volume!L50+Volume!K50)/3 -> 15.939 | N47: =(Volume!N50+Volume!M50+Volume!L50)/3 -> 18.837 | ... S47: =(Volume!S50+Volume!R50+Volume!Q50)/3 -> 23.9085
A48: Revenue: trainings sold to EAP clients | B48: Rp m | C48: =SUM(E48:G48) -> 0 | D48: =SUM(H48:S48) -> 64.125 | E48: =(Volume!E44+Volume!E45)*IF(Volume!E11=1,Unit_Economics!$B$5,Unit_Economics!$N$5) -> 0 | F48: =(Volume!F44+Volume!F45)*IF(Volume!F11=1,Unit_Economics!$B$5,Unit_Economics!$N$5) -> 0 | G48: =(Volume!G44+Volume!G45)*IF(Volume!G11=1,Unit_Economics!$B$5,Unit_Economics!$N$5) -> 0 | H48: =(Volume!H44+Volume!H45)*IF(Volume!H11=1,Unit_Economics!$B$5,Unit_Economics!$N$5) -> 0 | I48: =(Volume!I44+Volume!I45)*IF(Volume!I11=1,Unit_Economics!$B$5,Unit_Economics!$N$5) -> 0 | J48: =(Volume!J44+Volume!J45)*IF(Volume!J11=1,Unit_Economics!$B$5,Unit_Economics!$N$5) -> 0 | K48: =(Volume!K44+Volume!K45)*IF(Volume!K11=1,Unit_Economics!$B$5,Unit_Economics!$N$5) -> 0 | L48: =(Volume!L44+Volume!L45)*IF(Volume!L11=1,Unit_Economics!$B$5,Unit_Economics!$N$5) -> 14.25 | ... S48: =(Volume!S44+Volume!S45)*IF(Volume!S11=1,Unit_Economics!$B$5,Unit_Economics!$N$5) -> 7.125
A49: Revenue: LPS / OJK programs | B49: Rp m | C49: =SUM(E49:G49) -> 0 | D49: =SUM(H49:S49) -> 58.14 | E49: =Volume!E46*IF(Volume!E11=1,Unit_Economics!$B$5,Unit_Economics!$N$5) -> 0 | F49: =Volume!F46*IF(Volume!F11=1,Unit_Economics!$B$5,Unit_Economics!$N$5) -> 0 | G49: =Volume!G46*IF(Volume!G11=1,Unit_Economics!$B$5,Unit_Economics!$N$5) -> 0 | H49: =Volume!H46*IF(Volume!H11=1,Unit_Economics!$B$5,Unit_Economics!$N$5) -> 0 | I49: =Volume!I46*IF(Volume!I11=1,Unit_Economics!$B$5,Unit_Economics!$N$5) -> 0 | J49: =Volume!J46*IF(Volume!J11=1,Unit_Economics!$B$5,Unit_Economics!$N$5) -> 0 | K49: =Volume!K46*IF(Volume!K11=1,Unit_Economics!$B$5,Unit_Economics!$N$5) -> 0 | L49: =Volume!L46*IF(Volume!L11=1,Unit_Economics!$B$5,Unit_Economics!$N$5) -> 0 | ... S49: =Volume!S46*IF(Volume!S11=1,Unit_Economics!$B$5,Unit_Economics!$N$5) -> 9.69
A50: Revenue: school tests | B50: Rp m | C50: =SUM(E50:G50) -> 0 | D50: =SUM(H50:S50) -> 144 | E50: =Volume!E48*Inputs!$C$155 -> 0 | F50: =Volume!F48*Inputs!$C$155 -> 0 | G50: =Volume!G48*Inputs!$C$155 -> 0 | H50: =Volume!H48*Inputs!$C$155 -> 0 | I50: =Volume!I48*Inputs!$C$155 -> 24 | J50: =Volume!J48*Inputs!$C$155 -> 0 | K50: =Volume!K48*Inputs!$C$155 -> 0 | L50: =Volume!L48*Inputs!$C$155 -> 0 | ... S50: =Volume!S48*Inputs!$C$155 -> 0
A51: Total v16 revenue (in row 12) | B51: Rp m | C51: =SUM(E51:G51) -> 10.143 | D51: =SUM(H51:S51) -> 479.268 | E51: =SUM(E47:E50) -> 0 | F51: =SUM(F47:F50) -> 5.0715 | G51: =SUM(G47:G50) -> 5.0715 | H51: =SUM(H47:H50) -> 5.0715 | I51: =SUM(I47:I50) -> 31.9695 | J51: =SUM(J47:J50) -> 13.041 | K51: =SUM(K47:K50) -> 18.1125 | L51: =SUM(L47:L50) -> 32.3625 | ... S51: =SUM(S47:S50) -> 40.7235
A53: Delivery cost: BI KPw EAP packages | B53: Rp m | C53: =SUM(E53:G53) -> 8.0715 | D53: =SUM(H53:S53) -> 169.34073 | E53: =Volume!E42*Inputs!$C$143/3+Volume!E39*Inputs!$C$145*Inputs!$C$147 -> 0 | F53: =Volume!F42*Inputs!$C$143/3+Volume!F39*Inputs!$C$145*Inputs!$C$147 -> 4.07575 | G53: =Volume!G42*Inputs!$C$143/3+Volume!G39*Inputs!$C$145*Inputs!$C$147 -> 3.99575 | H53: =Volume!H42*Inputs!$C$143/3+Volume!H39*Inputs!$C$145*Inputs!$C$147 -> 3.99575 | I53: =Volume!I42*Inputs!$C$143/3+Volume!I39*Inputs!$C$145*Inputs!$C$147 -> 6.393285 | J53: =Volume!J42*Inputs!$C$143/3+Volume!J39*Inputs!$C$145*Inputs!$C$147 -> 10.389035 | K53: =Volume!K42*Inputs!$C$143/3+Volume!K39*Inputs!$C$145*Inputs!$C$147 -> 14.384785 | L53: =Volume!L42*Inputs!$C$143/3+Volume!L39*Inputs!$C$145*Inputs!$C$147 -> 14.384785 | ... S53: =Volume!S42*Inputs!$C$143/3+Volume!S39*Inputs!$C$145*Inputs!$C$147 -> 18.939855
A54: Delivery cost: trainings sold to EAP clients | B54: Rp m | C54: =SUM(E54:G54) -> 0 | D54: =SUM(H54:S54) -> 23.0625 | E54: =(Volume!E44+Volume!E45)*IF(Volume!E11=1,Unit_Economics!$F$5,Unit_Economics!$O$5) -> 0 | F54: =(Volume!F44+Volume!F45)*IF(Volume!F11=1,Unit_Economics!$F$5,Unit_Economics!$O$5) -> 0 | G54: =(Volume!G44+Volume!G45)*IF(Volume!G11=1,Unit_Economics!$F$5,Unit_Economics!$O$5) -> 0 | H54: =(Volume!H44+Volume!H45)*IF(Volume!H11=1,Unit_Economics!$F$5,Unit_Economics!$O$5) -> 0 | I54: =(Volume!I44+Volume!I45)*IF(Volume!I11=1,Unit_Economics!$F$5,Unit_Economics!$O$5) -> 0 | J54: =(Volume!J44+Volume!J45)*IF(Volume!J11=1,Unit_Economics!$F$5,Unit_Economics!$O$5) -> 0 | K54: =(Volume!K44+Volume!K45)*IF(Volume!K11=1,Unit_Economics!$F$5,Unit_Economics!$O$5) -> 0 | L54: =(Volume!L44+Volume!L45)*IF(Volume!L11=1,Unit_Economics!$F$5,Unit_Economics!$O$5) -> 5.125 | ... S54: =(Volume!S44+Volume!S45)*IF(Volume!S11=1,Unit_Economics!$F$5,Unit_Economics!$O$5) -> 2.5625
A55: Delivery cost: LPS / OJK programs | B55: Rp m | C55: =SUM(E55:G55) -> 0 | D55: =SUM(H55:S55) -> 20.91 | E55: =Volume!E46*IF(Volume!E11=1,Unit_Economics!$F$5,Unit_Economics!$O$5) -> 0 | F55: =Volume!F46*IF(Volume!F11=1,Unit_Economics!$F$5,Unit_Economics!$O$5) -> 0 | G55: =Volume!G46*IF(Volume!G11=1,Unit_Economics!$F$5,Unit_Economics!$O$5) -> 0 | H55: =Volume!H46*IF(Volume!H11=1,Unit_Economics!$F$5,Unit_Economics!$O$5) -> 0 | I55: =Volume!I46*IF(Volume!I11=1,Unit_Economics!$F$5,Unit_Economics!$O$5) -> 0 | J55: =Volume!J46*IF(Volume!J11=1,Unit_Economics!$F$5,Unit_Economics!$O$5) -> 0 | K55: =Volume!K46*IF(Volume!K11=1,Unit_Economics!$F$5,Unit_Economics!$O$5) -> 0 | L55: =Volume!L46*IF(Volume!L11=1,Unit_Economics!$F$5,Unit_Economics!$O$5) -> 0 | ... S55: =Volume!S46*IF(Volume!S11=1,Unit_Economics!$F$5,Unit_Economics!$O$5) -> 3.485
A56: Delivery cost: school tests (tool + assessor share) | B56: Rp m | C56: =SUM(E56:G56) -> 0 | D56: =SUM(H56:S56) -> 88.8 | E56: =Volume!E48*(Inputs!$C$156+Inputs!$C$157*(Inputs!$C$155-Inputs!$C$156)) -> 0 | F56: =Volume!F48*(Inputs!$C$156+Inputs!$C$157*(Inputs!$C$155-Inputs!$C$156)) -> 0 | G56: =Volume!G48*(Inputs!$C$156+Inputs!$C$157*(Inputs!$C$155-Inputs!$C$156)) -> 0 | H56: =Volume!H48*(Inputs!$C$156+Inputs!$C$157*(Inputs!$C$155-Inputs!$C$156)) -> 0 | I56: =Volume!I48*(Inputs!$C$156+Inputs!$C$157*(Inputs!$C$155-Inputs!$C$156)) -> 14.8 | J56: =Volume!J48*(Inputs!$C$156+Inputs!$C$157*(Inputs!$C$155-Inputs!$C$156)) -> 0 | K56: =Volume!K48*(Inputs!$C$156+Inputs!$C$157*(Inputs!$C$155-Inputs!$C$156)) -> 0 | L56: =Volume!L48*(Inputs!$C$156+Inputs!$C$157*(Inputs!$C$155-Inputs!$C$156)) -> 0 | ... S56: =Volume!S48*(Inputs!$C$156+Inputs!$C$157*(Inputs!$C$155-Inputs!$C$156)) -> 0
A57: Total v16 delivery cost (in row 21) | B57: Rp m | C57: =SUM(E57:G57) -> 8.0715 | D57: =SUM(H57:S57) -> 302.11323 | E57: =SUM(E53:E56) -> 0 | F57: =SUM(F53:F56) -> 4.07575 | G57: =SUM(G53:G56) -> 3.99575 | H57: =SUM(H53:H56) -> 3.99575 | I57: =SUM(I53:I56) -> 21.193285 | J57: =SUM(J53:J56) -> 10.389035 | K57: =SUM(K53:K56) -> 14.384785 | L57: =SUM(L53:L56) -> 19.509785 | ... S57: =SUM(S53:S56) -> 24.987355

Sheet CashFlow
A1: Pillar 3 - Cash flow by month (Rp million) - money counted when it moves
A2: Rp million unless stated. Q4 2026 and FY 2027 columns are totals (or averages / peaks where stated).
A4: Line | B4: Unit | C4: Q4 2026 | D4: FY 2027 | E4: Oct-26 | F4: Nov-26 | G4: Dec-26 | H4: Jan-27 | I4: Feb-27 | J4: Mar-27 | K4: Apr-27 | L4: May-27 | M4: Jun-27 | N4: Jul-27 | O4: Aug-27 | P4: Sep-27 | Q4: Oct-27 | R4: Nov-27 | S4: Dec-27
A5: Cash in
A6: B2C (paid on the day) | B6: Rp m | C6: =SUM(E6:G6) -> 9.414011 | D6: =SUM(H6:S6) -> 159.28657 | E6: =PnL!E10+PnL!E11 -> 5.428617 | F6: =PnL!F10+PnL!F11 -> 1.9606048 | G6: =PnL!G10+PnL!G11 -> 2.0247892 | H6: =PnL!H10+PnL!H11 -> 2.7373895 | I6: =PnL!I10+PnL!I11 -> 9.8607365 | J6: =PnL!J10+PnL!J11 -> 4.0491244 | K6: =PnL!K10+PnL!K11 -> 8.5549431 | L6: =PnL!L10+PnL!L11 -> 8.8890339 | ... S6: =PnL!S10+PnL!S11 -> 21.550545
A7: BI central - Flagship (incl. optional down payment) | B7: Rp m | C7: =SUM(E7:G7) -> 0 | D7: =SUM(H7:S7) -> 490 | E7: =PnL!E6*(Inputs!$C$73-Inputs!$C$117)+PnL!F6*Inputs!$C$117 -> 0 | F7: =PnL!F6*(Inputs!$C$73-Inputs!$C$117)+PnL!G6*Inputs!$C$117+PnL!E6*Inputs!$C$74 -> 0 | G7: =PnL!G6*(Inputs!$C$73-Inputs!$C$117)+PnL!H6*Inputs!$C$117+PnL!F6*Inputs!$C$74+PnL!E6*Inputs!$C$75 -> 0 | H7: =PnL!H6*(Inputs!$C$73-Inputs!$C$117)+PnL!I6*Inputs!$C$117+PnL!G6*Inputs!$C$74+PnL!F6*Inputs!$C$75 -> 0 | I7: =PnL!I6*(Inputs!$C$73-Inputs!$C$117)+PnL!J6*Inputs!$C$117+PnL!H6*Inputs!$C$74+PnL!G6*Inputs!$C$75 -> 0 | J7: =PnL!J6*(Inputs!$C$73-Inputs!$C$117)+PnL!K6*Inputs!$C$117+PnL!I6*Inputs!$C$74+PnL!H6*Inputs!$C$75 -> 60 | K7: =PnL!K6*(Inputs!$C$73-Inputs!$C$117)+PnL!L6*Inputs!$C$117+PnL!J6*Inputs!$C$74+PnL!I6*Inputs!$C$75 -> 30 | L7: =PnL!L6*(Inputs!$C$73-Inputs!$C$117)+PnL!M6*Inputs!$C$117+PnL!K6*Inputs!$C$74+PnL!J6*Inputs!$C$75 -> 70 | M7: =PnL!M6*(Inputs!$C$73-Inputs!$C$117)+PnL!N6*Inputs!$C$117+PnL!L6*Inputs!$C$74+PnL!K6*Inputs!$C$75 -> 30 | N7: =PnL!N6*(Inputs!$C$73-Inputs!$C$117)+PnL!O6*Inputs!$C$117+PnL!M6*Inputs!$C$74+PnL!L6*Inputs!$C$75 -> 70 | ... S7: =PnL!S6*(Inputs!$C$73-Inputs!$C$117)+PnL!T6*Inputs!$C$117+PnL!R6*Inputs!$C$74+PnL!Q6*Inputs!$C$75 -> 30
A8: BI KPW / LPS (payday cutoff rule) | B8: Rp m | C8: =SUM(E8:G8) -> 0 | D8: =SUM(H8:S8) -> 456 | E8: =PnL!E7*Inputs!$C$76 -> 0 | F8: =PnL!F7*Inputs!$C$76+PnL!E7*(1-Inputs!$C$76) -> 0 | G8: =PnL!G7*Inputs!$C$76+PnL!F7*(1-Inputs!$C$76) -> 0 | H8: =PnL!H7*Inputs!$C$76+PnL!G7*(1-Inputs!$C$76) -> 0 | I8: =PnL!I7*Inputs!$C$76+PnL!H7*(1-Inputs!$C$76) -> 0 | J8: =PnL!J7*Inputs!$C$76+PnL!I7*(1-Inputs!$C$76) -> 22.8 | K8: =PnL!K7*Inputs!$C$76+PnL!J7*(1-Inputs!$C$76) -> 5.7 | L8: =PnL!L7*Inputs!$C$76+PnL!K7*(1-Inputs!$C$76) -> 22.8 | M8: =PnL!M7*Inputs!$C$76+PnL!L7*(1-Inputs!$C$76) -> 28.5 | ... S8: =PnL!S7*Inputs!$C$76+PnL!R7*(1-Inputs!$C$76) -> 131.1
A9: Banks - KCP events | B9: Rp m | C9: =SUM(E9:G9) -> 0 | D9: =SUM(H9:S9) -> 299.6 | E9: =PnL!E8*Inputs!$C$77 -> 0 | F9: =PnL!F8*Inputs!$C$77+PnL!E8*Inputs!$C$78 -> 0 | G9: =PnL!G8*Inputs!$C$77+PnL!F8*Inputs!$C$78+PnL!E8*Inputs!$C$79 -> 0 | H9: =PnL!H8*Inputs!$C$77+PnL!G8*Inputs!$C$78+PnL!F8*Inputs!$C$79 -> 0 | I9: =PnL!I8*Inputs!$C$77+PnL!H8*Inputs!$C$78+PnL!G8*Inputs!$C$79 -> 0 | J9: =PnL!J8*Inputs!$C$77+PnL!I8*Inputs!$C$78+PnL!H8*Inputs!$C$79 -> 0 | K9: =PnL!K8*Inputs!$C$77+PnL!J8*Inputs!$C$78+PnL!I8*Inputs!$C$79 -> 10.7 | L9: =PnL!L8*Inputs!$C$77+PnL!K8*Inputs!$C$78+PnL!J8*Inputs!$C$79 -> 26.75 | M9: =PnL!M8*Inputs!$C$77+PnL!L8*Inputs!$C$78+PnL!K8*Inputs!$C$79 -> 16.05 | N9: =PnL!N8*Inputs!$C$77+PnL!M8*Inputs!$C$78+PnL!L8*Inputs!$C$79 -> 10.7 | ... S9: =PnL!S8*Inputs!$C$77+PnL!R8*Inputs!$C$78+PnL!Q8*Inputs!$C$79 -> 96.3
A10: Banks - EAP (paid the next month) | B10: Rp m | C10: =SUM(E10:G10) -> 30 | D10: =SUM(H10:S10) -> 405 | E10: =PnL!E9*0 -> 0 | F10: =PnL!F9*0+PnL!E9*1 -> 15 | G10: =PnL!G9*0+PnL!F9*1 -> 15 | H10: =PnL!H9*0+PnL!G9*1 -> 15 | I10: =PnL!I9*0+PnL!H9*1 -> 15 | J10: =PnL!J9*0+PnL!I9*1 -> 30 | K10: =PnL!K9*0+PnL!J9*1 -> 30 | L10: =PnL!L9*0+PnL!K9*1 -> 30 | M10: =PnL!M9*0+PnL!L9*1 -> 30 | ... S10: =PnL!S9*0+PnL!R9*1 -> 45
A11: Total cash in | B11: Rp m | C11: =SUM(E11:G11) -> 47.021261 | D11: =SUM(H11:S11) -> 2285.7916 | E11: =SUM(E6:E10)+E35 -> 5.428617 | F11: =SUM(F6:F10)+F35 -> 24.567855 | G11: =SUM(G6:G10)+G35 -> 17.024789 | H11: =SUM(H6:H10)+H35 -> 25.344639 | I11: =SUM(I6:I10)+I35 -> 48.814986 | J11: =SUM(J6:J10)+J35 -> 136.45637 | K11: =SUM(K6:K10)+K35 -> 104.51644 | L11: =SUM(L6:L10)+L35 -> 189.40053 | ... S11: =SUM(S6:S10)+S35 -> 376.67404
A13: Cash out
A14: Delivery costs (paid in the event month) | B14: Rp m | C14: =SUM(E14:G14) -> 29.625671 | D14: =SUM(H14:S14) -> 980.84082 | E14: =PnL!E21 -> 8.6621793 | F14: =PnL!F21 -> 10.498458 | G14: =PnL!G21 -> 10.465034 | H14: =PnL!H21 -> 10.98213 | I14: =PnL!I21 -> 38.071621 | J14: =PnL!J21 -> 61.577273 | K14: =PnL!K21 -> 45.592659 | L14: =PnL!L21 -> 74.210092 | ... S14: =PnL!S21 -> 121.59837
A15: Fixed costs (salaries paid on the 25th) | B15: Rp m | C15: =SUM(E15:G15) -> 96.63639 | D15: =SUM(H15:S15) -> 882.92578 | E15: =PnL!E31 -> 31.685442 | F15: =PnL!F31 -> 32.474586 | G15: =PnL!G31 -> 32.476361 | H15: =PnL!H31 -> 42.882367 | I15: =PnL!I31 -> 42.785582 | J15: =PnL!J31 -> 62.411306 | K15: =PnL!K31 -> 58.300834 | L15: =PnL!L31 -> 67.360432 | ... S15: =PnL!S31 -> 97.312888
A16: Income tax (paid the next month) | B16: Rp m | C16: =SUM(E16:G16) -> 0.21230361 | D16: =SUM(H16:S16) -> 10.756884 | E16: =0 -> 0 | F16: =PnL!E34 -> 0.10214308 | G16: =PnL!F34 -> 0.11016052 | H16: =PnL!G34 -> 0.11048145 | I16: =PnL!H34 -> 0.11404445 | J16: =PnL!I34 -> 0.35915118 | K16: =PnL!J34 -> 0.87795062 | L16: =PnL!K34 -> 0.55083722 | M16: =PnL!L34 -> 0.99875767 | ... S16: =PnL!R34 -> 2.1395852
A17: Total cash out | B17: Rp m | C17: =SUM(E17:G17) -> 126.47436 | D17: =SUM(H17:S17) -> 1874.5235 | E17: =SUM(E14:E16) -> 40.347622 | F17: =SUM(F14:F16) -> 43.075188 | G17: =SUM(G14:G16) -> 43.051556 | H17: =SUM(H14:H16) -> 53.974978 | I17: =SUM(I14:I16) -> 80.971248 | J17: =SUM(J14:J16) -> 124.34773 | K17: =SUM(K14:K16) -> 104.77144 | L17: =SUM(L14:L16) -> 142.12136 | ... S17: =SUM(S14:S16) -> 221.05085
A19: Net cash flow | B19: Rp m | C19: =SUM(E19:G19) -> -79.453104 | D19: =SUM(H19:S19) -> 411.26809 | E19: =E11-E17 -> -34.919005 | F19: =F11-F17 -> -18.507333 | G19: =G11-G17 -> -26.026766 | H19: =H11-H17 -> -28.630339 | I19: =I11-I17 -> -32.156261 | J19: =J11-J17 -> 12.108645 | K19: =K11-K17 -> -0.25500068 | L19: =L11-L17 -> 47.279173 | ... S19: =S11-S17 -> 155.6232
A20: Cash at start of month | B20: Rp m | C20: =E20 -> 210 | D20: =H20 -> 130.5469 | E20: =Inputs!$C$72 -> 210 | F20: =E21 -> 175.081 | G20: =F21 -> 156.57366 | H20: =G21 -> 130.5469 | I20: =H21 -> 101.91656 | J20: =I21 -> 69.760296 | K20: =J21 -> 81.868941 | L20: =K21 -> 81.61394 | M20: =L21 -> 128.89311 | ... S20: =R21 -> 386.19178
A21: Cash at end of month | B21: Rp m | C21: =G21 -> 130.5469 | D21: =S21 -> 541.81498 | E21: =E20+E19 -> 175.081 | F21: =F20+F19 -> 156.57366 | G21: =G20+G19 -> 130.5469 | H21: =H20+H19 -> 101.91656 | I21: =I20+I19 -> 69.760296 | J21: =J20+J19 -> 81.868941 | K21: =K20+K19 -> 81.61394 | L21: =L20+L19 -> 128.89311 | ... S21: =S20+S19 -> 541.81498
A23: Safety checks
A24: Cash floor: one month of fixed cost + this month's delivery cost | B24: Rp m | C24: =MAX(E24:G24) -> 42.973045 | D24: =MAX(H24:S24) -> 261.36389 | E24: =E15+E14 -> 40.347622 | F24: =F15+F14 -> 42.973045 | G24: =G15+G14 -> 42.941395 | H24: =H15+H14 -> 53.864497 | I24: =I15+I14 -> 80.857203 | J24: =J15+J14 -> 123.98858 | K24: =K15+K14 -> 103.89349 | L24: =L15+L14 -> 141.57052 | ... S24: =S15+S14 -> 218.91126
A25: Above the floor? (1 = yes, 0 = warning) | B25: flag | C25: =MIN(E25:G25) -> 1 | D25: =MIN(H25:S25) -> 0 | E25: =IF(E21>=E24,1,0) -> 1 | F25: =IF(F21>=F24,1,0) -> 1 | G25: =IF(G21>=G24,1,0) -> 1 | H25: =IF(H21>=H24,1,0) -> 1 | I25: =IF(I21>=I24,1,0) -> 0 | J25: =IF(J21>=J24,1,0) -> 0 | K25: =IF(K21>=K24,1,0) -> 0 | L25: =IF(L21>=L24,1,0) -> 0 | ... S25: =IF(S21>=S24,1,0) -> 1
A26: Money clients still owe you (end of month) | B26: Rp m | C26: =MAX(E26:G26) -> 17.53575 | D26: =MAX(H26:S26) -> 237.69875 | E26: =SUM(PnL!$E$12:E12)-SUM($E$11:E11) -> 15 | F26: =SUM(PnL!$E$12:F12)-SUM($E$11:F11) -> 12.46425 | G26: =SUM(PnL!$E$12:G12)-SUM($E$11:G11) -> 17.53575 | H26: =SUM(PnL!$E$12:H12)-SUM($E$11:H11) -> 15 | I26: =SUM(PnL!$E$12:I12)-SUM($E$11:I11) -> 38.01525 | J26: =SUM(PnL!$E$12:J12)-SUM($E$11:J11) -> 77.149 | K26: =SUM(PnL!$E$12:K12)-SUM($E$11:K11) -> 82.8 | L26: =SUM(PnL!$E$12:L12)-SUM($E$11:L11) -> 93.151 | ... S26: =SUM(PnL!$E$12:S12)-SUM($E$11:S11) -> 164.29875
A27: Months of runway if all B2B stopped from here (2027 avg B2C profit) | B27: months | C27: =MIN(E27:G27) -> 4.5419813 | D27: =MIN(H27:S27) -> 1.3952422 | E27: =IF(E15-((PnL!$D$10+PnL!$D$11-PnL!$D$19-PnL!$D$20)/12)<=0,99,E21/(E15-((PnL!$D$10+PnL!$D$11-PnL!$D$19-PnL!$D$20)/12))) -> 6.2637736 | F27: =IF(F15-((PnL!$D$10+PnL!$D$11-PnL!$D$19-PnL!$D$20)/12)<=0,99,F21/(F15-((PnL!$D$10+PnL!$D$11-PnL!$D$19-PnL!$D$20)/12))) -> 5.4478397 | G27: =IF(G15-((PnL!$D$10+PnL!$D$11-PnL!$D$19-PnL!$D$20)/12)<=0,99,G21/(G15-((PnL!$D$10+PnL!$D$11-PnL!$D$19-PnL!$D$20)/12))) -> 4.5419813 | H27: =IF(H15-((PnL!$D$10+PnL!$D$11-PnL!$D$19-PnL!$D$20)/12)<=0,99,H21/(H15-((PnL!$D$10+PnL!$D$11-PnL!$D$19-PnL!$D$20)/12))) -> 2.6033467 | I27: =IF(I15-((PnL!$D$10+PnL!$D$11-PnL!$D$19-PnL!$D$20)/12)<=0,99,I21/(I15-((PnL!$D$10+PnL!$D$11-PnL!$D$19-PnL!$D$20)/12))) -> 1.7863666 | J27: =IF(J15-((PnL!$D$10+PnL!$D$11-PnL!$D$19-PnL!$D$20)/12)<=0,99,J21/(J15-((PnL!$D$10+PnL!$D$11-PnL!$D$19-PnL!$D$20)/12))) -> 1.3952422 | K27: =IF(K15-((PnL!$D$10+PnL!$D$11-PnL!$D$19-PnL!$D$20)/12)<=0,99,K21/(K15-((PnL!$D$10+PnL!$D$11-PnL!$D$19-PnL!$D$20)/12))) -> 1.4956716 | L27: =IF(L15-((PnL!$D$10+PnL!$D$11-PnL!$D$19-PnL!$D$20)/12)<=0,99,L21/(L15-((PnL!$D$10+PnL!$D$11-PnL!$D$19-PnL!$D$20)/12))) -> 2.025782 | ... S27: =IF(S15-((PnL!$D$10+PnL!$D$11-PnL!$D$19-PnL!$D$20)/12)<=0,99,S21/(S15-((PnL!$D$10+PnL!$D$11-PnL!$D$19-PnL!$D$20)/12))) -> 5.7899326
A29: Note: this is a monthly model. Because BI pays on the 1st and salaries go out on the 25th, keep cash above the floor line at all times. Prices are assumed to exclude VAT (VAT passes through).
A31: v16 cash in
A32: BI KPw packages: 50% at signing, 50% two months later | B32: Rp m | C32: =SUM(E32:G32) -> 7.60725 | D32: =SUM(H32:S32) -> 213.003 | E32: =0.5*Volume!E50+0.5*0 -> 0 | F32: =0.5*Volume!F50+0.5*0 -> 7.60725 | G32: =0.5*Volume!G50+0.5*Volume!E50 -> 0 | H32: =0.5*Volume!H50+0.5*Volume!F50 -> 7.60725 | I32: =0.5*Volume!I50+0.5*Volume!G50 -> 11.95425 | J32: =0.5*Volume!J50+0.5*Volume!H50 -> 7.60725 | K32: =0.5*Volume!K50+0.5*Volume!I50 -> 19.5615 | L32: =0.5*Volume!L50+0.5*Volume!J50 -> 19.5615 | M32: =0.5*Volume!M50+0.5*Volume!K50 -> 11.95425 | N32: =0.5*Volume!N50+0.5*Volume!L50 -> 23.9085 | ... S32: =0.5*Volume!S50+0.5*Volume!Q50 -> 23.9085
A33: Trainings to EAP clients + LPS / OJK (payday rule) | B33: Rp m | C33: =SUM(E33:G33) -> 0 | D33: =SUM(H33:S33) -> 118.902 | E33: =(PnL!E48+PnL!E49)*Inputs!$C$76 -> 0 | F33: =(PnL!F48+PnL!F49)*Inputs!$C$76+(PnL!E48+PnL!E49)*(1-Inputs!$C$76) -> 0 | G33: =(PnL!G48+PnL!G49)*Inputs!$C$76+(PnL!F48+PnL!F49)*(1-Inputs!$C$76) -> 0 | H33: =(PnL!H48+PnL!H49)*Inputs!$C$76+(PnL!G48+PnL!G49)*(1-Inputs!$C$76) -> 0 | I33: =(PnL!I48+PnL!I49)*Inputs!$C$76+(PnL!H48+PnL!H49)*(1-Inputs!$C$76) -> 0 | J33: =(PnL!J48+PnL!J49)*Inputs!$C$76+(PnL!I48+PnL!I49)*(1-Inputs!$C$76) -> 0 | K33: =(PnL!K48+PnL!K49)*Inputs!$C$76+(PnL!J48+PnL!J49)*(1-Inputs!$C$76) -> 0 | L33: =(PnL!L48+PnL!L49)*Inputs!$C$76+(PnL!K48+PnL!K49)*(1-Inputs!$C$76) -> 11.4 | M33: =(PnL!M48+PnL!M49)*Inputs!$C$76+(PnL!L48+PnL!L49)*(1-Inputs!$C$76) -> 8.55 | ... S33: =(PnL!S48+PnL!S49)*Inputs!$C$76+(PnL!R48+PnL!R49)*(1-Inputs!$C$76) -> 16.815
A34: Schools | B34: Rp m | C34: =SUM(E34:G34) -> 0 | D34: =SUM(H34:S34) -> 144 | E34: =PnL!E50*Inputs!$C$160 -> 0 | F34: =PnL!F50*Inputs!$C$160+PnL!E50*(1-Inputs!$C$160) -> 0 | G34: =PnL!G50*Inputs!$C$160+PnL!F50*(1-Inputs!$C$160) -> 0 | H34: =PnL!H50*Inputs!$C$160+PnL!G50*(1-Inputs!$C$160) -> 0 | I34: =PnL!I50*Inputs!$C$160+PnL!H50*(1-Inputs!$C$160) -> 12 | J34: =PnL!J50*Inputs!$C$160+PnL!I50*(1-Inputs!$C$160) -> 12 | K34: =PnL!K50*Inputs!$C$160+PnL!J50*(1-Inputs!$C$160) -> 0 | L34: =PnL!L50*Inputs!$C$160+PnL!K50*(1-Inputs!$C$160) -> 0 | M34: =PnL!M50*Inputs!$C$160+PnL!L50*(1-Inputs!$C$160) -> 0 | ... S34: =PnL!S50*Inputs!$C$160+PnL!R50*(1-Inputs!$C$160) -> 12
A35: Total v16 cash in (in row 11) | B35: Rp m | C35: =SUM(E35:G35) -> 7.60725 | D35: =SUM(H35:S35) -> 475.905 | E35: =SUM(E32:E34) -> 0 | F35: =SUM(F32:F34) -> 7.60725 | G35: =SUM(G32:G34) -> 0 | H35: =SUM(H32:H34) -> 7.60725 | I35: =SUM(I32:I34) -> 23.95425 | J35: =SUM(J32:J34) -> 19.60725 | K35: =SUM(K32:K34) -> 19.5615 | L35: =SUM(L32:L34) -> 30.9615 | ... S35: =SUM(S32:S34) -> 52.7235

Sheet To_Fill
A1: To fill: numbers we estimated - please replace with your real numbers
A2: How to use: write your real number in the yellow 'Your real number' column, then copy it into the blue cell named in 'Where to change it' on the Inputs sheet. The model updates everywhere.
A4: # | B4: Pillar | C4: Item | D4: Value used now | E4: Unit | F4: Why it matters | G4: Where to change it | H4: Your real number | I4: Status
A5: e.g. | B5: 2. Fixed cost | C5: Office rent (example row - do not edit) | D5: 5 | E5: Rp m / month | F5: Shows the format to use. | G5: Inputs!C? | H5: 5.5 | I5: Done
A6: 1 | B6: 1. Unit economics | C6: Client pays travel for regional events? (1 = yes, 0 = no) | D6: =Inputs!C22 -> 1 | E6: switch | F6: If you pay travel yourself, each KPW event loses about Rp 6m of its Rp 12m profit. | G6: Inputs!C22 | I6: Open
A7: 2 | B7: 1. Unit economics | C7: Travel cost per handler per regional trip | D7: =Inputs!C23 -> 3.5 | E7: Rp m / person | F7: Only used if the switch above is 0. | G7: Inputs!C23 | I7: Open
A8: 3 | B8: 1. Unit economics | C8: Share of KPW / LPS events outside Jakarta | D8: =Inputs!C24 -> 0.8 | E8: % | F8: Only used if you pay travel yourself. | G8: Inputs!C24 | I8: Open
A9: 4 | B9: 2. Capacity | C9: Days per Flagship event | D9: =Inputs!C30 -> 3 | E9: days | F9: Drives handler-days and how many facilitators you must certify. | G9: Inputs!C30 | I9: Open
A10: 5 | B10: 2. Capacity | C10: Days per KPW / LPS event | D10: =Inputs!C31 -> 1 | E10: days | F10: Drives handler-days. | G10: Inputs!C31 | I10: Open
A11: 6 | B11: 2. Capacity | C11: Days per KCP event | D11: =Inputs!C32 -> 1 | E11: days | F11: Drives handler-days. | G11: Inputs!C32 | I11: Open
A12: 7 | B12: 2. Capacity | C12: Days per B2C event | D12: =Inputs!C33 -> 1 | E12: days | F12: Drives handler-days. | G12: Inputs!C33 | I12: Open
A13: 8 | B13: 2. Capacity | C13: Cost to certify one new facilitator | D13: =Inputs!C37 -> 2.5 | E13: Rp m / person | F13: One-off cost each time the pool must grow. | G13: Inputs!C37 | I13: Open
A14: 9 | B14: 2. Fixed cost | C14: Accountant / tax consultant | D14: =Inputs!C47 -> 1.5 | E14: Rp m / month | F14: Bank and regulator vendors need clean books and tax filings. | G14: Inputs!C47 | I14: Open
A15: 10 | B15: 2. Fixed cost | C15: Founder salaries start month | D15: =Inputs!C51 -> Jan-27 | E15: month | F15: Earlier start = less cash buffer in Q1-Q2. | G15: Inputs!C51 | I15: Open
A16: 11 | B16: 2. Fixed cost | C16: B2B sales push start month (and AM start, if hired) | D16: =Inputs!C54 -> Jan-27 | E16: month | F16: Starts sales travel spending. | G16: Inputs!C54 | I16: Open
A17: 12 | B17: 1. Unit economics | C17: Sales travel and meetings (from sales start month) | D17: =Inputs!C55 -> 2 | E17: Rp m / month | F17: Main part of B2B customer acquisition cost. | G17: Inputs!C55 | I17: Open
A18: 13 | B18: 2. Capacity | C18: PM trigger: average B2B events per month (last 3 months) at or above | D18: =Inputs!C57 -> 4 | E18: events | F18: Decides when Rp 5m is added to fixed cost. | G18: Inputs!C57 | I18: Open
A19: 14 | B19: 2. Capacity | C19: Second admin trigger: invoices per month above | D19: =Inputs!C58 -> 12 | E19: invoices | F19: Decides when a second admin (same salary as admin) is added. | G19: Inputs!C58 | I19: Open
A20: 15 | B20: 2. Capacity | C20: Invoices per month from small corporate clients | D20: =Inputs!C59 -> 1.33 | E20: invoices | F20: Only affects the admin trigger. | G20: Inputs!C59 | I20: Open
A21: 16 | B21: 1. Unit economics | C21: Coreitera fee already inside the delivery costs above? (1 = yes) | D21: =Inputs!C61 -> 1 | E21: switch | F21: If it is not already inside, every event costs more. | G21: Inputs!C61 | I21: Open
A22: 17 | B22: 1. Unit economics | C22: Coreitera fee per assessment | D22: =Inputs!C62 -> 0.075 | E22: Rp m / participant | F22: This is Coreitera's revenue line for the investor story. | G22: Inputs!C62 | I22: Open
A23: 18 | B23: 1. Unit economics | C23: Participants per Flagship event | D23: =Inputs!C63 -> 40 | E23: people | F23: Number of Coreitera assessments sold per event. | G23: Inputs!C63 | I23: Open
A24: 19 | B24: 1. Unit economics | C24: Participants per KPW / LPS event | D24: =Inputs!C64 -> 30 | E24: people | F24: Number of Coreitera assessments sold per event. | G24: Inputs!C64 | I24: Open
A25: 20 | B25: 1. Unit economics | C25: Participants per KCP event | D25: =Inputs!C65 -> 40 | E25: people | F25: Number of Coreitera assessments sold per event. | G25: Inputs!C65 | I25: Open
A26: 21 | B26: 1. Unit economics | C26: Participants per B2C event | D26: =Inputs!C66 -> 50 | E26: people | F26: Number of Coreitera assessments sold per event. | G26: Inputs!C66 | I26: Open
A27: 22 | B27: 1. Unit economics | C27: Theta fee per counseling allocation | D27: =Inputs!C67 -> 0.05 | E27: Rp m / session | F27: This is Theta's revenue line for the investor story. | G27: Inputs!C67 | I27: Open
A28: 23 | B28: 1. Unit economics | C28: Counseling sessions per EAP contract per month | D28: =Inputs!C68 -> 10 | E28: sessions | F28: Theta volume from EAP. | G28: Inputs!C68 | I28: Open
A29: 24 | B29: 1. Unit economics | C29: New B2B clients won in 2027 (LPS, OJK, banks) | D29: =Inputs!C70 -> 4 | E29: clients | F29: Sales cost / new clients = cost to win one client. | G29: Inputs!C70 | I29: Open
A30: 25 | B30: 3. Cash | C30: BI central (Flagship): paid same month | D30: =Inputs!C73 -> 0.6 | E30: % | F30: Cash timing. | G30: Inputs!C73 | I30: Open
A31: 26 | B31: 3. Cash | C31: BI central (Flagship): paid after ~30 days | D31: =Inputs!C74 -> 0.3 | E31: % | F31: Cash timing. | G31: Inputs!C74 | I31: Open
A32: 27 | B32: 3. Cash | C32: BI central (Flagship): paid after ~60 days | D32: =Inputs!C75 -> 0.1 | E32: % | F32: Cash timing. | G32: Inputs!C75 | I32: Open
A33: 28 | B33: 3. Cash | C33: KPW / LPS: share of invoices sent before the payday cutoff | D33: =Inputs!C76 -> 0.8 | E33: % | F33: Sending invoices on time moves cash forward by one month. | G33: Inputs!C76 | I33: Open
A34: 29 | B34: 3. Cash | C34: Banks (KCP events): paid same month | D34: =Inputs!C77 -> 0.2 | E34: % | F34: Cash timing for new bank clients. | G34: Inputs!C77 | I34: Open
A35: 30 | B35: 3. Cash | C35: Banks (KCP events): paid after ~30 days | D35: =Inputs!C78 -> 0.5 | E35: % | F35: Cash timing for new bank clients. | G35: Inputs!C78 | I35: Open
A36: 31 | B36: 3. Cash | C36: Banks (KCP events): paid after ~60 days | D36: =Inputs!C79 -> 0.3 | E36: % | F36: Cash timing for new bank clients. | G36: Inputs!C79 | I36: Open
A37: 32 | B37: 3. Cash | C37: Income tax on revenue (final tax, PP 55/2022) | D37: =Inputs!C80 -> 0.005 | E37: % of revenue | F37: If you pay normal corporate tax instead, tax is on profit, not revenue. | G37: Inputs!C80 | I37: Open
A38: 33 | B38: Goal | C38: Target net profit margin for 2027 | D38: =Inputs!C82 -> 0.15 | E38: % | F38: Used for the pass / fail check on the Summary. | G38: Inputs!C82 | I38: Open
A39: 34 | B39: Goal | C39: Share of 'KPW and LPS' events that are BI (rest is LPS / OJK) | D39: =Inputs!C83 -> 0.85 | E39: % | F39: Measures how much revenue depends on BI. | G39: Inputs!C83 | I39: Open
A40: 35 | B40: Pricing | C40: New prices start month | D40: =Inputs!C86 -> Jan-27 | E40: month | F40: New prices should start with the new budget year. | G40: Inputs!C86 | I40: Open
A41: 36 | B41: Pricing | C41: New price: Flagship regulator ToT (3 days, training part) | D41: =Inputs!C87 -> 94 | E41: Rp m / program | F41: Biggest single regulator product. | G41: Inputs!C87 | I41: Open
A42: 37 | B42: Pricing | C42: New price: KPW / LPS regional ToT (1 day, training part) | D42: =Inputs!C88 -> 24 | E42: Rp m / event | F42: 17 events a year, so each Rp1m matters. | G42: Inputs!C88 | I42: Open
A43: 38 | B43: Pricing | C43: New price: state-owned bank, per group per day | D43: =Inputs!C89 -> 45 | E43: Rp m / day | F43: Price for BRI, Mandiri, BNI, BTN. | G43: Inputs!C89 | I43: Open
A44: 39 | B44: Pricing | C44: New price: private big bank, per group per day | D44: =Inputs!C90 -> 55 | E44: Rp m / day | F44: Price for BCA and other private banks. | G44: Inputs!C90 | I44: Open
A45: 40 | B45: Pricing | C45: Share of 2027 bank events with private banks | D45: =Inputs!C91 -> 0.25 | E45: % | F45: Mix between the two bank prices. | G45: Inputs!C91 | I45: Open
A46: 41 | B46: Pricing | C46: Assessment and impact report, price per participant | D46: =Inputs!C92 -> 0.15 | E46: Rp m / person | F46: New line item = new budget ceiling, and Coreitera revenue. | G46: Inputs!C92 | I46: Open
A47: 42 | B47: Pricing | C47: Sell assessment with bank events? (1 = yes) | D47: =Inputs!C95 -> 1 | E47: switch | F47: Adds about Rp6m per bank event. | G47: Inputs!C95 | I47: Open
A48: 43 | B48: Pricing | C48: Elite package uplift over Signature package | D48: =Inputs!C97 -> 0.3 | E48: % | F48: Sets the top package price for banks. | G48: Inputs!C97 | I48: Open
A49: 44 | B49: Pricing | C49: B2B volume kept after the price change | D49: =Inputs!C98 -> 1 | E49: % | F49: The main risk of any price rise. | G49: Inputs!C98 | I49: Open
A50: 45 | B50: 3. Cash | C50: Is the Rp 210m free cash? Any unpaid bills, or money clients still owe you? | D50: Assumed free | F50: Changes the starting cash. | G50: Inputs: Cash in bank | I50: Open
A51: 46 | B51: Volume | C51: Which Oct-Dec 2026 events are signed, and which are still hopes? | D51: v10 plan | F51: Q4 2026 is 3 of your 15 months. | G51: Volume sheet, blue rows | I51: Open
A52: 47 | B52: Volume | C52: Is the bank EAP contract live today? | D52: 1 contract all months | F52: Rp 10m profit per month. | G52: Volume sheet, EAP row | I52: Open
A53: 48 | B53: Pricing | C53: What would a bank pay per employee per month for EAP? | D53: Rp 15m per contract per month | F53: Needed to price EAP per employee, as the rate card suggests. | G53: Inputs: Prices | I53: Open
A54: 49 | B54: Pricing | C54: One real quote from a big trainer to a bank (day rate) | D54: 2.5x your old rate | F54: Checks the private-bank price. | G54: Inputs: Rate card | I54: Open
A55: 50 | B55: Volume | C55: Live talks with LPS, OJK or a bank: stage and likely close month? | D55: In v10 KPW/LPS row | F55: Tests if the 2027 volume is realistic. | G55: Volume sheet, blue rows | I55: Open
A56: 51 | B56: Timing | C56: First month new events are delivered | D56: =Inputs!C102 -> Mar-27 | F56: Decides how long we live on cash only. | G56: Inputs!C102 | I56: Open
A57: 52 | B57: Pay plan | C57: BPJS + THR on top of staff pay | D57: =Inputs!C106 -> 0.18 | F57: Cost of every pay step. | G57: Inputs!C106 | I57: Open
A58: 53 | B58: Pay plan | C58: Lead Partnership pay (Oct-27) | D58: =Inputs!C124 -> 6 | F58: Hiring step in Oct-27. | G58: Inputs!C124 | I58: Open
A59: 54 | B59: Growth plan | C59: EAP contract 2 and 3 start months | D59: =Inputs!C107 -> Feb-27 | F59: Main source of new monthly income. | G59: Inputs!C107 | I59: Open
A60: 55 | B60: Growth plan | C60: Sales co-founder cash pay and start | D60: =Inputs!C109 -> 8 | F60: Hiring step in Jul-27. | G60: Inputs!C109 | I60: Open
A61: 56 | B61: Growth plan | C61: Bank training days per month and start | D61: =Inputs!C112 -> 1 | F61: The swing factor for 2027. | G61: Inputs!C112 | I61: Open
A62: 57 | B62: Operations | C62: Project manager fee per project | D62: =Inputs!C114 -> 2 | F62: Cost of every B2B project. | G62: Inputs!C114 | I62: Open
